Workbook

Sheet Plan_Resumen
A1: Plan hacia US$ 1M de utilidad anual - resumen de escenarios
A2: Todo son formulas. Cambia los supuestos en Plan_Supuestos. La utilidad es antes de impuestos salvo que pongas una tasa. Canales propios (Shopify + WhatsApp).
A4: Resultado | B4: Conservador | C4: Base | D4: Ambicioso
A5: Gasto Meta al mes 24 (S/ por mes) | B5: =Plan_Conservador!Y7 -> 52843.173 | C5: =Plan_Base!Y7 -> 121971.13 | D5: =Plan_Ambicioso!Y7 -> 224023.12
A6: CAC al mes 24 (S/) | B6: =Plan_Conservador!Y9 -> 128.92008 | C6: =Plan_Base!Y9 -> 100.76932 | D6: =Plan_Ambicioso!Y9 -> 69.480805
A7: Pedidos nuevos por dia al mes 24 | B7: =Plan_Conservador!Y13 -> 15.029335 | C7: =Plan_Base!Y13 -> 46.398642 | D7: =Plan_Ambicioso!Y13 -> 128.96979
A8: Utilidad neta del mes 12 (S/) | B8: =Plan_Conservador!M32 -> 14614.332 | C8: =Plan_Base!M32 -> 63144.127 | D8: =Plan_Ambicioso!M32 -> 167097.6
A9: Utilidad neta del mes 24 (S/) | B9: =Plan_Conservador!Y32 -> 31686.001 | C9: =Plan_Base!Y32 -> 204344.81 | D9: =Plan_Ambicioso!Y32 -> 808547.35
A10: Utilidad de los ultimos 12 meses, mes 13 a 24 (US$) | B10: =Plan_Conservador!Y34/Plan_Supuestos!$B$13 -> 81761.522 | C10: =Plan_Base!Y34/Plan_Supuestos!$B$13 -> 451936.41 | D10: =Plan_Ambicioso!Y34/Plan_Supuestos!$B$13 -> 1554638.4
A11: Run-rate anual al mes 24 (US$) | B11: =Plan_Conservador!Y36 -> 108637.72 | C11: =Plan_Base!Y36 -> 700610.77 | D11: =Plan_Ambicioso!Y36 -> 2772162.4
A12: Utilidad acumulada en 24 meses (US$) | B12: =Plan_Conservador!Y33/Plan_Supuestos!$B$13 -> 107573.48 | C12: =Plan_Base!Y33/Plan_Supuestos!$B$13 -> 561797.75 | D12: =Plan_Ambicioso!Y33/Plan_Supuestos!$B$13 -> 1812790.2
A13: Primer mes con run-rate anual >= meta | B13: =IFERROR(MATCH(1,Plan_Conservador!B37:Y37,0),"no en 24 meses") -> no en 24 meses | C13: =IFERROR(MATCH(1,Plan_Base!B37:Y37,0),"no en 24 meses") -> no en 24 meses | D13: =IFERROR(MATCH(1,Plan_Ambicioso!B37:Y37,0),"no en 24 meses") -> 16
A14: Necesidad maxima de caja (S/) | B14: =-MIN(0,MIN(Plan_Conservador!B42:Y42)) -> 0 | C14: =-MIN(0,MIN(Plan_Base!B42:Y42)) -> 0 | D14: =-MIN(0,MIN(Plan_Ambicioso!B42:Y42)) -> 0
A16: Lectura: la meta es US$ 1M de utilidad al año. "Run-rate" = utilidad del mes x 12. Si el escenario no llega, la fila "Primer mes" dice "no en 24 meses".
A18: Que comprar en el proximo lote (escenario Base)
A19: Producto | B19: Demanda meses 5 a 10 (Mar-Ago 2027) | C19: Con colchon | D19: Stock actual | E19: A comprar | F19: Costo unitario puesto en Lima (S/) | G19: Capital (S/)
A20: Purificadores Nativo + Vivo | B20: =SUM(Plan_Base!F43:K43) -> 1494.7985 | C20: =B20*(1+$B$27) -> 1793.7582 | D20: 450 | E20: =MAX(0,C20-D20) -> 1343.7582 | F20: =Costo_Lima!F35 -> 22.419911 | G20: =E20*F20 -> 30126.939
A21: Repuestos de caño | B21: =SUM(Plan_Base!F44:K44) -> 1953.0325 | C21: =B21*(1+$B$27) -> 2343.6389 | D21: 600 | E21: =MAX(0,C21-D21) -> 1743.6389 | F21: =Costo_Lima!F36 -> 2.5165207 | G21: =E21*F21 -> 4387.9035
A22: Piezas Ritual | B22: =SUM(Plan_Base!F45:K45) -> 278.31055 | C22: =B22*(1+$B$27) -> 333.97266 | D22: 0 | E22: =MAX(0,C22-D22) -> 333.97266 | F22: =Costo_Lima!F37 -> 16.242997 | G22: =E22*F22 -> 5424.7169
A23: Bidon 22 L | B23: =SUM(Plan_Base!F46:K46) -> 146.11764 | C23: =B23*(1+$B$27) -> 175.34117 | D23: 804 | E23: =MAX(0,C23-D23) -> 0 | F23: =Contenedor2!F71 -> 47.548951 | G23: =E23*F23 -> 0
A24: Bidon 16 L | B24: =SUM(Plan_Base!F47:K47) -> 94.632956 | C24: =B24*(1+$B$27) -> 113.55955 | D24: 804 | E24: =MAX(0,C24-D24) -> 0 | F24: =Contenedor2!F72 -> 39.841592 | G24: =E24*F24 -> 0
A25: elvo· Cero | B25: =SUM(Plan_Base!F48:K48) -> 73.745846 | C25: =B25*(1+$B$27) -> 88.495016 | D25: 100 | E25: =MAX(0,C25-D25) -> 0 | F25: =Contenedor2!F74 -> 635.12307 | G25: =E25*F25 -> 0
A26: Total capital del lote | G26: =SUM(G20:G25) -> 39939.559
A27: Colchon sobre la demanda | B27: 0.2
A28: Stock actual: 450 purificadores y 600 repuestos (usuario); bidones, Cero y kits son los del contenedor que llega el 25-oct. Los bidones y el Cero ya estan comprados: cuentan como stock.
A29: La demanda de purificadores y repuestos sale de los pedidos del escenario Base; el tiempo de importacion es de ~4.5 meses, por eso este lote llega para marzo de 2027.

Sheet Plan_Supuestos
A1: Plan hacia US$ 1M de utilidad - supuestos (canales propios: Shopify y WhatsApp/YaVendio)
A2: Azul = supuesto editable; amarillo = el mas incierto. Verde = viene de las otras hojas. Los marketplaces van en otro analisis.
A4: General (igual en los tres escenarios) | B4: Valor | C4: Nota
A5: Pedidos nuevos por dia hoy | B5: 4.5 | C5: Sep-oct 2026: ~222 pedidos en 49 dias entre Shopify y YaVendio.
A6: Gasto Meta mensual hoy (S/) | B6: 9000 | C6: Sep-oct 2026: S/ 14.1k en 49 dias.
A7: Pedidos de base historica que generan recompra el primer año | B7: 60 | C7: SUPUESTO: clientes anteriores que aun renuevan.
A8: Pedidos de Lima (% del total) | B8: 0.75 | C8: Lima 80% de entrega y provincia con seña: el promedio de 85% implica ~25% provincia.
A9: Costos fijos al mes (S/) | B9: 15000 | C9: SUPUESTO: equipo, software, oficina. REEMPLAZAR con tus costos reales.
A10: Costo variable por pedido (S/) | B10: 8 | C10: SUPUESTO: atencion al cliente, operaciones, facturacion.
A11: Meses de cobertura de inventario | B11: 5 | C11: Tiempo de importacion: ~4.5 meses.
A12: Impuesto a la renta (0 = utilidad antes de impuestos) | B12: 0 | C12: Confirmar con tu contador.
A13: Tipo de cambio | B13: =Supuestos!B5 -> 3.5
A14: Meta de utilidad anual (US$) | B14: 1000000
A16: Escenarios | B16: Conservador | C16: Base | D16: Ambicioso | E16: Nota
A17: CAC inicial (S/ por pedido nuevo) | B17: 80 | C17: 65 | D17: 55 | E17: Real: sep S/ 54, oct S/ 81, promedio S/ 64.
A18: Elasticidad del CAC al gasto | B18: 0.35 | C18: 0.25 | D18: 0.15 | E18: Si el gasto se duplica, el CAC sube 2^e - 1 (e = 0.25: +19%). SUPUESTO clave.
A19: Crecimiento mensual del gasto en Meta | B19: 0.08 | C19: 0.12 | D19: 0.15
A20: Tope de gasto mensual (S/) | B20: 150000 | C20: 250000 | D20: 400000
A21: Mejora mensual del CAC por optimizacion | B21: 0.005 | C21: 0.01 | D21: 0.015 | E21: Mejores anuncios, seña, confirmacion de pedido.
A22: Tope de la mejora acumulada del CAC | B22: 0.15 | C22: 0.2 | D22: 0.25
A23: Pedidos organicos (% de los pagados) | B23: 0.1 | C23: 0.15 | D23: 0.2 | E23: Referidos, busqueda, recontacto.
A24: Recompra (% de los pedidos nuevos de hace 12 meses) | B24: 0.08 | C24: 0.12 | D24: 0.16 | E24: Repuestos de nucleo.
A25: Participacion del Cero en el mes 12 (% de pedidos) | B25: 0.04 | C25: 0.06 | D25: 0.08 | E25: SUPUESTO: depende de poder vender un producto de S/ 2,299 en WhatsApp.
A26: Mejora de entrega en Lima a los 6 meses (puntos) | B26: 0 | C26: 0.05 | D26: 0.1 | E26: Seña en Lima, confirmacion 24 h antes, The Hub.
A29: Producto | B29: Utilidad antes de publicidad Lima (S/) | C29: Utilidad antes de publicidad provincia (S/) | D29: Utilidad mezclada (S/) | E29: Margen por pedido entregado en Lima (S/) | F29: Costo de producto por pedido (S/) | G29: Mezcla de pedidos: mes 1 | H29: Mezcla de pedidos: mes 12 | I29: Repuestos de caño por pedido | J29: Piezas Ritual por pedido | K29: Factor de CAC vs Nativo | L29: Utilidad despues de publicidad (S/) | M29: Retorno por S/ 1 de publicidad
A30: Nativo (mezcla de planes) | B30: =$B$39*Resumen!C5+$B$40*Resumen!C6+$B$41*Resumen!C7 -> 194.50275 | C30: =$B$39*Resumen!F5+$B$40*Resumen!F6+$B$41*Resumen!F7 -> 258.12843 | D30: =$B$8*B30+(1-$B$8)*C30 -> 210.40917 | E30: =(B30+Supuestos!$B$16+Supuestos!$B$18)/Supuestos!$B$7 -> 263.12843 | F30: =-($B$39*Desglose!B15+$B$40*Desglose!C15+$B$41*Desglose!D15) -> 25.691388 | G30: =1-SUM(G31:G35) -> 0.82 | H30: Resto | I30: =$B$40*1+$B$41*3 -> 1.3 | J30: 0 | K30: 1 | L30: =D30-K30*$C$17 -> 145.40917 | M30: =IF(K30>0,D30/(K30*$C$17),"") -> 3.2370641
A31: Vivo 3 años | B31: =Resumen!C9 -> 126.45455 | C31: =Resumen!F9 -> 173.06819 | D31: =$B$8*B31+(1-$B$8)*C31 -> 138.10796 | E31: =(B31+Supuestos!$B$16+Supuestos!$B$18)/Supuestos!$B$7 -> 178.06819 | F31: =-Desglose!F15 -> 24.936432 | G31: 0.08 | H31: 0.05 | I31: 1 | J31: 0 | K31: 1 | L31: =D31-K31*$C$17 -> 73.107959 | M31: =IF(K31>0,D31/(K31*$C$17),"") -> 2.1247378
A32: Bidon 22 L | B32: =Contenedor2!B89 -> 88.749631 | C32: =Contenedor2!B89 -> 88.749631 | D32: =$B$8*B32+(1-$B$8)*C32 -> 88.749631 | E32: =(B32+Supuestos!$B$16+Supuestos!$B$18)/Supuestos!$B$7 -> 130.93704 | F32: =-Contenedor2!B82 -> 47.548951 | G32: 0.05 | H32: 0.1 | I32: 0 | J32: 0 | K32: 0.5 | L32: =D32-K32*$C$17 -> 56.249631 | M32: =IF(K32>0,D32/(K32*$C$17),"") -> 2.7307579
A33: Bidon 16 L | B33: =Contenedor2!C89 -> 55.685713 | C33: =Contenedor2!C89 -> 55.685713 | D33: =$B$8*B33+(1-$B$8)*C33 -> 55.685713 | E33: =(B33+Supuestos!$B$16+Supuestos!$B$18)/Supuestos!$B$7 -> 89.607141 | F33: =-Contenedor2!C82 -> 39.841592 | G33: 0.04 | H33: 0.06 | I33: 0 | J33: 0 | K33: 0.5 | L33: =D33-K33*$C$17 -> 23.185713 | M33: =IF(K33>0,D33/(K33*$C$17),"") -> 1.7134065
A34: elvo· Cero | B34: =Contenedor2!E89 -> 905.08895 | C34: =Contenedor2!E89 -> 905.08895 | D34: =$B$8*B34+(1-$B$8)*C34 -> 905.08895 | E34: =(B34+Supuestos!$B$16+Supuestos!$B$18)/Supuestos!$B$7 -> 1151.3612 | F34: =-Contenedor2!E82 -> 635.12307 | G34: 0.01 | H34: Segun escenario | I34: 0 | J34: 0 | K34: 2.5 | L34: =D34-K34*$C$17 -> 742.58895 | M34: =IF(K34>0,D34/(K34*$C$17),"") -> 5.5697781
A35: Ritual (venta aparte con publicidad) | B35: =Resumen!C13 -> 48.657997 | C35: =Resumen!F13 -> 75.822497 | D35: =$B$8*B35+(1-$B$8)*C35 -> 55.449122 | E35: =(B35+Supuestos!$B$16+Supuestos!$B$18)/Supuestos!$B$7 -> 80.822497 | F35: =-Desglose!J15 -> 64.971988 | G35: 0 | H35: 0 | I35: 0 | J35: 1 | K35: 1 | L35: =D35-K35*$C$17 -> -9.5508777 | M35: =IF(K35>0,D35/(K35*$C$17),"") -> 0.85306342
A36: Repuesto Nativo (recompra) | B36: =Resumen!C15 -> 111.69897 | C36: =Resumen!F15 -> 154.62372 | D36: =$B$8*B36+(1-$B$8)*C36 -> 122.43016 | E36: =(B36+Supuestos!$B$16+Supuestos!$B$18)/Supuestos!$B$7 -> 159.62372 | F36: =-Costo_Lima!F36 -> -2.5165207 | I36: 0 | J36: 0 | K36: Recompra: sin CAC
A37: Nativo: mezcla de planes en cada pedido nuevo. Cero y bidones usan el margen de Lima en todo el pais. El Ritual y el bidon de 16 L no rinden si se venden con publicidad a este CAC; el Ritual entra como venta cruzada en el mismo envio.
A38: Mezcla de planes Nativo
A39: Nativo 18 meses | B39: 0.1
A40: Nativo 3 años | B40: 0.7
A41: Nativo 6 años | B41: 0.2
A43: Venta cruzada de Ritual (% de pedidos nuevos): mes 1 | B43: 0.08 | C43: SUPUESTO. Ritual sin kit agregado a un pedido de Nativo: sin segundo envio ni segundo CAC.
A44: Venta cruzada de Ritual (% de pedidos nuevos): mes 12 | B44: 0.2
A45: Utilidad por Ritual vendido en el mismo envio (S/) | B45: =0.85*(Desglose!H14+Desglose!H15+Desglose!H16) -> 54.543206 | C45: Margen entregado del Ritual (sin kit) x 85% de entrega.
A48: Calculo del CAC con datos reales (Shopify + YaVendio vs Meta Ads)
B49: Septiembre | C49: Octubre (1-19) | D49: Total
A50: Gasto Meta (US$) | B50: 2229.52 | C50: 1806.51 | D50: =B50+C50 -> 4036.03
A51: Gasto Meta (S/) | B51: =B50*$B$13 -> 7803.32 | C51: =C50*$B$13 -> 6322.785 | D51: =B51+C51 -> 14126.105
A52: Pedidos en Shopify (analitica de ventas) | B52: 64 | C52: 29 | D52: =B52+C52 -> 93
A53: Pedidos en YaVendio (estimado por fechas) | B53: 103 | C53: 50 | D53: =B53+C53 -> 153
A54: Pedidos brutos (Shopify + YaVendio) | B54: =B52+B53 -> 167 | C54: =C52+C53 -> 79 | D54: =B54+C54 -> 246
A55: A descontar: reflejos de YaVendio en Shopify, pruebas y vencidos (estimado) | B55: 33 | C55: 11 | D55: =B55+C55 -> 44
A56: Pedidos depurados | B56: =B54-B55 -> 134 | C56: =C54-C55 -> 68 | D56: =B56+C56 -> 202
A57: Ventas realizadas (80% de los pedidos) | B57: 0.8 | C57: 0.8 | D57: 0.8
A58: CAC por pedido, bruto (S/) | B58: =B51/B54 -> 46.726467 | C58: =C51/C54 -> 80.035253 | D58: =D51/D54 -> 57.423191
A59: CAC por venta realizada, bruto (S/) | B59: =B58/B57 -> 58.408084 | C59: =C58/C57 -> 100.04407 | D59: =D58/D57 -> 71.778989
A60: CAC por pedido, depurado (S/) | B60: =B51/B56 -> 58.233731 | C60: =C51/C56 -> 92.982132 | D60: =D51/D56 -> 69.931213
A61: CAC por venta realizada, depurado (S/) | B61: =B60/B57 -> 72.792164 | C61: =C60/C57 -> 116.22767 | D61: =D60/D57 -> 87.414016
A62: El plan usa S/ 65 por pedido (punto medio entre el bruto y el depurado). Meta: cuenta 893663859368314. En Shopify, los pedidos con origen de la app de YaVendio son reflejos de pedidos de WhatsApp.
A63: Febrero-abril (solo bidones por WhatsApp): gasto US$ 4,149 y ~850 pedidos en YaVendio = unos S/ 21-23 por pedido, S/ 26-28 por venta realizada, con ticket de S/ 130-140.

Sheet Plan_Conservador
A1: Plan a 24 meses - escenario Conservador
A2: Todo son formulas a partir de Plan_Supuestos y de las hojas de costos. Mes 1 = noviembre 2026.
A4: Mes # | B4: 1 | C4: 2 | D4: 3 | E4: 4 | F4: 5 | G4: 6 | H4: 7 | I4: 8 | J4: 9 | K4: 10 | L4: 11 | M4: 12 | N4: 13 | O4: 14 | P4: 15 | Q4: 16 | R4: 17 | S4: 18 | T4: 19 | U4: 20 | V4: 21 | W4: 22 | X4: 23 | Y4: 24
A5: Mes | B5: Nov-26 | C5: Dic-26 | D5: Ene-27 | E5: Feb-27 | F5: Mar-27 | G5: Abr-27 | H5: May-27 | I5: Jun-27 | J5: Jul-27 | K5: Ago-27 | L5: Sep-27 | M5: Oct-27 | N5: Nov-27 | O5: Dic-27 | P5: Ene-28 | Q5: Feb-28 | R5: Mar-28 | S5: Abr-28 | T5: May-28 | U5: Jun-28 | V5: Jul-28 | W5: Ago-28 | X5: Sep-28 | Y5: Oct-28
A7: Gasto Meta (S/) | B7: =MIN(Plan_Supuestos!$B$20,Plan_Supuestos!$B$6*(1+Plan_Supuestos!$B$19)^(B$4-1)) -> 9000 | C7: =MIN(Plan_Supuestos!$B$20,Plan_Supuestos!$B$6*(1+Plan_Supuestos!$B$19)^(C$4-1)) -> 9720 | D7: =MIN(Plan_Supuestos!$B$20,Plan_Supuestos!$B$6*(1+Plan_Supuestos!$B$19)^(D$4-1)) -> 10497.6 | E7: =MIN(Plan_Supuestos!$B$20,Plan_Supuestos!$B$6*(1+Plan_Supuestos!$B$19)^(E$4-1)) -> 11337.408 | F7: =MIN(Plan_Supuestos!$B$20,Plan_Supuestos!$B$6*(1+Plan_Supuestos!$B$19)^(F$4-1)) -> 12244.401 | G7: =MIN(Plan_Supuestos!$B$20,Plan_Supuestos!$B$6*(1+Plan_Supuestos!$B$19)^(G$4-1)) -> 13223.953 | H7: =MIN(Plan_Supuestos!$B$20,Plan_Supuestos!$B$6*(1+Plan_Supuestos!$B$19)^(H$4-1)) -> 14281.869 | I7: =MIN(Plan_Supuestos!$B$20,Plan_Supuestos!$B$6*(1+Plan_Supuestos!$B$19)^(I$4-1)) -> 15424.418 | ... Y7: =MIN(Plan_Supuestos!$B$20,Plan_Supuestos!$B$6*(1+Plan_Supuestos!$B$19)^(Y$4-1)) -> 52843.173
A8: Mejora de CAC acumulada | B8: =MIN(Plan_Supuestos!$B$22,Plan_Supuestos!$B$21*(B$4-1)) -> 0 | C8: =MIN(Plan_Supuestos!$B$22,Plan_Supuestos!$B$21*(C$4-1)) -> 0.005 | D8: =MIN(Plan_Supuestos!$B$22,Plan_Supuestos!$B$21*(D$4-1)) -> 0.01 | E8: =MIN(Plan_Supuestos!$B$22,Plan_Supuestos!$B$21*(E$4-1)) -> 0.015 | F8: =MIN(Plan_Supuestos!$B$22,Plan_Supuestos!$B$21*(F$4-1)) -> 0.02 | G8: =MIN(Plan_Supuestos!$B$22,Plan_Supuestos!$B$21*(G$4-1)) -> 0.025 | H8: =MIN(Plan_Supuestos!$B$22,Plan_Supuestos!$B$21*(H$4-1)) -> 0.03 | I8: =MIN(Plan_Supuestos!$B$22,Plan_Supuestos!$B$21*(I$4-1)) -> 0.035 | ... Y8: =MIN(Plan_Supuestos!$B$22,Plan_Supuestos!$B$21*(Y$4-1)) -> 0.115
A9: CAC (S/ por pedido nuevo, segun mezcla) | B9: =Plan_Supuestos!$B$17*(B7/Plan_Supuestos!$B$6)^Plan_Supuestos!$B$18*(1-B8)*SUMPRODUCT(B17:B22,Plan_Supuestos!$K$30:$K$35) -> 77.6 | C9: =Plan_Supuestos!$B$17*(C7/Plan_Supuestos!$B$6)^Plan_Supuestos!$B$18*(1-C8)*SUMPRODUCT(C17:C22,Plan_Supuestos!$K$30:$K$35) -> 79.394414 | D9: =Plan_Supuestos!$B$17*(D7/Plan_Supuestos!$B$6)^Plan_Supuestos!$B$18*(1-D8)*SUMPRODUCT(D17:D22,Plan_Supuestos!$K$30:$K$35) -> 81.2282 | E9: =Plan_Supuestos!$B$17*(E7/Plan_Supuestos!$B$6)^Plan_Supuestos!$B$18*(1-E8)*SUMPRODUCT(E17:E22,Plan_Supuestos!$K$30:$K$35) -> 83.102149 | F9: =Plan_Supuestos!$B$17*(F7/Plan_Supuestos!$B$6)^Plan_Supuestos!$B$18*(1-F8)*SUMPRODUCT(F17:F22,Plan_Supuestos!$K$30:$K$35) -> 85.017065 | G9: =Plan_Supuestos!$B$17*(G7/Plan_Supuestos!$B$6)^Plan_Supuestos!$B$18*(1-G8)*SUMPRODUCT(G17:G22,Plan_Supuestos!$K$30:$K$35) -> 86.973766 | H9: =Plan_Supuestos!$B$17*(H7/Plan_Supuestos!$B$6)^Plan_Supuestos!$B$18*(1-H8)*SUMPRODUCT(H17:H22,Plan_Supuestos!$K$30:$K$35) -> 88.973084 | I9: =Plan_Supuestos!$B$17*(I7/Plan_Supuestos!$B$6)^Plan_Supuestos!$B$18*(1-I8)*SUMPRODUCT(I17:I22,Plan_Supuestos!$K$30:$K$35) -> 91.015864 | ... Y9: =Plan_Supuestos!$B$17*(Y7/Plan_Supuestos!$B$6)^Plan_Supuestos!$B$18*(1-Y8)*SUMPRODUCT(Y17:Y22,Plan_Supuestos!$K$30:$K$35) -> 128.92008
A10: Pedidos pagados | B10: =B7/B9 -> 115.97938 | C10: =C7/C9 -> 122.42675 | D10: =D7/D9 -> 129.23591 | E10: =E7/E9 -> 136.42737 | F10: =F7/F9 -> 144.02286 | G10: =G7/G9 -> 152.0453 | H10: =H7/H9 -> 160.51898 | I10: =I7/I9 -> 169.46956 | ... Y10: =Y7/Y9 -> 409.89094
A11: Pedidos organicos | B11: =B10*Plan_Supuestos!$B$23 -> 11.597938 | C11: =C10*Plan_Supuestos!$B$23 -> 12.242675 | D11: =D10*Plan_Supuestos!$B$23 -> 12.923591 | E11: =E10*Plan_Supuestos!$B$23 -> 13.642737 | F11: =F10*Plan_Supuestos!$B$23 -> 14.402286 | G11: =G10*Plan_Supuestos!$B$23 -> 15.20453 | H11: =H10*Plan_Supuestos!$B$23 -> 16.051898 | I11: =I10*Plan_Supuestos!$B$23 -> 16.946956 | ... Y11: =Y10*Plan_Supuestos!$B$23 -> 40.989094
A12: Pedidos nuevos | B12: =B10+B11 -> 127.57732 | C12: =C10+C11 -> 134.66942 | D12: =D10+D11 -> 142.1595 | E12: =E10+E11 -> 150.07011 | F12: =F10+F11 -> 158.42514 | G12: =G10+G11 -> 167.24983 | H12: =H10+H11 -> 176.57088 | I12: =I10+I11 -> 186.41652 | ... Y12: =Y10+Y11 -> 450.88004
A13: Pedidos nuevos por dia | B13: =B12/30 -> 4.2525773 | C13: =C12/30 -> 4.4889808 | D13: =D12/30 -> 4.7386499 | E13: =E12/30 -> 5.0023371 | F13: =F12/30 -> 5.2808381 | G13: =G12/30 -> 5.5749945 | H13: =H12/30 -> 5.885696 | I13: =I12/30 -> 6.2138838 | ... Y13: =Y12/30 -> 15.029335
A14: Pedidos de recompra | B14: =Plan_Supuestos!$B$24*IF(B$4>12,INDEX($B12:$Y12,B$4-12),Plan_Supuestos!$B$7) -> 4.8 | C14: =Plan_Supuestos!$B$24*IF(C$4>12,INDEX($B12:$Y12,C$4-12),Plan_Supuestos!$B$7) -> 4.8 | D14: =Plan_Supuestos!$B$24*IF(D$4>12,INDEX($B12:$Y12,D$4-12),Plan_Supuestos!$B$7) -> 4.8 | E14: =Plan_Supuestos!$B$24*IF(E$4>12,INDEX($B12:$Y12,E$4-12),Plan_Supuestos!$B$7) -> 4.8 | F14: =Plan_Supuestos!$B$24*IF(F$4>12,INDEX($B12:$Y12,F$4-12),Plan_Supuestos!$B$7) -> 4.8 | G14: =Plan_Supuestos!$B$24*IF(G$4>12,INDEX($B12:$Y12,G$4-12),Plan_Supuestos!$B$7) -> 4.8 | H14: =Plan_Supuestos!$B$24*IF(H$4>12,INDEX($B12:$Y12,H$4-12),Plan_Supuestos!$B$7) -> 4.8 | I14: =Plan_Supuestos!$B$24*IF(I$4>12,INDEX($B12:$Y12,I$4-12),Plan_Supuestos!$B$7) -> 4.8 | ... Y14: =Plan_Supuestos!$B$24*IF(Y$4>12,INDEX($B12:$Y12,Y$4-12),Plan_Supuestos!$B$7) -> 18.533488
A15: Pedidos totales | B15: =B12+B14 -> 132.37732 | C15: =C12+C14 -> 139.46942 | D15: =D12+D14 -> 146.9595 | E15: =E12+E14 -> 154.87011 | F15: =F12+F14 -> 163.22514 | G15: =G12+G14 -> 172.04983 | H15: =H12+H14 -> 181.37088 | I15: =I12+I14 -> 191.21652 | ... Y15: =Y12+Y14 -> 469.41352
A16: Avance de la transicion de mezcla | B16: =MIN(1,(B$4-1)/11) -> 0 | C16: =MIN(1,(C$4-1)/11) -> 0.090909091 | D16: =MIN(1,(D$4-1)/11) -> 0.18181818 | E16: =MIN(1,(E$4-1)/11) -> 0.27272727 | F16: =MIN(1,(F$4-1)/11) -> 0.36363636 | G16: =MIN(1,(G$4-1)/11) -> 0.45454545 | H16: =MIN(1,(H$4-1)/11) -> 0.54545455 | I16: =MIN(1,(I$4-1)/11) -> 0.63636364 | ... Y16: =MIN(1,(Y$4-1)/11) -> 1
A17: Mezcla: Nativo | B17: =1-SUM(B18:B22) -> 0.82 | C17: =1-SUM(C18:C22) -> 0.81363636 | D17: =1-SUM(D18:D22) -> 0.80727273 | E17: =1-SUM(E18:E22) -> 0.80090909 | F17: =1-SUM(F18:F22) -> 0.79454545 | G17: =1-SUM(G18:G22) -> 0.78818182 | H17: =1-SUM(H18:H22) -> 0.78181818 | I17: =1-SUM(I18:I22) -> 0.77545455 | ... Y17: =1-SUM(Y18:Y22) -> 0.75
A18: Mezcla: Vivo | B18: =Plan_Supuestos!$G$31+(Plan_Supuestos!$H$31-Plan_Supuestos!$G$31)*B16 -> 0.08 | C18: =Plan_Supuestos!$G$31+(Plan_Supuestos!$H$31-Plan_Supuestos!$G$31)*C16 -> 0.077272727 | D18: =Plan_Supuestos!$G$31+(Plan_Supuestos!$H$31-Plan_Supuestos!$G$31)*D16 -> 0.074545455 | E18: =Plan_Supuestos!$G$31+(Plan_Supuestos!$H$31-Plan_Supuestos!$G$31)*E16 -> 0.071818182 | F18: =Plan_Supuestos!$G$31+(Plan_Supuestos!$H$31-Plan_Supuestos!$G$31)*F16 -> 0.069090909 | G18: =Plan_Supuestos!$G$31+(Plan_Supuestos!$H$31-Plan_Supuestos!$G$31)*G16 -> 0.066363636 | H18: =Plan_Supuestos!$G$31+(Plan_Supuestos!$H$31-Plan_Supuestos!$G$31)*H16 -> 0.063636364 | I18: =Plan_Supuestos!$G$31+(Plan_Supuestos!$H$31-Plan_Supuestos!$G$31)*I16 -> 0.060909091 | ... Y18: =Plan_Supuestos!$G$31+(Plan_Supuestos!$H$31-Plan_Supuestos!$G$31)*Y16 -> 0.05
A19: Mezcla: Bidon 22 L | B19: =Plan_Supuestos!$G$32+(Plan_Supuestos!$H$32-Plan_Supuestos!$G$32)*B16 -> 0.05 | C19: =Plan_Supuestos!$G$32+(Plan_Supuestos!$H$32-Plan_Supuestos!$G$32)*C16 -> 0.054545455 | D19: =Plan_Supuestos!$G$32+(Plan_Supuestos!$H$32-Plan_Supuestos!$G$32)*D16 -> 0.059090909 | E19: =Plan_Supuestos!$G$32+(Plan_Supuestos!$H$32-Plan_Supuestos!$G$32)*E16 -> 0.063636364 | F19: =Plan_Supuestos!$G$32+(Plan_Supuestos!$H$32-Plan_Supuestos!$G$32)*F16 -> 0.068181818 | G19: =Plan_Supuestos!$G$32+(Plan_Supuestos!$H$32-Plan_Supuestos!$G$32)*G16 -> 0.072727273 | H19: =Plan_Supuestos!$G$32+(Plan_Supuestos!$H$32-Plan_Supuestos!$G$32)*H16 -> 0.077272727 | I19: =Plan_Supuestos!$G$32+(Plan_Supuestos!$H$32-Plan_Supuestos!$G$32)*I16 -> 0.081818182 | ... Y19: =Plan_Supuestos!$G$32+(Plan_Supuestos!$H$32-Plan_Supuestos!$G$32)*Y16 -> 0.1
A20: Mezcla: Bidon 16 L | B20: =Plan_Supuestos!$G$33+(Plan_Supuestos!$H$33-Plan_Supuestos!$G$33)*B16 -> 0.04 | C20: =Plan_Supuestos!$G$33+(Plan_Supuestos!$H$33-Plan_Supuestos!$G$33)*C16 -> 0.041818182 | D20: =Plan_Supuestos!$G$33+(Plan_Supuestos!$H$33-Plan_Supuestos!$G$33)*D16 -> 0.043636364 | E20: =Plan_Supuestos!$G$33+(Plan_Supuestos!$H$33-Plan_Supuestos!$G$33)*E16 -> 0.045454545 | F20: =Plan_Supuestos!$G$33+(Plan_Supuestos!$H$33-Plan_Supuestos!$G$33)*F16 -> 0.047272727 | G20: =Plan_Supuestos!$G$33+(Plan_Supuestos!$H$33-Plan_Supuestos!$G$33)*G16 -> 0.049090909 | H20: =Plan_Supuestos!$G$33+(Plan_Supuestos!$H$33-Plan_Supuestos!$G$33)*H16 -> 0.050909091 | I20: =Plan_Supuestos!$G$33+(Plan_Supuestos!$H$33-Plan_Supuestos!$G$33)*I16 -> 0.052727273 | ... Y20: =Plan_Supuestos!$G$33+(Plan_Supuestos!$H$33-Plan_Supuestos!$G$33)*Y16 -> 0.06
A21: Mezcla: Cero | B21: =Plan_Supuestos!$G$34+(Plan_Supuestos!$B$25-Plan_Supuestos!$G$34)*B16 -> 0.01 | C21: =Plan_Supuestos!$G$34+(Plan_Supuestos!$B$25-Plan_Supuestos!$G$34)*C16 -> 0.012727273 | D21: =Plan_Supuestos!$G$34+(Plan_Supuestos!$B$25-Plan_Supuestos!$G$34)*D16 -> 0.015454545 | E21: =Plan_Supuestos!$G$34+(Plan_Supuestos!$B$25-Plan_Supuestos!$G$34)*E16 -> 0.018181818 | F21: =Plan_Supuestos!$G$34+(Plan_Supuestos!$B$25-Plan_Supuestos!$G$34)*F16 -> 0.020909091 | G21: =Plan_Supuestos!$G$34+(Plan_Supuestos!$B$25-Plan_Supuestos!$G$34)*G16 -> 0.023636364 | H21: =Plan_Supuestos!$G$34+(Plan_Supuestos!$B$25-Plan_Supuestos!$G$34)*H16 -> 0.026363636 | I21: =Plan_Supuestos!$G$34+(Plan_Supuestos!$B$25-Plan_Supuestos!$G$34)*I16 -> 0.029090909 | ... Y21: =Plan_Supuestos!$G$34+(Plan_Supuestos!$B$25-Plan_Supuestos!$G$34)*Y16 -> 0.04
A22: Mezcla: Ritual (venta aparte) | B22: =Plan_Supuestos!$G$35+(Plan_Supuestos!$H$35-Plan_Supuestos!$G$35)*B16 -> 0 | C22: =Plan_Supuestos!$G$35+(Plan_Supuestos!$H$35-Plan_Supuestos!$G$35)*C16 -> 0 | D22: =Plan_Supuestos!$G$35+(Plan_Supuestos!$H$35-Plan_Supuestos!$G$35)*D16 -> 0 | E22: =Plan_Supuestos!$G$35+(Plan_Supuestos!$H$35-Plan_Supuestos!$G$35)*E16 -> 0 | F22: =Plan_Supuestos!$G$35+(Plan_Supuestos!$H$35-Plan_Supuestos!$G$35)*F16 -> 0 | G22: =Plan_Supuestos!$G$35+(Plan_Supuestos!$H$35-Plan_Supuestos!$G$35)*G16 -> 0 | H22: =Plan_Supuestos!$G$35+(Plan_Supuestos!$H$35-Plan_Supuestos!$G$35)*H16 -> 0 | I22: =Plan_Supuestos!$G$35+(Plan_Supuestos!$H$35-Plan_Supuestos!$G$35)*I16 -> 0 | ... Y22: =Plan_Supuestos!$G$35+(Plan_Supuestos!$H$35-Plan_Supuestos!$G$35)*Y16 -> 0
A23: Utilidad por pedido nuevo antes de publicidad (S/) | B23: =SUMPRODUCT(B17:B22,Plan_Supuestos!$D$30:$D$35)+(Plan_Supuestos!$B$43+(Plan_Supuestos!$B$44-Plan_Supuestos!$B$43)*B16)*Plan_Supuestos!$B$45 -> 203.66341 | C23: =SUMPRODUCT(C17:C22,Plan_Supuestos!$D$30:$D$35)+(Plan_Supuestos!$B$43+(Plan_Supuestos!$B$44-Plan_Supuestos!$B$43)*C16)*Plan_Supuestos!$B$45 -> 205.51588 | D23: =SUMPRODUCT(D17:D22,Plan_Supuestos!$D$30:$D$35)+(Plan_Supuestos!$B$43+(Plan_Supuestos!$B$44-Plan_Supuestos!$B$43)*D16)*Plan_Supuestos!$B$45 -> 207.36835 | E23: =SUMPRODUCT(E17:E22,Plan_Supuestos!$D$30:$D$35)+(Plan_Supuestos!$B$43+(Plan_Supuestos!$B$44-Plan_Supuestos!$B$43)*E16)*Plan_Supuestos!$B$45 -> 209.22082 | F23: =SUMPRODUCT(F17:F22,Plan_Supuestos!$D$30:$D$35)+(Plan_Supuestos!$B$43+(Plan_Supuestos!$B$44-Plan_Supuestos!$B$43)*F16)*Plan_Supuestos!$B$45 -> 211.07329 | G23: =SUMPRODUCT(G17:G22,Plan_Supuestos!$D$30:$D$35)+(Plan_Supuestos!$B$43+(Plan_Supuestos!$B$44-Plan_Supuestos!$B$43)*G16)*Plan_Supuestos!$B$45 -> 212.92576 | H23: =SUMPRODUCT(H17:H22,Plan_Supuestos!$D$30:$D$35)+(Plan_Supuestos!$B$43+(Plan_Supuestos!$B$44-Plan_Supuestos!$B$43)*H16)*Plan_Supuestos!$B$45 -> 214.77823 | I23: =SUMPRODUCT(I17:I22,Plan_Supuestos!$D$30:$D$35)+(Plan_Supuestos!$B$43+(Plan_Supuestos!$B$44-Plan_Supuestos!$B$43)*I16)*Plan_Supuestos!$B$45 -> 216.6307 | ... Y23: =SUMPRODUCT(Y17:Y22,Plan_Supuestos!$D$30:$D$35)+(Plan_Supuestos!$B$43+(Plan_Supuestos!$B$44-Plan_Supuestos!$B$43)*Y16)*Plan_Supuestos!$B$45 -> 224.04058
A24: Mejora por entrega en Lima por pedido (S/) | B24: =Plan_Supuestos!$B$26*MIN(1,B$4/6)*Plan_Supuestos!$B$8*SUMPRODUCT(B17:B22,Plan_Supuestos!$E$30:$E$35) -> 0 | C24: =Plan_Supuestos!$B$26*MIN(1,C$4/6)*Plan_Supuestos!$B$8*SUMPRODUCT(C17:C22,Plan_Supuestos!$E$30:$E$35) -> 0 | D24: =Plan_Supuestos!$B$26*MIN(1,D$4/6)*Plan_Supuestos!$B$8*SUMPRODUCT(D17:D22,Plan_Supuestos!$E$30:$E$35) -> 0 | E24: =Plan_Supuestos!$B$26*MIN(1,E$4/6)*Plan_Supuestos!$B$8*SUMPRODUCT(E17:E22,Plan_Supuestos!$E$30:$E$35) -> 0 | F24: =Plan_Supuestos!$B$26*MIN(1,F$4/6)*Plan_Supuestos!$B$8*SUMPRODUCT(F17:F22,Plan_Supuestos!$E$30:$E$35) -> 0 | G24: =Plan_Supuestos!$B$26*MIN(1,G$4/6)*Plan_Supuestos!$B$8*SUMPRODUCT(G17:G22,Plan_Supuestos!$E$30:$E$35) -> 0 | H24: =Plan_Supuestos!$B$26*MIN(1,H$4/6)*Plan_Supuestos!$B$8*SUMPRODUCT(H17:H22,Plan_Supuestos!$E$30:$E$35) -> 0 | I24: =Plan_Supuestos!$B$26*MIN(1,I$4/6)*Plan_Supuestos!$B$8*SUMPRODUCT(I17:I22,Plan_Supuestos!$E$30:$E$35) -> 0 | ... Y24: =Plan_Supuestos!$B$26*MIN(1,Y$4/6)*Plan_Supuestos!$B$8*SUMPRODUCT(Y17:Y22,Plan_Supuestos!$E$30:$E$35) -> 0
A25: Utilidad pedidos nuevos antes de publicidad | B25: =B12*(B23+B24) -> 25982.832 | C25: =C12*(C23+C24) -> 27676.705 | D25: =D12*(D23+D24) -> 29479.38 | E25: =E12*(E23+E24) -> 31397.792 | F25: =F12*(F23+F24) -> 33439.316 | G25: =G12*(G23+G24) -> 35611.798 | H25: =H12*(H23+H24) -> 37923.581 | I25: =I12*(I23+I24) -> 40383.54 | ... Y25: =Y12*(Y23+Y24) -> 101015.42
A26: Utilidad recompra | B26: =B14*Plan_Supuestos!$D$36 -> 587.66477 | C26: =C14*Plan_Supuestos!$D$36 -> 587.66477 | D26: =D14*Plan_Supuestos!$D$36 -> 587.66477 | E26: =E14*Plan_Supuestos!$D$36 -> 587.66477 | F26: =F14*Plan_Supuestos!$D$36 -> 587.66477 | G26: =G14*Plan_Supuestos!$D$36 -> 587.66477 | H26: =H14*Plan_Supuestos!$D$36 -> 587.66477 | I26: =I14*Plan_Supuestos!$D$36 -> 587.66477 | ... Y26: =Y14*Plan_Supuestos!$D$36 -> 2269.0579
A27: Gasto Meta | B27: =-B7 -> -9000 | C27: =-C7 -> -9720 | D27: =-D7 -> -10497.6 | E27: =-E7 -> -11337.408 | F27: =-F7 -> -12244.401 | G27: =-G7 -> -13223.953 | H27: =-H7 -> -14281.869 | I27: =-I7 -> -15424.418 | ... Y27: =-Y7 -> -52843.173
A28: Utilidad despues de publicidad | B28: =B25+B26+B27 -> 17570.497 | C28: =C25+C26+C27 -> 18544.37 | D28: =D25+D26+D27 -> 19569.445 | E28: =E25+E26+E27 -> 20648.049 | F28: =F25+F26+F27 -> 21782.58 | G28: =G25+G26+G27 -> 22975.51 | H28: =H25+H26+H27 -> 24229.377 | I28: =I25+I26+I27 -> 25546.786 | ... Y28: =Y25+Y26+Y27 -> 50441.309
A29: Costos fijos y variables | B29: =-(Plan_Supuestos!$B$9+Plan_Supuestos!$B$10*B15) -> -16059.019 | C29: =-(Plan_Supuestos!$B$9+Plan_Supuestos!$B$10*C15) -> -16115.755 | D29: =-(Plan_Supuestos!$B$9+Plan_Supuestos!$B$10*D15) -> -16175.676 | E29: =-(Plan_Supuestos!$B$9+Plan_Supuestos!$B$10*E15) -> -16238.961 | F29: =-(Plan_Supuestos!$B$9+Plan_Supuestos!$B$10*F15) -> -16305.801 | G29: =-(Plan_Supuestos!$B$9+Plan_Supuestos!$B$10*G15) -> -16376.399 | H29: =-(Plan_Supuestos!$B$9+Plan_Supuestos!$B$10*H15) -> -16450.967 | I29: =-(Plan_Supuestos!$B$9+Plan_Supuestos!$B$10*I15) -> -16529.732 | ... Y29: =-(Plan_Supuestos!$B$9+Plan_Supuestos!$B$10*Y15) -> -18755.308
A30: Utilidad antes de impuestos | B30: =B28+B29 -> 1511.4781 | C30: =C28+C29 -> 2428.6143 | D30: =D28+D29 -> 3393.7688 | E30: =E28+E29 -> 4409.0877 | F30: =F28+F29 -> 5476.7792 | G30: =G28+G29 -> 6599.1114 | H30: =H28+H29 -> 7778.4098 | I30: =I28+I29 -> 9017.0542 | ... Y30: =Y28+Y29 -> 31686.001
A31: Impuesto | B31: =-MAX(0,B30)*Plan_Supuestos!$B$12 -> 0 | C31: =-MAX(0,C30)*Plan_Supuestos!$B$12 -> 0 | D31: =-MAX(0,D30)*Plan_Supuestos!$B$12 -> 0 | E31: =-MAX(0,E30)*Plan_Supuestos!$B$12 -> 0 | F31: =-MAX(0,F30)*Plan_Supuestos!$B$12 -> 0 | G31: =-MAX(0,G30)*Plan_Supuestos!$B$12 -> 0 | H31: =-MAX(0,H30)*Plan_Supuestos!$B$12 -> 0 | I31: =-MAX(0,I30)*Plan_Supuestos!$B$12 -> 0 | ... Y31: =-MAX(0,Y30)*Plan_Supuestos!$B$12 -> 0
A32: UTILIDAD NETA DEL MES | B32: =B30+B31 -> 1511.4781 | C32: =C30+C31 -> 2428.6143 | D32: =D30+D31 -> 3393.7688 | E32: =E30+E31 -> 4409.0877 | F32: =F30+F31 -> 5476.7792 | G32: =G30+G31 -> 6599.1114 | H32: =H30+H31 -> 7778.4098 | I32: =I30+I31 -> 9017.0542 | ... Y32: =Y30+Y31 -> 31686.001
A33: Utilidad acumulada | B33: =B32 -> 1511.4781 | C33: =B33+C32 -> 3940.0925 | D33: =C33+D32 -> 7333.8613 | E33: =D33+E32 -> 11742.949 | F33: =E33+F32 -> 17219.728 | G33: =F33+G32 -> 23818.84 | H33: =G33+H32 -> 31597.249 | I33: =H33+I32 -> 40614.304 | J33: =I33+J32 -> 50931.778 | ... Y33: =X33+Y32 -> 376507.16
A34: Utilidad ultimos 12 meses | M34: =SUM(B32:M32) -> 90341.838 | N34: =SUM(C32:N32) -> 105231.83 | O34: =SUM(D32:O32) -> 120467.37 | P34: =SUM(E32:P32) -> 136032.11 | Q34: =SUM(F32:Q32) -> 151906.21 | R34: =SUM(G32:R32) -> 168065.96 | S34: =SUM(H32:S32) -> 184483.36 | T34: =SUM(I32:T32) -> 201125.69 | ... Y34: =SUM(N32:Y32) -> 286165.33
A35: Run-rate anual (mes x 12) (S/) | B35: =B32*12 -> 18137.737 | C35: =C32*12 -> 29143.372 | D35: =D32*12 -> 40725.226 | E35: =E32*12 -> 52909.053 | F35: =F32*12 -> 65721.35 | G35: =G32*12 -> 79189.336 | H35: =H32*12 -> 93340.918 | I35: =I32*12 -> 108204.65 | ... Y35: =Y32*12 -> 380232.01
A36: Run-rate anual (US$) | B36: =B35/Plan_Supuestos!$B$13 -> 5182.2106 | C36: =C35/Plan_Supuestos!$B$13 -> 8326.6778 | D36: =D35/Plan_Supuestos!$B$13 -> 11635.779 | E36: =E35/Plan_Supuestos!$B$13 -> 15116.872 | F36: =F35/Plan_Supuestos!$B$13 -> 18777.529 | G36: =G35/Plan_Supuestos!$B$13 -> 22625.525 | H36: =H35/Plan_Supuestos!$B$13 -> 26668.834 | I36: =I35/Plan_Supuestos!$B$13 -> 30915.614 | ... Y36: =Y35/Plan_Supuestos!$B$13 -> 108637.72
A37: ¿Run-rate supera la meta? (1 = si) | B37: =IF(B36>=Plan_Supuestos!$B$14,1,0) -> 0 | C37: =IF(C36>=Plan_Supuestos!$B$14,1,0) -> 0 | D37: =IF(D36>=Plan_Supuestos!$B$14,1,0) -> 0 | E37: =IF(E36>=Plan_Supuestos!$B$14,1,0) -> 0 | F37: =IF(F36>=Plan_Supuestos!$B$14,1,0) -> 0 | G37: =IF(G36>=Plan_Supuestos!$B$14,1,0) -> 0 | H37: =IF(H36>=Plan_Supuestos!$B$14,1,0) -> 0 | I37: =IF(I36>=Plan_Supuestos!$B$14,1,0) -> 0 | ... Y37: =IF(Y36>=Plan_Supuestos!$B$14,1,0) -> 0
A38: Costo de producto del mes | B38: =B12*(Plan_Supuestos!$B$8*Supuestos!$B$7+(1-Plan_Supuestos!$B$8)*Supuestos!$B$8)*SUMPRODUCT(B17:B22,Plan_Supuestos!$F$30:$F$35)+B14*Plan_Supuestos!$F$36 -> 3608.1269 | C38: =C12*(Plan_Supuestos!$B$8*Supuestos!$B$7+(1-Plan_Supuestos!$B$8)*Supuestos!$B$8)*SUMPRODUCT(C17:C22,Plan_Supuestos!$F$30:$F$35)+C14*Plan_Supuestos!$F$36 -> 4014.1873 | D38: =D12*(Plan_Supuestos!$B$8*Supuestos!$B$7+(1-Plan_Supuestos!$B$8)*Supuestos!$B$8)*SUMPRODUCT(D17:D22,Plan_Supuestos!$F$30:$F$35)+D14*Plan_Supuestos!$F$36 -> 4454.3232 | E38: =E12*(Plan_Supuestos!$B$8*Supuestos!$B$7+(1-Plan_Supuestos!$B$8)*Supuestos!$B$8)*SUMPRODUCT(E17:E22,Plan_Supuestos!$F$30:$F$35)+E14*Plan_Supuestos!$F$36 -> 4931.0938 | F38: =F12*(Plan_Supuestos!$B$8*Supuestos!$B$7+(1-Plan_Supuestos!$B$8)*Supuestos!$B$8)*SUMPRODUCT(F17:F22,Plan_Supuestos!$F$30:$F$35)+F14*Plan_Supuestos!$F$36 -> 5447.2405 | G38: =G12*(Plan_Supuestos!$B$8*Supuestos!$B$7+(1-Plan_Supuestos!$B$8)*Supuestos!$B$8)*SUMPRODUCT(G17:G22,Plan_Supuestos!$F$30:$F$35)+G14*Plan_Supuestos!$F$36 -> 6005.6993 | H38: =H12*(Plan_Supuestos!$B$8*Supuestos!$B$7+(1-Plan_Supuestos!$B$8)*Supuestos!$B$8)*SUMPRODUCT(H17:H22,Plan_Supuestos!$F$30:$F$35)+H14*Plan_Supuestos!$F$36 -> 6609.6141 | I38: =I12*(Plan_Supuestos!$B$8*Supuestos!$B$7+(1-Plan_Supuestos!$B$8)*Supuestos!$B$8)*SUMPRODUCT(I17:I22,Plan_Supuestos!$F$30:$F$35)+I14*Plan_Supuestos!$F$36 -> 7262.3513 | ... Y38: =Y12*(Plan_Supuestos!$B$8*Supuestos!$B$7+(1-Plan_Supuestos!$B$8)*Supuestos!$B$8)*SUMPRODUCT(Y17:Y22,Plan_Supuestos!$F$30:$F$35)+Y14*Plan_Supuestos!$F$36 -> 20290.676
A39: Inventario requerido | B39: =B38*Plan_Supuestos!$B$11 -> 18040.634 | C39: =C38*Plan_Supuestos!$B$11 -> 20070.937 | D39: =D38*Plan_Supuestos!$B$11 -> 22271.616 | E39: =E38*Plan_Supuestos!$B$11 -> 24655.469 | F39: =F38*Plan_Supuestos!$B$11 -> 27236.203 | G39: =G38*Plan_Supuestos!$B$11 -> 30028.496 | H39: =H38*Plan_Supuestos!$B$11 -> 33048.071 | I39: =I38*Plan_Supuestos!$B$11 -> 36311.757 | ... Y39: =Y38*Plan_Supuestos!$B$11 -> 101453.38
A40: Variacion de inventario | B40: =0 -> 0 | C40: =C39-B39 -> 2030.3021 | D40: =D39-C39 -> 2200.6793 | E40: =E39-D39 -> 2383.853 | F40: =F39-E39 -> 2580.7336 | G40: =G39-F39 -> 2792.2939 | H40: =H39-G39 -> 3019.5741 | I40: =I39-H39 -> 3263.6862 | J40: =J39-I39 -> 3525.8187 | ... Y40: =Y39-X39 -> 5492.7568
A41: Flujo de caja del mes | B41: =B32-B40 -> 1511.4781 | C41: =C32-C40 -> 398.3122 | D41: =D32-D40 -> 1193.0896 | E41: =E32-E40 -> 2025.2347 | F41: =F32-F40 -> 2896.0456 | G41: =G32-G40 -> 3806.8175 | H41: =H32-H40 -> 4758.8357 | I41: =I32-I40 -> 5753.368 | ... Y41: =Y32-Y40 -> 26193.244
A42: Caja acumulada | B42: =B41 -> 1511.4781 | C42: =B42+C41 -> 1909.7903 | D42: =C42+D41 -> 3102.8799 | E42: =D42+E41 -> 5128.1145 | F42: =E42+F41 -> 8024.1601 | G42: =F42+G41 -> 11830.978 | H42: =G42+H41 -> 16589.813 | I42: =H42+I41 -> 22343.181 | J42: =I42+J41 -> 29134.837 | ... Y42: =X42+Y41 -> 293094.42
A43: Unidades: purificadores Nativo + Vivo | B43: =B12*(B17+B18) -> 114.81959 | C43: =C12*(C17+C18) -> 119.97821 | D43: =D12*(D17+D18) -> 125.35883 | E43: =E12*(E17+E18) -> 130.97028 | F43: =F12*(F17+F18) -> 136.82172 | G43: =G12*(G17+G18) -> 142.92259 | H43: =H12*(H17+H18) -> 149.28265 | I43: =I12*(I17+I18) -> 155.91199 | ... Y43: =Y12*(Y17+Y18) -> 360.70403
A44: Unidades: repuestos de caño | B44: =B12*(B17*Plan_Supuestos!$I$30+B18*Plan_Supuestos!$I$31)+B14 -> 151.00361 | C44: =C12*(C17*Plan_Supuestos!$I$30+C18*Plan_Supuestos!$I$31)+C14 -> 157.6498 | D44: =D12*(D17*Plan_Supuestos!$I$30+D18*Plan_Supuestos!$I$31)+D14 -> 164.58727 | E44: =E12*(E17*Plan_Supuestos!$I$30+E18*Plan_Supuestos!$I$31)+E14 -> 171.82804 | F44: =F12*(F17*Plan_Supuestos!$I$30+F18*Plan_Supuestos!$I$31)+F14 -> 179.38451 | G44: =G12*(G17*Plan_Supuestos!$I$30+G18*Plan_Supuestos!$I$31)+G14 -> 187.26957 | H44: =H12*(H17*Plan_Supuestos!$I$30+H18*Plan_Supuestos!$I$31)+H14 -> 195.49655 | I44: =I12*(I17*Plan_Supuestos!$I$30+I18*Plan_Supuestos!$I$31)+I14 -> 204.07925 | ... Y44: =Y12*(Y17*Plan_Supuestos!$I$30+Y18*Plan_Supuestos!$I$31)+Y14 -> 480.68552
A45: Unidades: Ritual (venta cruzada) | B45: =B12*(Plan_Supuestos!$B$43+(Plan_Supuestos!$B$44-Plan_Supuestos!$B$43)*B16)*Plan_Supuestos!$J$35 -> 10.206186 | C45: =C12*(Plan_Supuestos!$B$43+(Plan_Supuestos!$B$44-Plan_Supuestos!$B$43)*C16)*Plan_Supuestos!$J$35 -> 12.242675 | D45: =D12*(Plan_Supuestos!$B$43+(Plan_Supuestos!$B$44-Plan_Supuestos!$B$43)*D16)*Plan_Supuestos!$J$35 -> 14.474421 | E45: =E12*(Plan_Supuestos!$B$43+(Plan_Supuestos!$B$44-Plan_Supuestos!$B$43)*E16)*Plan_Supuestos!$J$35 -> 16.916994 | F45: =F12*(Plan_Supuestos!$B$43+(Plan_Supuestos!$B$44-Plan_Supuestos!$B$43)*F16)*Plan_Supuestos!$J$35 -> 19.587109 | G45: =G12*(Plan_Supuestos!$B$43+(Plan_Supuestos!$B$44-Plan_Supuestos!$B$43)*G16)*Plan_Supuestos!$J$35 -> 22.502705 | H45: =H12*(Plan_Supuestos!$B$43+(Plan_Supuestos!$B$44-Plan_Supuestos!$B$43)*H16)*Plan_Supuestos!$J$35 -> 25.683037 | I45: =I12*(Plan_Supuestos!$B$43+(Plan_Supuestos!$B$44-Plan_Supuestos!$B$43)*I16)*Plan_Supuestos!$J$35 -> 29.148764 | ... Y45: =Y12*(Plan_Supuestos!$B$43+(Plan_Supuestos!$B$44-Plan_Supuestos!$B$43)*Y16)*Plan_Supuestos!$J$35 -> 90.176007
A46: Unidades: bidon 22 L | B46: =B12*B19 -> 6.378866 | C46: =C12*C19 -> 7.3456049 | D46: =D12*D19 -> 8.4003339 | E46: =E12*E19 -> 9.5499162 | F46: =F12*F19 -> 10.801714 | G46: =G12*G19 -> 12.163624 | H46: =H12*H19 -> 13.644114 | I46: =I12*I19 -> 15.25226 | ... Y46: =Y12*Y19 -> 45.088004
A47: Unidades: bidon 16 L | B47: =B12*B20 -> 5.1030928 | C47: =C12*C20 -> 5.6316304 | D47: =D12*D20 -> 6.2033235 | E47: =E12*E20 -> 6.8213687 | F47: =F12*F20 -> 7.4891886 | G47: =G12*G20 -> 8.2104464 | H47: =H12*H20 -> 8.989063 | I47: =I12*I20 -> 9.8292344 | ... Y47: =Y12*Y20 -> 27.052802
A48: Unidades: Cero | B48: =B12*B21 -> 1.2757732 | C48: =C12*C21 -> 1.7139745 | D48: =D12*D21 -> 2.1970104 | E48: =E12*E21 -> 2.7285475 | F48: =F12*F21 -> 3.3125257 | G48: =G12*G21 -> 3.9531779 | H48: =H12*H21 -> 4.6550505 | I48: =I12*I21 -> 5.4230259 | ... Y48: =Y12*Y21 -> 18.035201

Sheet Plan_Base
A1: Plan a 24 meses - escenario Base
A2: Todo son formulas a partir de Plan_Supuestos y de las hojas de costos. Mes 1 = noviembre 2026.
A4: Mes # | B4: 1 | C4: 2 | D4: 3 | E4: 4 | F4: 5 | G4: 6 | H4: 7 | I4: 8 | J4: 9 | K4: 10 | L4: 11 | M4: 12 | N4: 13 | O4: 14 | P4: 15 | Q4: 16 | R4: 17 | S4: 18 | T4: 19 | U4: 20 | V4: 21 | W4: 22 | X4: 23 | Y4: 24
A5: Mes | B5: Nov-26 | C5: Dic-26 | D5: Ene-27 | E5: Feb-27 | F5: Mar-27 | G5: Abr-27 | H5: May-27 | I5: Jun-27 | J5: Jul-27 | K5: Ago-27 | L5: Sep-27 | M5: Oct-27 | N5: Nov-27 | O5: Dic-27 | P5: Ene-28 | Q5: Feb-28 | R5: Mar-28 | S5: Abr-28 | T5: May-28 | U5: Jun-28 | V5: Jul-28 | W5: Ago-28 | X5: Sep-28 | Y5: Oct-28
A7: Gasto Meta (S/) | B7: =MIN(Plan_Supuestos!$C$20,Plan_Supuestos!$B$6*(1+Plan_Supuestos!$C$19)^(B$4-1)) -> 9000 | C7: =MIN(Plan_Supuestos!$C$20,Plan_Supuestos!$B$6*(1+Plan_Supuestos!$C$19)^(C$4-1)) -> 10080 | D7: =MIN(Plan_Supuestos!$C$20,Plan_Supuestos!$B$6*(1+Plan_Supuestos!$C$19)^(D$4-1)) -> 11289.6 | E7: =MIN(Plan_Supuestos!$C$20,Plan_Supuestos!$B$6*(1+Plan_Supuestos!$C$19)^(E$4-1)) -> 12644.352 | F7: =MIN(Plan_Supuestos!$C$20,Plan_Supuestos!$B$6*(1+Plan_Supuestos!$C$19)^(F$4-1)) -> 14161.674 | G7: =MIN(Plan_Supuestos!$C$20,Plan_Supuestos!$B$6*(1+Plan_Supuestos!$C$19)^(G$4-1)) -> 15861.075 | H7: =MIN(Plan_Supuestos!$C$20,Plan_Supuestos!$B$6*(1+Plan_Supuestos!$C$19)^(H$4-1)) -> 17764.404 | I7: =MIN(Plan_Supuestos!$C$20,Plan_Supuestos!$B$6*(1+Plan_Supuestos!$C$19)^(I$4-1)) -> 19896.133 | ... Y7: =MIN(Plan_Supuestos!$C$20,Plan_Supuestos!$B$6*(1+Plan_Supuestos!$C$19)^(Y$4-1)) -> 121971.13
A8: Mejora de CAC acumulada | B8: =MIN(Plan_Supuestos!$C$22,Plan_Supuestos!$C$21*(B$4-1)) -> 0 | C8: =MIN(Plan_Supuestos!$C$22,Plan_Supuestos!$C$21*(C$4-1)) -> 0.01 | D8: =MIN(Plan_Supuestos!$C$22,Plan_Supuestos!$C$21*(D$4-1)) -> 0.02 | E8: =MIN(Plan_Supuestos!$C$22,Plan_Supuestos!$C$21*(E$4-1)) -> 0.03 | F8: =MIN(Plan_Supuestos!$C$22,Plan_Supuestos!$C$21*(F$4-1)) -> 0.04 | G8: =MIN(Plan_Supuestos!$C$22,Plan_Supuestos!$C$21*(G$4-1)) -> 0.05 | H8: =MIN(Plan_Supuestos!$C$22,Plan_Supuestos!$C$21*(H$4-1)) -> 0.06 | I8: =MIN(Plan_Supuestos!$C$22,Plan_Supuestos!$C$21*(I$4-1)) -> 0.07 | ... Y8: =MIN(Plan_Supuestos!$C$22,Plan_Supuestos!$C$21*(Y$4-1)) -> 0.2
A9: CAC (S/ por pedido nuevo, segun mezcla) | B9: =Plan_Supuestos!$C$17*(B7/Plan_Supuestos!$B$6)^Plan_Supuestos!$C$18*(1-B8)*SUMPRODUCT(B17:B22,Plan_Supuestos!$K$30:$K$35) -> 63.05 | C9: =Plan_Supuestos!$C$17*(C7/Plan_Supuestos!$B$6)^Plan_Supuestos!$C$18*(1-C8)*SUMPRODUCT(C17:C22,Plan_Supuestos!$K$30:$K$35) -> 64.453995 | D9: =Plan_Supuestos!$C$17*(D7/Plan_Supuestos!$B$6)^Plan_Supuestos!$C$18*(1-D8)*SUMPRODUCT(D17:D22,Plan_Supuestos!$K$30:$K$35) -> 65.881613 | E9: =Plan_Supuestos!$C$17*(E7/Plan_Supuestos!$B$6)^Plan_Supuestos!$C$18*(1-E8)*SUMPRODUCT(E17:E22,Plan_Supuestos!$K$30:$K$35) -> 67.332907 | F9: =Plan_Supuestos!$C$17*(F7/Plan_Supuestos!$B$6)^Plan_Supuestos!$C$18*(1-F8)*SUMPRODUCT(F17:F22,Plan_Supuestos!$K$30:$K$35) -> 68.807913 | G9: =Plan_Supuestos!$C$17*(G7/Plan_Supuestos!$B$6)^Plan_Supuestos!$C$18*(1-G8)*SUMPRODUCT(G17:G22,Plan_Supuestos!$K$30:$K$35) -> 70.306641 | H9: =Plan_Supuestos!$C$17*(H7/Plan_Supuestos!$B$6)^Plan_Supuestos!$C$18*(1-H8)*SUMPRODUCT(H17:H22,Plan_Supuestos!$K$30:$K$35) -> 71.829081 | I9: =Plan_Supuestos!$C$17*(I7/Plan_Supuestos!$B$6)^Plan_Supuestos!$C$18*(1-I8)*SUMPRODUCT(I17:I22,Plan_Supuestos!$K$30:$K$35) -> 73.375197 | ... Y9: =Plan_Supuestos!$C$17*(Y7/Plan_Supuestos!$B$6)^Plan_Supuestos!$C$18*(1-Y8)*SUMPRODUCT(Y17:Y22,Plan_Supuestos!$K$30:$K$35) -> 100.76932
A10: Pedidos pagados | B10: =B7/B9 -> 142.74385 | C10: =C7/C9 -> 156.39062 | D10: =D7/D9 -> 171.36192 | E10: =E7/E9 -> 187.78859 | F10: =F7/F9 -> 205.81462 | G10: =G7/G9 -> 225.59853 | H10: =H7/H9 -> 247.31493 | I10: =I7/I9 -> 271.15611 | ... Y10: =Y7/Y9 -> 1210.3994
A11: Pedidos organicos | B11: =B10*Plan_Supuestos!$C$23 -> 21.411578 | C11: =C10*Plan_Supuestos!$C$23 -> 23.458592 | D11: =D10*Plan_Supuestos!$C$23 -> 25.704289 | E11: =E10*Plan_Supuestos!$C$23 -> 28.168289 | F11: =F10*Plan_Supuestos!$C$23 -> 30.872193 | G11: =G10*Plan_Supuestos!$C$23 -> 33.83978 | H11: =H10*Plan_Supuestos!$C$23 -> 37.09724 | I11: =I10*Plan_Supuestos!$C$23 -> 40.673416 | ... Y11: =Y10*Plan_Supuestos!$C$23 -> 181.5599
A12: Pedidos nuevos | B12: =B10+B11 -> 164.15543 | C12: =C10+C11 -> 179.84921 | D12: =D10+D11 -> 197.06621 | E12: =E10+E11 -> 215.95688 | F12: =F10+F11 -> 236.68681 | G12: =G10+G11 -> 259.43831 | H12: =H10+H11 -> 284.41217 | I12: =I10+I11 -> 311.82952 | ... Y12: =Y10+Y11 -> 1391.9593
A13: Pedidos nuevos por dia | B13: =B12/30 -> 5.4718477 | C13: =C12/30 -> 5.9949736 | D13: =D12/30 -> 6.5688738 | E13: =E12/30 -> 7.1985628 | F13: =F12/30 -> 7.8895603 | G13: =G12/30 -> 8.6479438 | H13: =H12/30 -> 9.4804057 | I13: =I12/30 -> 10.394317 | ... Y13: =Y12/30 -> 46.398642
A14: Pedidos de recompra | B14: =Plan_Supuestos!$C$24*IF(B$4>12,INDEX($B12:$Y12,B$4-12),Plan_Supuestos!$B$7) -> 7.2 | C14: =Plan_Supuestos!$C$24*IF(C$4>12,INDEX($B12:$Y12,C$4-12),Plan_Supuestos!$B$7) -> 7.2 | D14: =Plan_Supuestos!$C$24*IF(D$4>12,INDEX($B12:$Y12,D$4-12),Plan_Supuestos!$B$7) -> 7.2 | E14: =Plan_Supuestos!$C$24*IF(E$4>12,INDEX($B12:$Y12,E$4-12),Plan_Supuestos!$B$7) -> 7.2 | F14: =Plan_Supuestos!$C$24*IF(F$4>12,INDEX($B12:$Y12,F$4-12),Plan_Supuestos!$B$7) -> 7.2 | G14: =Plan_Supuestos!$C$24*IF(G$4>12,INDEX($B12:$Y12,G$4-12),Plan_Supuestos!$B$7) -> 7.2 | H14: =Plan_Supuestos!$C$24*IF(H$4>12,INDEX($B12:$Y12,H$4-12),Plan_Supuestos!$B$7) -> 7.2 | I14: =Plan_Supuestos!$C$24*IF(I$4>12,INDEX($B12:$Y12,I$4-12),Plan_Supuestos!$B$7) -> 7.2 | ... Y14: =Plan_Supuestos!$C$24*IF(Y$4>12,INDEX($B12:$Y12,Y$4-12),Plan_Supuestos!$B$7) -> 54.143403
A15: Pedidos totales | B15: =B12+B14 -> 171.35543 | C15: =C12+C14 -> 187.04921 | D15: =D12+D14 -> 204.26621 | E15: =E12+E14 -> 223.15688 | F15: =F12+F14 -> 243.88681 | G15: =G12+G14 -> 266.63831 | H15: =H12+H14 -> 291.61217 | I15: =I12+I14 -> 319.02952 | ... Y15: =Y12+Y14 -> 1446.1027
A16: Avance de la transicion de mezcla | B16: =MIN(1,(B$4-1)/11) -> 0 | C16: =MIN(1,(C$4-1)/11) -> 0.090909091 | D16: =MIN(1,(D$4-1)/11) -> 0.18181818 | E16: =MIN(1,(E$4-1)/11) -> 0.27272727 | F16: =MIN(1,(F$4-1)/11) -> 0.36363636 | G16: =MIN(1,(G$4-1)/11) -> 0.45454545 | H16: =MIN(1,(H$4-1)/11) -> 0.54545455 | I16: =MIN(1,(I$4-1)/11) -> 0.63636364 | ... Y16: =MIN(1,(Y$4-1)/11) -> 1
A17: Mezcla: Nativo | B17: =1-SUM(B18:B22) -> 0.82 | C17: =1-SUM(C18:C22) -> 0.81181818 | D17: =1-SUM(D18:D22) -> 0.80363636 | E17: =1-SUM(E18:E22) -> 0.79545455 | F17: =1-SUM(F18:F22) -> 0.78727273 | G17: =1-SUM(G18:G22) -> 0.77909091 | H17: =1-SUM(H18:H22) -> 0.77090909 | I17: =1-SUM(I18:I22) -> 0.76272727 | ... Y17: =1-SUM(Y18:Y22) -> 0.73
A18: Mezcla: Vivo | B18: =Plan_Supuestos!$G$31+(Plan_Supuestos!$H$31-Plan_Supuestos!$G$31)*B16 -> 0.08 | C18: =Plan_Supuestos!$G$31+(Plan_Supuestos!$H$31-Plan_Supuestos!$G$31)*C16 -> 0.077272727 | D18: =Plan_Supuestos!$G$31+(Plan_Supuestos!$H$31-Plan_Supuestos!$G$31)*D16 -> 0.074545455 | E18: =Plan_Supuestos!$G$31+(Plan_Supuestos!$H$31-Plan_Supuestos!$G$31)*E16 -> 0.071818182 | F18: =Plan_Supuestos!$G$31+(Plan_Supuestos!$H$31-Plan_Supuestos!$G$31)*F16 -> 0.069090909 | G18: =Plan_Supuestos!$G$31+(Plan_Supuestos!$H$31-Plan_Supuestos!$G$31)*G16 -> 0.066363636 | H18: =Plan_Supuestos!$G$31+(Plan_Supuestos!$H$31-Plan_Supuestos!$G$31)*H16 -> 0.063636364 | I18: =Plan_Supuestos!$G$31+(Plan_Supuestos!$H$31-Plan_Supuestos!$G$31)*I16 -> 0.060909091 | ... Y18: =Plan_Supuestos!$G$31+(Plan_Supuestos!$H$31-Plan_Supuestos!$G$31)*Y16 -> 0.05
A19: Mezcla: Bidon 22 L | B19: =Plan_Supuestos!$G$32+(Plan_Supuestos!$H$32-Plan_Supuestos!$G$32)*B16 -> 0.05 | C19: =Plan_Supuestos!$G$32+(Plan_Supuestos!$H$32-Plan_Supuestos!$G$32)*C16 -> 0.054545455 | D19: =Plan_Supuestos!$G$32+(Plan_Supuestos!$H$32-Plan_Supuestos!$G$32)*D16 -> 0.059090909 | E19: =Plan_Supuestos!$G$32+(Plan_Supuestos!$H$32-Plan_Supuestos!$G$32)*E16 -> 0.063636364 | F19: =Plan_Supuestos!$G$32+(Plan_Supuestos!$H$32-Plan_Supuestos!$G$32)*F16 -> 0.068181818 | G19: =Plan_Supuestos!$G$32+(Plan_Supuestos!$H$32-Plan_Supuestos!$G$32)*G16 -> 0.072727273 | H19: =Plan_Supuestos!$G$32+(Plan_Supuestos!$H$32-Plan_Supuestos!$G$32)*H16 -> 0.077272727 | I19: =Plan_Supuestos!$G$32+(Plan_Supuestos!$H$32-Plan_Supuestos!$G$32)*I16 -> 0.081818182 | ... Y19: =Plan_Supuestos!$G$32+(Plan_Supuestos!$H$32-Plan_Supuestos!$G$32)*Y16 -> 0.1
A20: Mezcla: Bidon 16 L | B20: =Plan_Supuestos!$G$33+(Plan_Supuestos!$H$33-Plan_Supuestos!$G$33)*B16 -> 0.04 | C20: =Plan_Supuestos!$G$33+(Plan_Supuestos!$H$33-Plan_Supuestos!$G$33)*C16 -> 0.041818182 | D20: =Plan_Supuestos!$G$33+(Plan_Supuestos!$H$33-Plan_Supuestos!$G$33)*D16 -> 0.043636364 | E20: =Plan_Supuestos!$G$33+(Plan_Supuestos!$H$33-Plan_Supuestos!$G$33)*E16 -> 0.045454545 | F20: =Plan_Supuestos!$G$33+(Plan_Supuestos!$H$33-Plan_Supuestos!$G$33)*F16 -> 0.047272727 | G20: =Plan_Supuestos!$G$33+(Plan_Supuestos!$H$33-Plan_Supuestos!$G$33)*G16 -> 0.049090909 | H20: =Plan_Supuestos!$G$33+(Plan_Supuestos!$H$33-Plan_Supuestos!$G$33)*H16 -> 0.050909091 | I20: =Plan_Supuestos!$G$33+(Plan_Supuestos!$H$33-Plan_Supuestos!$G$33)*I16 -> 0.052727273 | ... Y20: =Plan_Supuestos!$G$33+(Plan_Supuestos!$H$33-Plan_Supuestos!$G$33)*Y16 -> 0.06
A21: Mezcla: Cero | B21: =Plan_Supuestos!$G$34+(Plan_Supuestos!$C$25-Plan_Supuestos!$G$34)*B16 -> 0.01 | C21: =Plan_Supuestos!$G$34+(Plan_Supuestos!$C$25-Plan_Supuestos!$G$34)*C16 -> 0.014545455 | D21: =Plan_Supuestos!$G$34+(Plan_Supuestos!$C$25-Plan_Supuestos!$G$34)*D16 -> 0.019090909 | E21: =Plan_Supuestos!$G$34+(Plan_Supuestos!$C$25-Plan_Supuestos!$G$34)*E16 -> 0.023636364 | F21: =Plan_Supuestos!$G$34+(Plan_Supuestos!$C$25-Plan_Supuestos!$G$34)*F16 -> 0.028181818 | G21: =Plan_Supuestos!$G$34+(Plan_Supuestos!$C$25-Plan_Supuestos!$G$34)*G16 -> 0.032727273 | H21: =Plan_Supuestos!$G$34+(Plan_Supuestos!$C$25-Plan_Supuestos!$G$34)*H16 -> 0.037272727 | I21: =Plan_Supuestos!$G$34+(Plan_Supuestos!$C$25-Plan_Supuestos!$G$34)*I16 -> 0.041818182 | ... Y21: =Plan_Supuestos!$G$34+(Plan_Supuestos!$C$25-Plan_Supuestos!$G$34)*Y16 -> 0.06
A22: Mezcla: Ritual (venta aparte) | B22: =Plan_Supuestos!$G$35+(Plan_Supuestos!$H$35-Plan_Supuestos!$G$35)*B16 -> 0 | C22: =Plan_Supuestos!$G$35+(Plan_Supuestos!$H$35-Plan_Supuestos!$G$35)*C16 -> 0 | D22: =Plan_Supuestos!$G$35+(Plan_Supuestos!$H$35-Plan_Supuestos!$G$35)*D16 -> 0 | E22: =Plan_Supuestos!$G$35+(Plan_Supuestos!$H$35-Plan_Supuestos!$G$35)*E16 -> 0 | F22: =Plan_Supuestos!$G$35+(Plan_Supuestos!$H$35-Plan_Supuestos!$G$35)*F16 -> 0 | G22: =Plan_Supuestos!$G$35+(Plan_Supuestos!$H$35-Plan_Supuestos!$G$35)*G16 -> 0 | H22: =Plan_Supuestos!$G$35+(Plan_Supuestos!$H$35-Plan_Supuestos!$G$35)*H16 -> 0 | I22: =Plan_Supuestos!$G$35+(Plan_Supuestos!$H$35-Plan_Supuestos!$G$35)*I16 -> 0 | ... Y22: =Plan_Supuestos!$G$35+(Plan_Supuestos!$H$35-Plan_Supuestos!$G$35)*Y16 -> 0
A23: Utilidad por pedido nuevo antes de publicidad (S/) | B23: =SUMPRODUCT(B17:B22,Plan_Supuestos!$D$30:$D$35)+(Plan_Supuestos!$B$43+(Plan_Supuestos!$B$44-Plan_Supuestos!$B$43)*B16)*Plan_Supuestos!$B$45 -> 203.66341 | C23: =SUMPRODUCT(C17:C22,Plan_Supuestos!$D$30:$D$35)+(Plan_Supuestos!$B$43+(Plan_Supuestos!$B$44-Plan_Supuestos!$B$43)*C16)*Plan_Supuestos!$B$45 -> 206.77893 | D23: =SUMPRODUCT(D17:D22,Plan_Supuestos!$D$30:$D$35)+(Plan_Supuestos!$B$43+(Plan_Supuestos!$B$44-Plan_Supuestos!$B$43)*D16)*Plan_Supuestos!$B$45 -> 209.89446 | E23: =SUMPRODUCT(E17:E22,Plan_Supuestos!$D$30:$D$35)+(Plan_Supuestos!$B$43+(Plan_Supuestos!$B$44-Plan_Supuestos!$B$43)*E16)*Plan_Supuestos!$B$45 -> 213.00998 | F23: =SUMPRODUCT(F17:F22,Plan_Supuestos!$D$30:$D$35)+(Plan_Supuestos!$B$43+(Plan_Supuestos!$B$44-Plan_Supuestos!$B$43)*F16)*Plan_Supuestos!$B$45 -> 216.12551 | G23: =SUMPRODUCT(G17:G22,Plan_Supuestos!$D$30:$D$35)+(Plan_Supuestos!$B$43+(Plan_Supuestos!$B$44-Plan_Supuestos!$B$43)*G16)*Plan_Supuestos!$B$45 -> 219.24103 | H23: =SUMPRODUCT(H17:H22,Plan_Supuestos!$D$30:$D$35)+(Plan_Supuestos!$B$43+(Plan_Supuestos!$B$44-Plan_Supuestos!$B$43)*H16)*Plan_Supuestos!$B$45 -> 222.35655 | I23: =SUMPRODUCT(I17:I22,Plan_Supuestos!$D$30:$D$35)+(Plan_Supuestos!$B$43+(Plan_Supuestos!$B$44-Plan_Supuestos!$B$43)*I16)*Plan_Supuestos!$B$45 -> 225.47208 | ... Y23: =SUMPRODUCT(Y17:Y22,Plan_Supuestos!$D$30:$D$35)+(Plan_Supuestos!$B$43+(Plan_Supuestos!$B$44-Plan_Supuestos!$B$43)*Y16)*Plan_Supuestos!$B$45 -> 237.93417
A24: Mejora por entrega en Lima por pedido (S/) | B24: =Plan_Supuestos!$C$26*MIN(1,B$4/6)*Plan_Supuestos!$B$8*SUMPRODUCT(B17:B22,Plan_Supuestos!$E$30:$E$35) -> 1.572847 | C24: =Plan_Supuestos!$C$26*MIN(1,C$4/6)*Plan_Supuestos!$B$8*SUMPRODUCT(C17:C22,Plan_Supuestos!$E$30:$E$35) -> 3.187607 | D24: =Plan_Supuestos!$C$26*MIN(1,D$4/6)*Plan_Supuestos!$B$8*SUMPRODUCT(D17:D22,Plan_Supuestos!$E$30:$E$35) -> 4.84428 | E24: =Plan_Supuestos!$C$26*MIN(1,E$4/6)*Plan_Supuestos!$B$8*SUMPRODUCT(E17:E22,Plan_Supuestos!$E$30:$E$35) -> 6.542866 | F24: =Plan_Supuestos!$C$26*MIN(1,F$4/6)*Plan_Supuestos!$B$8*SUMPRODUCT(F17:F22,Plan_Supuestos!$E$30:$E$35) -> 8.2833651 | G24: =Plan_Supuestos!$C$26*MIN(1,G$4/6)*Plan_Supuestos!$B$8*SUMPRODUCT(G17:G22,Plan_Supuestos!$E$30:$E$35) -> 10.065777 | H24: =Plan_Supuestos!$C$26*MIN(1,H$4/6)*Plan_Supuestos!$B$8*SUMPRODUCT(H17:H22,Plan_Supuestos!$E$30:$E$35) -> 10.191516 | I24: =Plan_Supuestos!$C$26*MIN(1,I$4/6)*Plan_Supuestos!$B$8*SUMPRODUCT(I17:I22,Plan_Supuestos!$E$30:$E$35) -> 10.317255 | ... Y24: =Plan_Supuestos!$C$26*MIN(1,Y$4/6)*Plan_Supuestos!$B$8*SUMPRODUCT(Y17:Y22,Plan_Supuestos!$E$30:$E$35) -> 10.820211
A25: Utilidad pedidos nuevos antes de publicidad | B25: =B12*(B23+B24) -> 33690.646 | C25: =C12*(C23+C24) -> 37762.316 | D25: =D12*(D23+D24) -> 42317.75 | E25: =E12*(E23+E24) -> 47413.949 | F25: =F12*(F23+F24) -> 53114.62 | G25: =G12*(G23+G24) -> 59490.971 | H25: =H12*(H23+H24) -> 66139.501 | I25: =I12*(I23+I24) -> 73526.075 | ... Y25: =Y12*(Y23+Y24) -> 346255.97
A26: Utilidad recompra | B26: =B14*Plan_Supuestos!$D$36 -> 881.49715 | C26: =C14*Plan_Supuestos!$D$36 -> 881.49715 | D26: =D14*Plan_Supuestos!$D$36 -> 881.49715 | E26: =E14*Plan_Supuestos!$D$36 -> 881.49715 | F26: =F14*Plan_Supuestos!$D$36 -> 881.49715 | G26: =G14*Plan_Supuestos!$D$36 -> 881.49715 | H26: =H14*Plan_Supuestos!$D$36 -> 881.49715 | I26: =I14*Plan_Supuestos!$D$36 -> 881.49715 | ... Y26: =Y14*Plan_Supuestos!$D$36 -> 6628.7854
A27: Gasto Meta | B27: =-B7 -> -9000 | C27: =-C7 -> -10080 | D27: =-D7 -> -11289.6 | E27: =-E7 -> -12644.352 | F27: =-F7 -> -14161.674 | G27: =-G7 -> -15861.075 | H27: =-H7 -> -17764.404 | I27: =-I7 -> -19896.133 | ... Y27: =-Y7 -> -121971.13
A28: Utilidad despues de publicidad | B28: =B25+B26+B27 -> 25572.144 | C28: =C25+C26+C27 -> 28563.813 | D28: =D25+D26+D27 -> 31909.647 | E28: =E25+E26+E27 -> 35651.094 | F28: =F25+F26+F27 -> 39834.443 | G28: =G25+G26+G27 -> 44511.393 | H28: =H25+H26+H27 -> 49256.594 | I28: =I25+I26+I27 -> 54511.44 | ... Y28: =Y25+Y26+Y27 -> 230913.63
A29: Costos fijos y variables | B29: =-(Plan_Supuestos!$B$9+Plan_Supuestos!$B$10*B15) -> -16370.843 | C29: =-(Plan_Supuestos!$B$9+Plan_Supuestos!$B$10*C15) -> -16496.394 | D29: =-(Plan_Supuestos!$B$9+Plan_Supuestos!$B$10*D15) -> -16634.13 | E29: =-(Plan_Supuestos!$B$9+Plan_Supuestos!$B$10*E15) -> -16785.255 | F29: =-(Plan_Supuestos!$B$9+Plan_Supuestos!$B$10*F15) -> -16951.094 | G29: =-(Plan_Supuestos!$B$9+Plan_Supuestos!$B$10*G15) -> -17133.107 | H29: =-(Plan_Supuestos!$B$9+Plan_Supuestos!$B$10*H15) -> -17332.897 | I29: =-(Plan_Supuestos!$B$9+Plan_Supuestos!$B$10*I15) -> -17552.236 | ... Y29: =-(Plan_Supuestos!$B$9+Plan_Supuestos!$B$10*Y15) -> -26568.821
A30: Utilidad antes de impuestos | B30: =B28+B29 -> 9201.3001 | C30: =C28+C29 -> 12067.42 | D30: =D28+D29 -> 15275.517 | E30: =E28+E29 -> 18865.839 | F30: =F28+F29 -> 22883.348 | G30: =G28+G29 -> 27378.287 | H30: =H28+H29 -> 31923.697 | I30: =I28+I29 -> 36959.203 | ... Y30: =Y28+Y29 -> 204344.81
A31: Impuesto | B31: =-MAX(0,B30)*Plan_Supuestos!$B$12 -> 0 | C31: =-MAX(0,C30)*Plan_Supuestos!$B$12 -> 0 | D31: =-MAX(0,D30)*Plan_Supuestos!$B$12 -> 0 | E31: =-MAX(0,E30)*Plan_Supuestos!$B$12 -> 0 | F31: =-MAX(0,F30)*Plan_Supuestos!$B$12 -> 0 | G31: =-MAX(0,G30)*Plan_Supuestos!$B$12 -> 0 | H31: =-MAX(0,H30)*Plan_Supuestos!$B$12 -> 0 | I31: =-MAX(0,I30)*Plan_Supuestos!$B$12 -> 0 | ... Y31: =-MAX(0,Y30)*Plan_Supuestos!$B$12 -> 0
A32: UTILIDAD NETA DEL MES | B32: =B30+B31 -> 9201.3001 | C32: =C30+C31 -> 12067.42 | D32: =D30+D31 -> 15275.517 | E32: =E30+E31 -> 18865.839 | F32: =F30+F31 -> 22883.348 | G32: =G30+G31 -> 27378.287 | H32: =H30+H31 -> 31923.697 | I32: =I30+I31 -> 36959.203 | ... Y32: =Y30+Y31 -> 204344.81
A33: Utilidad acumulada | B33: =B32 -> 9201.3001 | C33: =B33+C32 -> 21268.72 | D33: =C33+D32 -> 36544.237 | E33: =D33+E32 -> 55410.076 | F33: =E33+F32 -> 78293.424 | G33: =F33+G32 -> 105671.71 | H33: =G33+H32 -> 137595.41 | I33: =H33+I32 -> 174554.61 | J33: =I33+J32 -> 217092.06 | ... Y33: =X33+Y32 -> 1966292.1
A34: Utilidad ultimos 12 meses | M34: =SUM(B32:M32) -> 384514.7 | N34: =SUM(C32:N32) -> 447111.49 | O34: =SUM(D32:O32) -> 514957.58 | P34: =SUM(E32:P32) -> 588471.75 | Q34: =SUM(F32:Q32) -> 668104.43 | R34: =SUM(G32:R32) -> 754339.84 | S34: =SUM(H32:S32) -> 847698.33 | T34: =SUM(I32:T32) -> 949221.94 | ... Y34: =SUM(N32:Y32) -> 1581777.4
A35: Run-rate anual (mes x 12) (S/) | B35: =B32*12 -> 110415.6 | C35: =C32*12 -> 144809.03 | D35: =D32*12 -> 183306.21 | E35: =E32*12 -> 226390.06 | F35: =F32*12 -> 274600.18 | G35: =G32*12 -> 328539.44 | H35: =H32*12 -> 383084.36 | I35: =I32*12 -> 443510.44 | ... Y35: =Y32*12 -> 2452137.7
A36: Run-rate anual (US$) | B36: =B35/Plan_Supuestos!$B$13 -> 31547.315 | C36: =C35/Plan_Supuestos!$B$13 -> 41374.01 | D36: =D35/Plan_Supuestos!$B$13 -> 52373.202 | E36: =E35/Plan_Supuestos!$B$13 -> 64682.876 | F36: =F35/Plan_Supuestos!$B$13 -> 78457.194 | G36: =G35/Plan_Supuestos!$B$13 -> 93868.412 | H36: =H35/Plan_Supuestos!$B$13 -> 109452.67 | I36: =I35/Plan_Supuestos!$B$13 -> 126717.27 | ... Y36: =Y35/Plan_Supuestos!$B$13 -> 700610.77
A37: ¿Run-rate supera la meta? (1 = si) | B37: =IF(B36>=Plan_Supuestos!$B$14,1,0) -> 0 | C37: =IF(C36>=Plan_Supuestos!$B$14,1,0) -> 0 | D37: =IF(D36>=Plan_Supuestos!$B$14,1,0) -> 0 | E37: =IF(E36>=Plan_Supuestos!$B$14,1,0) -> 0 | F37: =IF(F36>=Plan_Supuestos!$B$14,1,0) -> 0 | G37: =IF(G36>=Plan_Supuestos!$B$14,1,0) -> 0 | H37: =IF(H36>=Plan_Supuestos!$B$14,1,0) -> 0 | I37: =IF(I36>=Plan_Supuestos!$B$14,1,0) -> 0 | ... Y37: =IF(Y36>=Plan_Supuestos!$B$14,1,0) -> 0
A38: Costo de producto del mes | B38: =B12*(Plan_Supuestos!$B$8*Supuestos!$B$7+(1-Plan_Supuestos!$B$8)*Supuestos!$B$8)*SUMPRODUCT(B17:B22,Plan_Supuestos!$F$30:$F$35)+B14*Plan_Supuestos!$F$36 -> 4640.0485 | C38: =C12*(Plan_Supuestos!$B$8*Supuestos!$B$7+(1-Plan_Supuestos!$B$8)*Supuestos!$B$8)*SUMPRODUCT(C17:C22,Plan_Supuestos!$F$30:$F$35)+C14*Plan_Supuestos!$F$36 -> 5528.2969 | D38: =D12*(Plan_Supuestos!$B$8*Supuestos!$B$7+(1-Plan_Supuestos!$B$8)*Supuestos!$B$8)*SUMPRODUCT(D17:D22,Plan_Supuestos!$F$30:$F$35)+D14*Plan_Supuestos!$F$36 -> 6544.5697 | E38: =E12*(Plan_Supuestos!$B$8*Supuestos!$B$7+(1-Plan_Supuestos!$B$8)*Supuestos!$B$8)*SUMPRODUCT(E17:E22,Plan_Supuestos!$F$30:$F$35)+E14*Plan_Supuestos!$F$36 -> 7705.5008 | F38: =F12*(Plan_Supuestos!$B$8*Supuestos!$B$7+(1-Plan_Supuestos!$B$8)*Supuestos!$B$8)*SUMPRODUCT(F17:F22,Plan_Supuestos!$F$30:$F$35)+F14*Plan_Supuestos!$F$36 -> 9029.7855 | G38: =G12*(Plan_Supuestos!$B$8*Supuestos!$B$7+(1-Plan_Supuestos!$B$8)*Supuestos!$B$8)*SUMPRODUCT(G17:G22,Plan_Supuestos!$F$30:$F$35)+G14*Plan_Supuestos!$F$36 -> 10538.431 | H38: =H12*(Plan_Supuestos!$B$8*Supuestos!$B$7+(1-Plan_Supuestos!$B$8)*Supuestos!$B$8)*SUMPRODUCT(H17:H22,Plan_Supuestos!$F$30:$F$35)+H14*Plan_Supuestos!$F$36 -> 12255.037 | I38: =I12*(Plan_Supuestos!$B$8*Supuestos!$B$7+(1-Plan_Supuestos!$B$8)*Supuestos!$B$8)*SUMPRODUCT(I17:I22,Plan_Supuestos!$F$30:$F$35)+I14*Plan_Supuestos!$F$36 -> 14206.11 | ... Y38: =Y12*(Plan_Supuestos!$B$8*Supuestos!$B$7+(1-Plan_Supuestos!$B$8)*Supuestos!$B$8)*SUMPRODUCT(Y17:Y22,Plan_Supuestos!$F$30:$F$35)+Y14*Plan_Supuestos!$F$36 -> 77070.387
A39: Inventario requerido | B39: =B38*Plan_Supuestos!$B$11 -> 23200.242 | C39: =C38*Plan_Supuestos!$B$11 -> 27641.485 | D39: =D38*Plan_Supuestos!$B$11 -> 32722.848 | E39: =E38*Plan_Supuestos!$B$11 -> 38527.504 | F39: =F38*Plan_Supuestos!$B$11 -> 45148.928 | G39: =G38*Plan_Supuestos!$B$11 -> 52692.155 | H39: =H38*Plan_Supuestos!$B$11 -> 61275.185 | I39: =I38*Plan_Supuestos!$B$11 -> 71030.548 | ... Y39: =Y38*Plan_Supuestos!$B$11 -> 385351.93
A40: Variacion de inventario | B40: =0 -> 0 | C40: =C39-B39 -> 4441.2422 | D40: =D39-C39 -> 5081.3639 | E40: =E39-D39 -> 5804.6554 | F40: =F39-E39 -> 6621.4237 | G40: =G39-F39 -> 7543.2278 | H40: =H39-G39 -> 8583.0294 | I40: =I39-H39 -> 9755.3636 | J40: =J39-I39 -> 11076.529 | ... Y40: =Y39-X39 -> 31395.498
A41: Flujo de caja del mes | B41: =B32-B40 -> 9201.3001 | C41: =C32-C40 -> 7626.1773 | D41: =D32-D40 -> 10194.153 | E41: =E32-E40 -> 13061.183 | F41: =F32-F40 -> 16261.924 | G41: =G32-G40 -> 19835.059 | H41: =H32-H40 -> 23340.667 | I41: =I32-I40 -> 27203.84 | ... Y41: =Y32-Y40 -> 172949.31
A42: Caja acumulada | B42: =B41 -> 9201.3001 | C42: =B42+C41 -> 16827.477 | D42: =C42+D41 -> 27021.631 | E42: =D42+E41 -> 40082.814 | F42: =E42+F41 -> 56344.739 | G42: =F42+G41 -> 76179.798 | H42: =G42+H41 -> 99520.465 | I42: =H42+I41 -> 126724.3 | J42: =I42+J41 -> 158185.22 | ... Y42: =X42+Y41 -> 1604140.4
A43: Unidades: purificadores Nativo + Vivo | B43: =B12*(B17+B18) -> 147.73989 | C43: =C12*(C17+C18) -> 159.9023 | D43: =D12*(D17+D18) -> 173.05997 | E43: =E12*(E17+E18) -> 187.29351 | F43: =F12*(F17+F18) -> 202.68998 | G43: =G12*(G17+G18) -> 219.3433 | H43: =H12*(H17+H18) -> 237.35488 | I43: =I12*(I17+I18) -> 256.83413 | ... Y43: =Y12*(Y17+Y18) -> 1085.7282
A44: Unidades: repuestos de caño | B44: =B12*(B17*Plan_Supuestos!$I$30+B18*Plan_Supuestos!$I$31)+B14 -> 195.32213 | C44: =C12*(C17*Plan_Supuestos!$I$30+C18*Plan_Supuestos!$I$31)+C14 -> 210.90375 | D44: =D12*(D17*Plan_Supuestos!$I$30+D18*Plan_Supuestos!$I$31)+D14 -> 227.77084 | E44: =E12*(E17*Plan_Supuestos!$I$30+E18*Plan_Supuestos!$I$31)+E14 -> 246.02868 | F44: =F12*(F17*Plan_Supuestos!$I$30+F18*Plan_Supuestos!$I$31)+F14 -> 265.7911 | G44: =G12*(G17*Plan_Supuestos!$I$30+G18*Plan_Supuestos!$I$31)+G14 -> 287.18111 | H44: =H12*(H17*Plan_Supuestos!$I$30+H18*Plan_Supuestos!$I$31)+H14 -> 310.33166 | I44: =I12*(I17*Plan_Supuestos!$I$30+I18*Plan_Supuestos!$I$31)+I14 -> 335.3864 | ... Y44: =Y12*(Y17*Plan_Supuestos!$I$30+Y18*Plan_Supuestos!$I$31)+Y14 -> 1444.7107
A45: Unidades: Ritual (venta cruzada) | B45: =B12*(Plan_Supuestos!$B$43+(Plan_Supuestos!$B$44-Plan_Supuestos!$B$43)*B16)*Plan_Supuestos!$J$35 -> 13.132435 | C45: =C12*(Plan_Supuestos!$B$43+(Plan_Supuestos!$B$44-Plan_Supuestos!$B$43)*C16)*Plan_Supuestos!$J$35 -> 16.349928 | D45: =D12*(Plan_Supuestos!$B$43+(Plan_Supuestos!$B$44-Plan_Supuestos!$B$43)*D16)*Plan_Supuestos!$J$35 -> 20.064924 | E45: =E12*(Plan_Supuestos!$B$43+(Plan_Supuestos!$B$44-Plan_Supuestos!$B$43)*E16)*Plan_Supuestos!$J$35 -> 24.34423 | F45: =F12*(Plan_Supuestos!$B$43+(Plan_Supuestos!$B$44-Plan_Supuestos!$B$43)*F16)*Plan_Supuestos!$J$35 -> 29.263097 | G45: =G12*(Plan_Supuestos!$B$43+(Plan_Supuestos!$B$44-Plan_Supuestos!$B$43)*G16)*Plan_Supuestos!$J$35 -> 34.906246 | H45: =H12*(Plan_Supuestos!$B$43+(Plan_Supuestos!$B$44-Plan_Supuestos!$B$43)*H16)*Plan_Supuestos!$J$35 -> 41.369043 | I45: =I12*(Plan_Supuestos!$B$43+(Plan_Supuestos!$B$44-Plan_Supuestos!$B$43)*I16)*Plan_Supuestos!$J$35 -> 48.758798 | ... Y45: =Y12*(Plan_Supuestos!$B$43+(Plan_Supuestos!$B$44-Plan_Supuestos!$B$43)*Y16)*Plan_Supuestos!$J$35 -> 278.39185
A46: Unidades: bidon 22 L | B46: =B12*B19 -> 8.2077716 | C46: =C12*C19 -> 9.8099568 | D46: =D12*D19 -> 11.644822 | E46: =E12*E19 -> 13.742711 | F46: =F12*F19 -> 16.137737 | G46: =G12*G19 -> 18.868241 | H46: =H12*H19 -> 21.977304 | I46: =I12*I19 -> 25.513325 | ... Y46: =Y12*Y19 -> 139.19593
A47: Unidades: bidon 16 L | B47: =B12*B20 -> 6.5662173 | C47: =C12*C20 -> 7.5209669 | D47: =D12*D20 -> 8.599253 | E47: =E12*E20 -> 9.816222 | F47: =F12*F20 -> 11.188831 | G47: =G12*G20 -> 12.736063 | H47: =H12*H20 -> 14.479165 | I47: =I12*I20 -> 16.44192 | ... Y47: =Y12*Y20 -> 83.517555
A48: Unidades: Cero | B48: =B12*B21 -> 1.6415543 | C48: =C12*C21 -> 2.6159885 | D48: =D12*D21 -> 3.7621732 | E48: =E12*E21 -> 5.1044354 | F48: =F12*F21 -> 6.6702646 | G48: =G12*G21 -> 8.4907085 | H48: =H12*H21 -> 10.600817 | I48: =I12*I21 -> 13.040144 | ... Y48: =Y12*Y21 -> 83.517555

Sheet Plan_Ambicioso
A1: Plan a 24 meses - escenario Ambicioso
A2: Todo son formulas a partir de Plan_Supuestos y de las hojas de costos. Mes 1 = noviembre 2026.
A4: Mes # | B4: 1 | C4: 2 | D4: 3 | E4: 4 | F4: 5 | G4: 6 | H4: 7 | I4: 8 | J4: 9 | K4: 10 | L4: 11 | M4: 12 | N4: 13 | O4: 14 | P4: 15 | Q4: 16 | R4: 17 | S4: 18 | T4: 19 | U4: 20 | V4: 21 | W4: 22 | X4: 23 | Y4: 24
A5: Mes | B5: Nov-26 | C5: Dic-26 | D5: Ene-27 | E5: Feb-27 | F5: Mar-27 | G5: Abr-27 | H5: May-27 | I5: Jun-27 | J5: Jul-27 | K5: Ago-27 | L5: Sep-27 | M5: Oct-27 | N5: Nov-27 | O5: Dic-27 | P5: Ene-28 | Q5: Feb-28 | R5: Mar-28 | S5: Abr-28 | T5: May-28 | U5: Jun-28 | V5: Jul-28 | W5: Ago-28 | X5: Sep-28 | Y5: Oct-28
A7: Gasto Meta (S/) | B7: =MIN(Plan_Supuestos!$D$20,Plan_Supuestos!$B$6*(1+Plan_Supuestos!$D$19)^(B$4-1)) -> 9000 | C7: =MIN(Plan_Supuestos!$D$20,Plan_Supuestos!$B$6*(1+Plan_Supuestos!$D$19)^(C$4-1)) -> 10350 | D7: =MIN(Plan_Supuestos!$D$20,Plan_Supuestos!$B$6*(1+Plan_Supuestos!$D$19)^(D$4-1)) -> 11902.5 | E7: =MIN(Plan_Supuestos!$D$20,Plan_Supuestos!$B$6*(1+Plan_Supuestos!$D$19)^(E$4-1)) -> 13687.875 | F7: =MIN(Plan_Supuestos!$D$20,Plan_Supuestos!$B$6*(1+Plan_Supuestos!$D$19)^(F$4-1)) -> 15741.056 | G7: =MIN(Plan_Supuestos!$D$20,Plan_Supuestos!$B$6*(1+Plan_Supuestos!$D$19)^(G$4-1)) -> 18102.215 | H7: =MIN(Plan_Supuestos!$D$20,Plan_Supuestos!$B$6*(1+Plan_Supuestos!$D$19)^(H$4-1)) -> 20817.547 | I7: =MIN(Plan_Supuestos!$D$20,Plan_Supuestos!$B$6*(1+Plan_Supuestos!$D$19)^(I$4-1)) -> 23940.179 | ... Y7: =MIN(Plan_Supuestos!$D$20,Plan_Supuestos!$B$6*(1+Plan_Supuestos!$D$19)^(Y$4-1)) -> 224023.12
A8: Mejora de CAC acumulada | B8: =MIN(Plan_Supuestos!$D$22,Plan_Supuestos!$D$21*(B$4-1)) -> 0 | C8: =MIN(Plan_Supuestos!$D$22,Plan_Supuestos!$D$21*(C$4-1)) -> 0.015 | D8: =MIN(Plan_Supuestos!$D$22,Plan_Supuestos!$D$21*(D$4-1)) -> 0.03 | E8: =MIN(Plan_Supuestos!$D$22,Plan_Supuestos!$D$21*(E$4-1)) -> 0.045 | F8: =MIN(Plan_Supuestos!$D$22,Plan_Supuestos!$D$21*(F$4-1)) -> 0.06 | G8: =MIN(Plan_Supuestos!$D$22,Plan_Supuestos!$D$21*(G$4-1)) -> 0.075 | H8: =MIN(Plan_Supuestos!$D$22,Plan_Supuestos!$D$21*(H$4-1)) -> 0.09 | I8: =MIN(Plan_Supuestos!$D$22,Plan_Supuestos!$D$21*(I$4-1)) -> 0.105 | ... Y8: =MIN(Plan_Supuestos!$D$22,Plan_Supuestos!$D$21*(Y$4-1)) -> 0.25
A9: CAC (S/ por pedido nuevo, segun mezcla) | B9: =Plan_Supuestos!$D$17*(B7/Plan_Supuestos!$B$6)^Plan_Supuestos!$D$18*(1-B8)*SUMPRODUCT(B17:B22,Plan_Supuestos!$K$30:$K$35) -> 53.35 | C9: =Plan_Supuestos!$D$17*(C7/Plan_Supuestos!$B$6)^Plan_Supuestos!$D$18*(1-C8)*SUMPRODUCT(C17:C22,Plan_Supuestos!$K$30:$K$35) -> 54.015101 | D9: =Plan_Supuestos!$D$17*(D7/Plan_Supuestos!$B$6)^Plan_Supuestos!$D$18*(1-D8)*SUMPRODUCT(D17:D22,Plan_Supuestos!$K$30:$K$35) -> 54.673488 | E9: =Plan_Supuestos!$D$17*(E7/Plan_Supuestos!$B$6)^Plan_Supuestos!$D$18*(1-E8)*SUMPRODUCT(E17:E22,Plan_Supuestos!$K$30:$K$35) -> 55.324347 | F9: =Plan_Supuestos!$D$17*(F7/Plan_Supuestos!$B$6)^Plan_Supuestos!$D$18*(1-F8)*SUMPRODUCT(F17:F22,Plan_Supuestos!$K$30:$K$35) -> 55.966826 | G9: =Plan_Supuestos!$D$17*(G7/Plan_Supuestos!$B$6)^Plan_Supuestos!$D$18*(1-G8)*SUMPRODUCT(G17:G22,Plan_Supuestos!$K$30:$K$35) -> 56.600037 | H9: =Plan_Supuestos!$D$17*(H7/Plan_Supuestos!$B$6)^Plan_Supuestos!$D$18*(1-H8)*SUMPRODUCT(H17:H22,Plan_Supuestos!$K$30:$K$35) -> 57.22305 | I9: =Plan_Supuestos!$D$17*(I7/Plan_Supuestos!$B$6)^Plan_Supuestos!$D$18*(1-I8)*SUMPRODUCT(I17:I22,Plan_Supuestos!$K$30:$K$35) -> 57.834897 | ... Y9: =Plan_Supuestos!$D$17*(Y7/Plan_Supuestos!$B$6)^Plan_Supuestos!$D$18*(1-Y8)*SUMPRODUCT(Y17:Y22,Plan_Supuestos!$K$30:$K$35) -> 69.480805
A10: Pedidos pagados | B10: =B7/B9 -> 168.69728 | C10: =C7/C9 -> 191.61308 | D10: =D7/D9 -> 217.70149 | E10: =E7/E9 -> 247.41141 | F10: =F7/F9 -> 281.2569 | G10: =G7/G9 -> 319.82691 | H10: =H7/H9 -> 363.79653 | I10: =I7/I9 -> 413.94003 | ... Y10: =Y7/Y9 -> 3224.2447
A11: Pedidos organicos | B11: =B10*Plan_Supuestos!$D$23 -> 33.739456 | C11: =C10*Plan_Supuestos!$D$23 -> 38.322617 | D11: =D10*Plan_Supuestos!$D$23 -> 43.540298 | E11: =E10*Plan_Supuestos!$D$23 -> 49.482283 | F11: =F10*Plan_Supuestos!$D$23 -> 56.25138 | G11: =G10*Plan_Supuestos!$D$23 -> 63.965382 | H11: =H10*Plan_Supuestos!$D$23 -> 72.759306 | I11: =I10*Plan_Supuestos!$D$23 -> 82.788006 | ... Y11: =Y10*Plan_Supuestos!$D$23 -> 644.84894
A12: Pedidos nuevos | B12: =B10+B11 -> 202.43674 | C12: =C10+C11 -> 229.9357 | D12: =D10+D11 -> 261.24179 | E12: =E10+E11 -> 296.8937 | F12: =F10+F11 -> 337.50828 | G12: =G10+G11 -> 383.79229 | H12: =H10+H11 -> 436.55584 | I12: =I10+I11 -> 496.72803 | ... Y12: =Y10+Y11 -> 3869.0937
A13: Pedidos nuevos por dia | B13: =B12/30 -> 6.7478913 | C13: =C12/30 -> 7.6645233 | D13: =D12/30 -> 8.7080597 | E13: =E12/30 -> 9.8964566 | F13: =F12/30 -> 11.250276 | G13: =G12/30 -> 12.793076 | H13: =H12/30 -> 14.551861 | I13: =I12/30 -> 16.557601 | ... Y13: =Y12/30 -> 128.96979
A14: Pedidos de recompra | B14: =Plan_Supuestos!$D$24*IF(B$4>12,INDEX($B12:$Y12,B$4-12),Plan_Supuestos!$B$7) -> 9.6 | C14: =Plan_Supuestos!$D$24*IF(C$4>12,INDEX($B12:$Y12,C$4-12),Plan_Supuestos!$B$7) -> 9.6 | D14: =Plan_Supuestos!$D$24*IF(D$4>12,INDEX($B12:$Y12,D$4-12),Plan_Supuestos!$B$7) -> 9.6 | E14: =Plan_Supuestos!$D$24*IF(E$4>12,INDEX($B12:$Y12,E$4-12),Plan_Supuestos!$B$7) -> 9.6 | F14: =Plan_Supuestos!$D$24*IF(F$4>12,INDEX($B12:$Y12,F$4-12),Plan_Supuestos!$B$7) -> 9.6 | G14: =Plan_Supuestos!$D$24*IF(G$4>12,INDEX($B12:$Y12,G$4-12),Plan_Supuestos!$B$7) -> 9.6 | H14: =Plan_Supuestos!$D$24*IF(H$4>12,INDEX($B12:$Y12,H$4-12),Plan_Supuestos!$B$7) -> 9.6 | I14: =Plan_Supuestos!$D$24*IF(I$4>12,INDEX($B12:$Y12,I$4-12),Plan_Supuestos!$B$7) -> 9.6 | ... Y14: =Plan_Supuestos!$D$24*IF(Y$4>12,INDEX($B12:$Y12,Y$4-12),Plan_Supuestos!$B$7) -> 133.65526
A15: Pedidos totales | B15: =B12+B14 -> 212.03674 | C15: =C12+C14 -> 239.5357 | D15: =D12+D14 -> 270.84179 | E15: =E12+E14 -> 306.4937 | F15: =F12+F14 -> 347.10828 | G15: =G12+G14 -> 393.39229 | H15: =H12+H14 -> 446.15584 | I15: =I12+I14 -> 506.32803 | ... Y15: =Y12+Y14 -> 4002.7489
A16: Avance de la transicion de mezcla | B16: =MIN(1,(B$4-1)/11) -> 0 | C16: =MIN(1,(C$4-1)/11) -> 0.090909091 | D16: =MIN(1,(D$4-1)/11) -> 0.18181818 | E16: =MIN(1,(E$4-1)/11) -> 0.27272727 | F16: =MIN(1,(F$4-1)/11) -> 0.36363636 | G16: =MIN(1,(G$4-1)/11) -> 0.45454545 | H16: =MIN(1,(H$4-1)/11) -> 0.54545455 | I16: =MIN(1,(I$4-1)/11) -> 0.63636364 | ... Y16: =MIN(1,(Y$4-1)/11) -> 1
A17: Mezcla: Nativo | B17: =1-SUM(B18:B22) -> 0.82 | C17: =1-SUM(C18:C22) -> 0.81 | D17: =1-SUM(D18:D22) -> 0.8 | E17: =1-SUM(E18:E22) -> 0.79 | F17: =1-SUM(F18:F22) -> 0.78 | G17: =1-SUM(G18:G22) -> 0.77 | H17: =1-SUM(H18:H22) -> 0.76 | I17: =1-SUM(I18:I22) -> 0.75 | ... Y17: =1-SUM(Y18:Y22) -> 0.71
A18: Mezcla: Vivo | B18: =Plan_Supuestos!$G$31+(Plan_Supuestos!$H$31-Plan_Supuestos!$G$31)*B16 -> 0.08 | C18: =Plan_Supuestos!$G$31+(Plan_Supuestos!$H$31-Plan_Supuestos!$G$31)*C16 -> 0.077272727 | D18: =Plan_Supuestos!$G$31+(Plan_Supuestos!$H$31-Plan_Supuestos!$G$31)*D16 -> 0.074545455 | E18: =Plan_Supuestos!$G$31+(Plan_Supuestos!$H$31-Plan_Supuestos!$G$31)*E16 -> 0.071818182 | F18: =Plan_Supuestos!$G$31+(Plan_Supuestos!$H$31-Plan_Supuestos!$G$31)*F16 -> 0.069090909 | G18: =Plan_Supuestos!$G$31+(Plan_Supuestos!$H$31-Plan_Supuestos!$G$31)*G16 -> 0.066363636 | H18: =Plan_Supuestos!$G$31+(Plan_Supuestos!$H$31-Plan_Supuestos!$G$31)*H16 -> 0.063636364 | I18: =Plan_Supuestos!$G$31+(Plan_Supuestos!$H$31-Plan_Supuestos!$G$31)*I16 -> 0.060909091 | ... Y18: =Plan_Supuestos!$G$31+(Plan_Supuestos!$H$31-Plan_Supuestos!$G$31)*Y16 -> 0.05
A19: Mezcla: Bidon 22 L | B19: =Plan_Supuestos!$G$32+(Plan_Supuestos!$H$32-Plan_Supuestos!$G$32)*B16 -> 0.05 | C19: =Plan_Supuestos!$G$32+(Plan_Supuestos!$H$32-Plan_Supuestos!$G$32)*C16 -> 0.054545455 | D19: =Plan_Supuestos!$G$32+(Plan_Supuestos!$H$32-Plan_Supuestos!$G$32)*D16 -> 0.059090909 | E19: =Plan_Supuestos!$G$32+(Plan_Supuestos!$H$32-Plan_Supuestos!$G$32)*E16 -> 0.063636364 | F19: =Plan_Supuestos!$G$32+(Plan_Supuestos!$H$32-Plan_Supuestos!$G$32)*F16 -> 0.068181818 | G19: =Plan_Supuestos!$G$32+(Plan_Supuestos!$H$32-Plan_Supuestos!$G$32)*G16 -> 0.072727273 | H19: =Plan_Supuestos!$G$32+(Plan_Supuestos!$H$32-Plan_Supuestos!$G$32)*H16 -> 0.077272727 | I19: =Plan_Supuestos!$G$32+(Plan_Supuestos!$H$32-Plan_Supuestos!$G$32)*I16 -> 0.081818182 | ... Y19: =Plan_Supuestos!$G$32+(Plan_Supuestos!$H$32-Plan_Supuestos!$G$32)*Y16 -> 0.1
A20: Mezcla: Bidon 16 L | B20: =Plan_Supuestos!$G$33+(Plan_Supuestos!$H$33-Plan_Supuestos!$G$33)*B16 -> 0.04 | C20: =Plan_Supuestos!$G$33+(Plan_Supuestos!$H$33-Plan_Supuestos!$G$33)*C16 -> 0.041818182 | D20: =Plan_Supuestos!$G$33+(Plan_Supuestos!$H$33-Plan_Supuestos!$G$33)*D16 -> 0.043636364 | E20: =Plan_Supuestos!$G$33+(Plan_Supuestos!$H$33-Plan_Supuestos!$G$33)*E16 -> 0.045454545 | F20: =Plan_Supuestos!$G$33+(Plan_Supuestos!$H$33-Plan_Supuestos!$G$33)*F16 -> 0.047272727 | G20: =Plan_Supuestos!$G$33+(Plan_Supuestos!$H$33-Plan_Supuestos!$G$33)*G16 -> 0.049090909 | H20: =Plan_Supuestos!$G$33+(Plan_Supuestos!$H$33-Plan_Supuestos!$G$33)*H16 -> 0.050909091 | I20: =Plan_Supuestos!$G$33+(Plan_Supuestos!$H$33-Plan_Supuestos!$G$33)*I16 -> 0.052727273 | ... Y20: =Plan_Supuestos!$G$33+(Plan_Supuestos!$H$33-Plan_Supuestos!$G$33)*Y16 -> 0.06
A21: Mezcla: Cero | B21: =Plan_Supuestos!$G$34+(Plan_Supuestos!$D$25-Plan_Supuestos!$G$34)*B16 -> 0.01 | C21: =Plan_Supuestos!$G$34+(Plan_Supuestos!$D$25-Plan_Supuestos!$G$34)*C16 -> 0.016363636 | D21: =Plan_Supuestos!$G$34+(Plan_Supuestos!$D$25-Plan_Supuestos!$G$34)*D16 -> 0.022727273 | E21: =Plan_Supuestos!$G$34+(Plan_Supuestos!$D$25-Plan_Supuestos!$G$34)*E16 -> 0.029090909 | F21: =Plan_Supuestos!$G$34+(Plan_Supuestos!$D$25-Plan_Supuestos!$G$34)*F16 -> 0.035454545 | G21: =Plan_Supuestos!$G$34+(Plan_Supuestos!$D$25-Plan_Supuestos!$G$34)*G16 -> 0.041818182 | H21: =Plan_Supuestos!$G$34+(Plan_Supuestos!$D$25-Plan_Supuestos!$G$34)*H16 -> 0.048181818 | I21: =Plan_Supuestos!$G$34+(Plan_Supuestos!$D$25-Plan_Supuestos!$G$34)*I16 -> 0.054545455 | ... Y21: =Plan_Supuestos!$G$34+(Plan_Supuestos!$D$25-Plan_Supuestos!$G$34)*Y16 -> 0.08
A22: Mezcla: Ritual (venta aparte) | B22: =Plan_Supuestos!$G$35+(Plan_Supuestos!$H$35-Plan_Supuestos!$G$35)*B16 -> 0 | C22: =Plan_Supuestos!$G$35+(Plan_Supuestos!$H$35-Plan_Supuestos!$G$35)*C16 -> 0 | D22: =Plan_Supuestos!$G$35+(Plan_Supuestos!$H$35-Plan_Supuestos!$G$35)*D16 -> 0 | E22: =Plan_Supuestos!$G$35+(Plan_Supuestos!$H$35-Plan_Supuestos!$G$35)*E16 -> 0 | F22: =Plan_Supuestos!$G$35+(Plan_Supuestos!$H$35-Plan_Supuestos!$G$35)*F16 -> 0 | G22: =Plan_Supuestos!$G$35+(Plan_Supuestos!$H$35-Plan_Supuestos!$G$35)*G16 -> 0 | H22: =Plan_Supuestos!$G$35+(Plan_Supuestos!$H$35-Plan_Supuestos!$G$35)*H16 -> 0 | I22: =Plan_Supuestos!$G$35+(Plan_Supuestos!$H$35-Plan_Supuestos!$G$35)*I16 -> 0 | ... Y22: =Plan_Supuestos!$G$35+(Plan_Supuestos!$H$35-Plan_Supuestos!$G$35)*Y16 -> 0
A23: Utilidad por pedido nuevo antes de publicidad (S/) | B23: =SUMPRODUCT(B17:B22,Plan_Supuestos!$D$30:$D$35)+(Plan_Supuestos!$B$43+(Plan_Supuestos!$B$44-Plan_Supuestos!$B$43)*B16)*Plan_Supuestos!$B$45 -> 203.66341 | C23: =SUMPRODUCT(C17:C22,Plan_Supuestos!$D$30:$D$35)+(Plan_Supuestos!$B$43+(Plan_Supuestos!$B$44-Plan_Supuestos!$B$43)*C16)*Plan_Supuestos!$B$45 -> 208.04199 | D23: =SUMPRODUCT(D17:D22,Plan_Supuestos!$D$30:$D$35)+(Plan_Supuestos!$B$43+(Plan_Supuestos!$B$44-Plan_Supuestos!$B$43)*D16)*Plan_Supuestos!$B$45 -> 212.42057 | E23: =SUMPRODUCT(E17:E22,Plan_Supuestos!$D$30:$D$35)+(Plan_Supuestos!$B$43+(Plan_Supuestos!$B$44-Plan_Supuestos!$B$43)*E16)*Plan_Supuestos!$B$45 -> 216.79914 | F23: =SUMPRODUCT(F17:F22,Plan_Supuestos!$D$30:$D$35)+(Plan_Supuestos!$B$43+(Plan_Supuestos!$B$44-Plan_Supuestos!$B$43)*F16)*Plan_Supuestos!$B$45 -> 221.17772 | G23: =SUMPRODUCT(G17:G22,Plan_Supuestos!$D$30:$D$35)+(Plan_Supuestos!$B$43+(Plan_Supuestos!$B$44-Plan_Supuestos!$B$43)*G16)*Plan_Supuestos!$B$45 -> 225.5563 | H23: =SUMPRODUCT(H17:H22,Plan_Supuestos!$D$30:$D$35)+(Plan_Supuestos!$B$43+(Plan_Supuestos!$B$44-Plan_Supuestos!$B$43)*H16)*Plan_Supuestos!$B$45 -> 229.93488 | I23: =SUMPRODUCT(I17:I22,Plan_Supuestos!$D$30:$D$35)+(Plan_Supuestos!$B$43+(Plan_Supuestos!$B$44-Plan_Supuestos!$B$43)*I16)*Plan_Supuestos!$B$45 -> 234.31346 | ... Y23: =SUMPRODUCT(Y17:Y22,Plan_Supuestos!$D$30:$D$35)+(Plan_Supuestos!$B$43+(Plan_Supuestos!$B$44-Plan_Supuestos!$B$43)*Y16)*Plan_Supuestos!$B$45 -> 251.82777
A24: Mejora por entrega en Lima por pedido (S/) | B24: =Plan_Supuestos!$D$26*MIN(1,B$4/6)*Plan_Supuestos!$B$8*SUMPRODUCT(B17:B22,Plan_Supuestos!$E$30:$E$35) -> 3.145694 | C24: =Plan_Supuestos!$D$26*MIN(1,C$4/6)*Plan_Supuestos!$B$8*SUMPRODUCT(C17:C22,Plan_Supuestos!$E$30:$E$35) -> 6.4155882 | D24: =Plan_Supuestos!$D$26*MIN(1,D$4/6)*Plan_Supuestos!$B$8*SUMPRODUCT(D17:D22,Plan_Supuestos!$E$30:$E$35) -> 9.8096826 | E24: =Plan_Supuestos!$D$26*MIN(1,E$4/6)*Plan_Supuestos!$B$8*SUMPRODUCT(E17:E22,Plan_Supuestos!$E$30:$E$35) -> 13.327977 | F24: =Plan_Supuestos!$D$26*MIN(1,F$4/6)*Plan_Supuestos!$B$8*SUMPRODUCT(F17:F22,Plan_Supuestos!$E$30:$E$35) -> 16.970472 | G24: =Plan_Supuestos!$D$26*MIN(1,G$4/6)*Plan_Supuestos!$B$8*SUMPRODUCT(G17:G22,Plan_Supuestos!$E$30:$E$35) -> 20.737167 | H24: =Plan_Supuestos!$D$26*MIN(1,H$4/6)*Plan_Supuestos!$B$8*SUMPRODUCT(H17:H22,Plan_Supuestos!$E$30:$E$35) -> 21.109768 | I24: =Plan_Supuestos!$D$26*MIN(1,I$4/6)*Plan_Supuestos!$B$8*SUMPRODUCT(I17:I22,Plan_Supuestos!$E$30:$E$35) -> 21.482369 | ... Y24: =Plan_Supuestos!$D$26*MIN(1,Y$4/6)*Plan_Supuestos!$B$8*SUMPRODUCT(Y17:Y22,Plan_Supuestos!$E$30:$E$35) -> 22.972772
A25: Utilidad pedidos nuevos antes de publicidad | B25: =B12*(B23+B24) -> 41865.76 | C25: =C12*(C23+C24) -> 49311.453 | D25: =D12*(D23+D24) -> 58055.828 | E25: =E12*(E23+E24) -> 68323.292 | F25: =F12*(F23+F24) -> 80376.988 | G25: =G12*(G23+G24) -> 94525.534 | H25: =H12*(H23+H24) -> 109595.01 | I25: =I12*(I23+I24) -> 127060.96 | ... Y25: =Y12*(Y23+Y24) -> 1063229
A26: Utilidad recompra | B26: =B14*Plan_Supuestos!$D$36 -> 1175.3295 | C26: =C14*Plan_Supuestos!$D$36 -> 1175.3295 | D26: =D14*Plan_Supuestos!$D$36 -> 1175.3295 | E26: =E14*Plan_Supuestos!$D$36 -> 1175.3295 | F26: =F14*Plan_Supuestos!$D$36 -> 1175.3295 | G26: =G14*Plan_Supuestos!$D$36 -> 1175.3295 | H26: =H14*Plan_Supuestos!$D$36 -> 1175.3295 | I26: =I14*Plan_Supuestos!$D$36 -> 1175.3295 | ... Y26: =Y14*Plan_Supuestos!$D$36 -> 16363.434
A27: Gasto Meta | B27: =-B7 -> -9000 | C27: =-C7 -> -10350 | D27: =-D7 -> -11902.5 | E27: =-E7 -> -13687.875 | F27: =-F7 -> -15741.056 | G27: =-G7 -> -18102.215 | H27: =-H7 -> -20817.547 | I27: =-I7 -> -23940.179 | ... Y27: =-Y7 -> -224023.12
A28: Utilidad despues de publicidad | B28: =B25+B26+B27 -> 34041.09 | C28: =C25+C26+C27 -> 40136.782 | D28: =D25+D26+D27 -> 47328.658 | E28: =E25+E26+E27 -> 55810.746 | F28: =F25+F26+F27 -> 65811.261 | G28: =G25+G26+G27 -> 77598.649 | H28: =H25+H26+H27 -> 89952.788 | I28: =I25+I26+I27 -> 104296.11 | ... Y28: =Y25+Y26+Y27 -> 855569.35
A29: Costos fijos y variables | B29: =-(Plan_Supuestos!$B$9+Plan_Supuestos!$B$10*B15) -> -16696.294 | C29: =-(Plan_Supuestos!$B$9+Plan_Supuestos!$B$10*C15) -> -16916.286 | D29: =-(Plan_Supuestos!$B$9+Plan_Supuestos!$B$10*D15) -> -17166.734 | E29: =-(Plan_Supuestos!$B$9+Plan_Supuestos!$B$10*E15) -> -17451.95 | F29: =-(Plan_Supuestos!$B$9+Plan_Supuestos!$B$10*F15) -> -17776.866 | G29: =-(Plan_Supuestos!$B$9+Plan_Supuestos!$B$10*G15) -> -18147.138 | H29: =-(Plan_Supuestos!$B$9+Plan_Supuestos!$B$10*H15) -> -18569.247 | I29: =-(Plan_Supuestos!$B$9+Plan_Supuestos!$B$10*I15) -> -19050.624 | ... Y29: =-(Plan_Supuestos!$B$9+Plan_Supuestos!$B$10*Y15) -> -47021.991
A30: Utilidad antes de impuestos | B30: =B28+B29 -> 17344.796 | C30: =C28+C29 -> 23220.497 | D30: =D28+D29 -> 30161.923 | E30: =E28+E29 -> 38358.797 | F30: =F28+F29 -> 48034.395 | G30: =G28+G29 -> 59451.51 | H30: =H28+H29 -> 71383.542 | I30: =I28+I29 -> 85245.484 | ... Y30: =Y28+Y29 -> 808547.35
A31: Impuesto | B31: =-MAX(0,B30)*Plan_Supuestos!$B$12 -> 0 | C31: =-MAX(0,C30)*Plan_Supuestos!$B$12 -> 0 | D31: =-MAX(0,D30)*Plan_Supuestos!$B$12 -> 0 | E31: =-MAX(0,E30)*Plan_Supuestos!$B$12 -> 0 | F31: =-MAX(0,F30)*Plan_Supuestos!$B$12 -> 0 | G31: =-MAX(0,G30)*Plan_Supuestos!$B$12 -> 0 | H31: =-MAX(0,H30)*Plan_Supuestos!$B$12 -> 0 | I31: =-MAX(0,I30)*Plan_Supuestos!$B$12 -> 0 | ... Y31: =-MAX(0,Y30)*Plan_Supuestos!$B$12 -> 0
A32: UTILIDAD NETA DEL MES | B32: =B30+B31 -> 17344.796 | C32: =C30+C31 -> 23220.497 | D32: =D30+D31 -> 30161.923 | E32: =E30+E31 -> 38358.797 | F32: =F30+F31 -> 48034.395 | G32: =G30+G31 -> 59451.51 | H32: =H30+H31 -> 71383.542 | I32: =I30+I31 -> 85245.484 | ... Y32: =Y30+Y31 -> 808547.35
A33: Utilidad acumulada | B33: =B32 -> 17344.796 | C33: =B33+C32 -> 40565.293 | D33: =C33+D32 -> 70727.216 | E33: =D33+E32 -> 109086.01 | F33: =E33+F32 -> 157120.41 | G33: =F33+G32 -> 216571.92 | H33: =G33+H32 -> 287955.46 | I33: =H33+I32 -> 373200.94 | J33: =I33+J32 -> 474552.04 | ... Y33: =X33+Y32 -> 6344765.7
A34: Utilidad ultimos 12 meses | M34: =SUM(B32:M32) -> 903531.35 | N34: =SUM(C32:N32) -> 1082315.8 | O34: =SUM(D32:O32) -> 1286106.9 | P34: =SUM(E32:P32) -> 1518474.3 | Q34: =SUM(F32:Q32) -> 1783515.9 | R34: =SUM(G32:R32) -> 2085940.1 | S34: =SUM(H32:S32) -> 2427764.7 | T34: =SUM(I32:T32) -> 2807936.2 | ... Y34: =SUM(N32:Y32) -> 5441234.4
A35: Run-rate anual (mes x 12) (S/) | B35: =B32*12 -> 208137.55 | C35: =C32*12 -> 278645.96 | D35: =D32*12 -> 361943.08 | E35: =E32*12 -> 460305.56 | F35: =F32*12 -> 576412.74 | G35: =G32*12 -> 713418.12 | H35: =H32*12 -> 856602.5 | I35: =I32*12 -> 1022945.8 | ... Y35: =Y32*12 -> 9702568.2
A36: Run-rate anual (US$) | B36: =B35/Plan_Supuestos!$B$13 -> 59467.872 | C36: =C35/Plan_Supuestos!$B$13 -> 79613.131 | D36: =D35/Plan_Supuestos!$B$13 -> 103412.31 | E36: =E35/Plan_Supuestos!$B$13 -> 131515.87 | F36: =F35/Plan_Supuestos!$B$13 -> 164689.36 | G36: =G35/Plan_Supuestos!$B$13 -> 203833.75 | H36: =H35/Plan_Supuestos!$B$13 -> 244743.57 | I36: =I35/Plan_Supuestos!$B$13 -> 292270.23 | ... Y36: =Y35/Plan_Supuestos!$B$13 -> 2772162.4
A37: ¿Run-rate supera la meta? (1 = si) | B37: =IF(B36>=Plan_Supuestos!$B$14,1,0) -> 0 | C37: =IF(C36>=Plan_Supuestos!$B$14,1,0) -> 0 | D37: =IF(D36>=Plan_Supuestos!$B$14,1,0) -> 0 | E37: =IF(E36>=Plan_Supuestos!$B$14,1,0) -> 0 | F37: =IF(F36>=Plan_Supuestos!$B$14,1,0) -> 0 | G37: =IF(G36>=Plan_Supuestos!$B$14,1,0) -> 0 | H37: =IF(H36>=Plan_Supuestos!$B$14,1,0) -> 0 | I37: =IF(I36>=Plan_Supuestos!$B$14,1,0) -> 0 | ... Y37: =IF(Y36>=Plan_Supuestos!$B$14,1,0) -> 1
A38: Costo de producto del mes | B38: =B12*(Plan_Supuestos!$B$8*Supuestos!$B$7+(1-Plan_Supuestos!$B$8)*Supuestos!$B$8)*SUMPRODUCT(B17:B22,Plan_Supuestos!$F$30:$F$35)+B14*Plan_Supuestos!$F$36 -> 5720.3008 | C38: =C12*(Plan_Supuestos!$B$8*Supuestos!$B$7+(1-Plan_Supuestos!$B$8)*Supuestos!$B$8)*SUMPRODUCT(C17:C22,Plan_Supuestos!$F$30:$F$35)+C14*Plan_Supuestos!$F$36 -> 7283.4521 | D38: =D12*(Plan_Supuestos!$B$8*Supuestos!$B$7+(1-Plan_Supuestos!$B$8)*Supuestos!$B$8)*SUMPRODUCT(D17:D22,Plan_Supuestos!$F$30:$F$35)+D14*Plan_Supuestos!$F$36 -> 9167.8023 | E38: =E12*(Plan_Supuestos!$B$8*Supuestos!$B$7+(1-Plan_Supuestos!$B$8)*Supuestos!$B$8)*SUMPRODUCT(E17:E22,Plan_Supuestos!$F$30:$F$35)+E14*Plan_Supuestos!$F$36 -> 11433.024 | F38: =F12*(Plan_Supuestos!$B$8*Supuestos!$B$7+(1-Plan_Supuestos!$B$8)*Supuestos!$B$8)*SUMPRODUCT(F17:F22,Plan_Supuestos!$F$30:$F$35)+F14*Plan_Supuestos!$F$36 -> 14149.409 | G38: =G12*(Plan_Supuestos!$B$8*Supuestos!$B$7+(1-Plan_Supuestos!$B$8)*Supuestos!$B$8)*SUMPRODUCT(G17:G22,Plan_Supuestos!$F$30:$F$35)+G14*Plan_Supuestos!$F$36 -> 17399.729 | H38: =H12*(Plan_Supuestos!$B$8*Supuestos!$B$7+(1-Plan_Supuestos!$B$8)*Supuestos!$B$8)*SUMPRODUCT(H17:H22,Plan_Supuestos!$F$30:$F$35)+H14*Plan_Supuestos!$F$36 -> 21281.427 | I38: =I12*(Plan_Supuestos!$B$8*Supuestos!$B$7+(1-Plan_Supuestos!$B$8)*Supuestos!$B$8)*SUMPRODUCT(I17:I22,Plan_Supuestos!$F$30:$F$35)+I14*Plan_Supuestos!$F$36 -> 25909.189 | ... Y38: =Y12*(Plan_Supuestos!$B$8*Supuestos!$B$7+(1-Plan_Supuestos!$B$8)*Supuestos!$B$8)*SUMPRODUCT(Y17:Y22,Plan_Supuestos!$F$30:$F$35)+Y14*Plan_Supuestos!$F$36 -> 254352.56
A39: Inventario requerido | B39: =B38*Plan_Supuestos!$B$11 -> 28601.504 | C39: =C38*Plan_Supuestos!$B$11 -> 36417.26 | D39: =D38*Plan_Supuestos!$B$11 -> 45839.012 | E39: =E38*Plan_Supuestos!$B$11 -> 57165.12 | F39: =F38*Plan_Supuestos!$B$11 -> 70747.044 | G39: =G38*Plan_Supuestos!$B$11 -> 86998.645 | H39: =H38*Plan_Supuestos!$B$11 -> 106407.13 | I39: =I38*Plan_Supuestos!$B$11 -> 129545.95 | ... Y39: =Y38*Plan_Supuestos!$B$11 -> 1271762.8
A40: Variacion de inventario | B40: =0 -> 0 | C40: =C39-B39 -> 7815.7564 | D40: =D39-C39 -> 9421.7512 | E40: =E39-D39 -> 11326.108 | F40: =F39-E39 -> 13581.924 | G40: =G39-F39 -> 16251.601 | H40: =H39-G39 -> 19408.489 | I40: =I39-H39 -> 23138.812 | J40: =J39-I39 -> 27543.943 | ... Y40: =Y39-X39 -> 142436.05
A41: Flujo de caja del mes | B41: =B32-B40 -> 17344.796 | C41: =C32-C40 -> 15404.74 | D41: =D32-D40 -> 20740.172 | E41: =E32-E40 -> 27032.688 | F41: =F32-F40 -> 34452.472 | G41: =G32-G40 -> 43199.91 | H41: =H32-H40 -> 51975.052 | I41: =I32-I40 -> 62106.672 | ... Y41: =Y32-Y40 -> 666111.3
A42: Caja acumulada | B42: =B41 -> 17344.796 | C42: =B42+C41 -> 32749.536 | D42: =C42+D41 -> 53489.708 | E42: =D42+E41 -> 80522.397 | F42: =E42+F41 -> 114974.87 | G42: =F42+G41 -> 158174.78 | H42: =G42+H41 -> 210149.83 | I42: =H42+I41 -> 272256.5 | J42: =I42+J41 -> 346063.66 | ... Y42: =X42+Y41 -> 5101604.5
A43: Unidades: purificadores Nativo + Vivo | B43: =B12*(B17+B18) -> 182.19306 | C43: =C12*(C17+C18) -> 204.01567 | D43: =D12*(D17+D18) -> 228.46782 | E43: =E12*(E17+E18) -> 255.86839 | F43: =F12*(F17+F18) -> 286.57521 | G43: =G12*(G17+G18) -> 320.98991 | H43: =H12*(H17+H18) -> 359.56326 | I43: =I12*(I17+I18) -> 402.80128 | ... Y43: =Y12*(Y17+Y18) -> 2940.5112
A44: Unidades: repuestos de caño | B44: =B12*(B17*Plan_Supuestos!$I$30+B18*Plan_Supuestos!$I$31)+B14 -> 241.5925 | C44: =C12*(C17*Plan_Supuestos!$I$30+C18*Plan_Supuestos!$I$31)+C14 -> 269.49005 | D44: =D12*(D17*Plan_Supuestos!$I$30+D18*Plan_Supuestos!$I$31)+D14 -> 300.76585 | E44: =E12*(E17*Plan_Supuestos!$I$30+E18*Plan_Supuestos!$I$31)+E14 -> 335.83219 | F44: =F12*(F17*Plan_Supuestos!$I$30+F18*Plan_Supuestos!$I$31)+F14 -> 375.15215 | G44: =G12*(G17*Plan_Supuestos!$I$30+G18*Plan_Supuestos!$I$31)+G14 -> 419.24593 | H44: =H12*(H17*Plan_Supuestos!$I$30+H18*Plan_Supuestos!$I$31)+H14 -> 468.69799 | I44: =I12*(I17*Plan_Supuestos!$I$30+I18*Plan_Supuestos!$I$31)+I14 -> 524.16509 | ... Y44: =Y12*(Y17*Plan_Supuestos!$I$30+Y18*Plan_Supuestos!$I$31)+Y14 -> 3898.2834
A45: Unidades: Ritual (venta cruzada) | B45: =B12*(Plan_Supuestos!$B$43+(Plan_Supuestos!$B$44-Plan_Supuestos!$B$43)*B16)*Plan_Supuestos!$J$35 -> 16.194939 | C45: =C12*(Plan_Supuestos!$B$43+(Plan_Supuestos!$B$44-Plan_Supuestos!$B$43)*C16)*Plan_Supuestos!$J$35 -> 20.903245 | D45: =D12*(Plan_Supuestos!$B$43+(Plan_Supuestos!$B$44-Plan_Supuestos!$B$43)*D16)*Plan_Supuestos!$J$35 -> 26.599164 | E45: =E12*(Plan_Supuestos!$B$43+(Plan_Supuestos!$B$44-Plan_Supuestos!$B$43)*E16)*Plan_Supuestos!$J$35 -> 33.468017 | F45: =F12*(Plan_Supuestos!$B$43+(Plan_Supuestos!$B$44-Plan_Supuestos!$B$43)*F16)*Plan_Supuestos!$J$35 -> 41.728297 | G45: =G12*(Plan_Supuestos!$B$43+(Plan_Supuestos!$B$44-Plan_Supuestos!$B$43)*G16)*Plan_Supuestos!$J$35 -> 51.637508 | H45: =H12*(Plan_Supuestos!$B$43+(Plan_Supuestos!$B$44-Plan_Supuestos!$B$43)*H16)*Plan_Supuestos!$J$35 -> 63.499031 | I45: =I12*(Plan_Supuestos!$B$43+(Plan_Supuestos!$B$44-Plan_Supuestos!$B$43)*I16)*Plan_Supuestos!$J$35 -> 77.670202 | ... Y45: =Y12*(Plan_Supuestos!$B$43+(Plan_Supuestos!$B$44-Plan_Supuestos!$B$43)*Y16)*Plan_Supuestos!$J$35 -> 773.81873
A46: Unidades: bidon 22 L | B46: =B12*B19 -> 10.121837 | C46: =C12*C19 -> 12.541947 | D46: =D12*D19 -> 15.437015 | E46: =E12*E19 -> 18.893235 | F46: =F12*F19 -> 23.011928 | G46: =G12*G19 -> 27.912167 | H46: =H12*H19 -> 33.73386 | I46: =I12*I19 -> 40.641385 | ... Y46: =Y12*Y19 -> 386.90937
A47: Unidades: bidon 16 L | B47: =B12*B20 -> 8.0974695 | C47: =C12*C20 -> 9.6154929 | D47: =D12*D20 -> 11.399642 | E47: =E12*E20 -> 13.495168 | F47: =F12*F20 -> 15.954937 | G47: =G12*G20 -> 18.840712 | H47: =H12*H20 -> 22.224661 | I47: =I12*I20 -> 26.191115 | ... Y47: =Y12*Y20 -> 232.14562
A48: Unidades: Cero | B48: =B12*B21 -> 2.0243674 | C48: =C12*C21 -> 3.7625842 | D48: =D12*D21 -> 5.9373134 | E48: =E12*E21 -> 8.6369075 | F48: =F12*F21 -> 11.966203 | G48: =G12*G21 -> 16.049496 | H48: =H12*H21 -> 21.034054 | I48: =I12*I21 -> 27.094256 | ... Y48: =Y12*Y21 -> 309.52749

Sheet Resumen
A1: Resumen - utilidad por pedido (S/)
A2: Todas las cifras vienen de la hoja Desglose; cambia los supuestos en la hoja Supuestos.
A4: Producto | B4: Precio | C4: Utilidad antes de publicidad (Lima) | D4: Utilidad final (Lima) | E4: % del precio (Lima) | F4: Utilidad antes de publicidad (Provincia) | G4: Utilidad final (Provincia) | H4: % del precio (Provincia)
A5: =Desglose!B4 -> Nativo 18 meses | B5: =Desglose!B5 -> 299 | C5: =Desglose!B21 -> 161.15927 | D5: =Desglose!B23 -> 96.159271 | E5: =Desglose!B24 -> 0.32160291 | F5: =Desglose!B36 -> 216.44909 | G5: =Desglose!B38 -> 151.44909 | H5: =Desglose!B39 -> 0.50651869
A6: =Desglose!C4 -> Nativo 3 años | B6: =Desglose!C5 -> 349 | C6: =Desglose!C21 -> 191.83756 | D6: =Desglose!C23 -> 126.83756 | E6: =Desglose!C24 -> 0.3634314 | F6: =Desglose!C36 -> 254.79695 | G6: =Desglose!C38 -> 189.79695 | H6: =Desglose!C39 -> 0.5438308
A7: =Desglose!D4 -> Nativo 6 años | B7: =Desglose!D5 -> 399 | C7: =Desglose!D21 -> 220.50263 | D7: =Desglose!D23 -> 155.50263 | E7: =Desglose!D24 -> 0.38973091 | F7: =Desglose!D36 -> 290.62829 | G7: =Desglose!D38 -> 225.62829 | H7: =Desglose!D39 -> 0.56548444
A8: =Desglose!E4 -> Vivo 18 meses | B8: =Desglose!E5 -> 199 | C8: =Desglose!E21 -> 95.776261 | D8: =Desglose!E23 -> 30.776261 | E8: =Desglose!E24 -> 0.15465458 | F8: =Desglose!E36 -> 134.72033 | G8: =Desglose!E38 -> 69.720326 | H8: =Desglose!E39 -> 0.3503534
A9: =Desglose!F4 -> Vivo 3 años | B9: =Desglose!F5 -> 249 | C9: =Desglose!F21 -> 126.45455 | D9: =Desglose!F23 -> 61.45455 | E9: =Desglose!F24 -> 0.24680542 | F9: =Desglose!F36 -> 173.06819 | G9: =Desglose!F38 -> 108.06819 | H9: =Desglose!F39 -> 0.43400878
A10: =Desglose!G4 -> Vivo 6 años | B10: =Desglose!G5 -> 329 | C10: =Desglose!G21 -> 174.73452 | D10: =Desglose!G23 -> 109.73452 | E10: =Desglose!G24 -> 0.33353959 | F10: =Desglose!G36 -> 233.41816 | G10: =Desglose!G38 -> 168.41816 | H10: =Desglose!G39 -> 0.51190929
A11: =Desglose!H4 -> Ritual 1 filtro sin kit | B11: =Desglose!H5 -> 99 | C11: =Desglose!H21 -> 35.334782 | D11: =Desglose!H23 -> -29.665218 | E11: =Desglose!H24 -> -0.29964866 | F11: =Desglose!H36 -> 59.168478 | G11: =Desglose!H38 -> -5.831522 | H11: =Desglose!H39 -> -0.058904263
A12: =Desglose!I4 -> Ritual 1 filtro con kit | B12: =Desglose!I5 -> 99 | C12: =Desglose!I21 -> 22.340385 | D12: =Desglose!I23 -> -42.659615 | E12: =Desglose!I24 -> -0.4309052 | F12: =Desglose!I36 -> 42.925481 | G12: =Desglose!I38 -> -22.074519 | H12: =Desglose!I39 -> -0.22297494
A13: =Desglose!J4 -> Ritual Dúo con kit | B13: =Desglose!J5 -> 179 | C13: =Desglose!J21 -> 48.657997 | D13: =Desglose!J23 -> -16.342003 | E13: =Desglose!J24 -> -0.091296103 | F13: =Desglose!J36 -> 75.822497 | G13: =Desglose!J38 -> 10.822497 | H13: =Desglose!J39 -> 0.060460876
A14: =Desglose!K4 -> Ritual Familia con kit | B14: =Desglose!K5 -> 249 | C14: =Desglose!K21 -> 68.437309 | D14: =Desglose!K23 -> 3.4373093 | E14: =Desglose!K24 -> 0.013804455 | F14: =Desglose!K36 -> 100.54664 | G14: =Desglose!K38 -> 35.546637 | H14: =Desglose!K39 -> 0.14275758
A15: =Desglose!L4 -> Repuesto Nativo | B15: =Desglose!L5 -> 199 | C15: =Desglose!L21 -> 111.69897 | D15: =Desglose!L23 -> 111.69897 | E15: =Desglose!L24 -> 0.56130138 | F15: =Desglose!L36 -> 154.62372 | G15: =Desglose!L38 -> 154.62372 | H15: =Desglose!L39 -> 0.7770036
A16: =Desglose!M4 -> Repuesto Vivo | B16: =Desglose!M5 -> 99 | C16: =Desglose!M21 -> 46.315964 | D16: =Desglose!M23 -> 46.315964 | E16: =Desglose!M24 -> 0.46783802 | F16: =Desglose!M36 -> 72.894954 | G16: =Desglose!M38 -> 72.894954 | H16: =Desglose!M39 -> 0.73631267
A17: =Desglose!N4 -> Repuesto Ritual | B17: =Desglose!N5 -> 49 | C17: =Desglose!N21 -> 2.6432773 | D17: =Desglose!N23 -> 2.6432773 | E17: =Desglose!N24 -> 0.053944435 | F17: =Desglose!N36 -> 18.304097 | G17: =Desglose!N38 -> 18.304097 | H17: =Desglose!N39 -> 0.37355299
A19: Provincia: segun la celda de Supuestos (el cliente paga el envio = 1). Con 0 se muestra envio gratis con courier a cargo de elvo.
A20: Todos los precios incluyen IGV 18%. La utilidad es antes de costos fijos (equipo, software), almacen e impuesto a la renta.

Sheet Supuestos
A1: Supuestos - elvo· margen por producto
A2: Azul = dato que puedes cambiar. Verde = viene de otra hoja. Los precios de venta incluyen IGV.
A3: General
A4: IGV | B4: 0.18 | C4: Tasa vigente. Venta neta = precio / (1 + IGV).
A5: Tipo de cambio (S/ por US$) | B5: 3.5 | C5: Indicado por el usuario.
A6: Publicidad por pedido (CAC, S/) | B6: 65 | C6: Real sep-oct 2026: gasto Meta S/ 14.1k / ~222 pedidos (Shopify + YaVendio) = S/ 64 (sep 54, oct 81). Corrige el S/ 31 inicial.
A7: Entrega efectiva en Lima | B7: 0.8 | C7: Usuario: todos los pedidos de Lima son contraentrega y se entrega el 80%. (El 85% inicial era el promedio con provincia.)
A8: Entrega efectiva en provincia | B8: 1 | C8: Con seña de S/ 50 la falla no genera perdida (usuario).
A10: Costos unitarios puestos en Lima (S/, ver hoja Costo_Lima)
A11: Purificador Nativo / Vivo | B11: =Costo_Lima!F35 -> 22.419911 | C11: Mismo costo para Nativo y Vivo (usuario).
A12: Repuesto (cartucho de caño) | B12: =Costo_Lima!F36 -> 2.5165207
A13: Pieza Ritual (filtro o kit) | B13: =Costo_Lima!F37 -> 16.242997 | C13: Repuesto Ritual = costo de un Ritual (usuario).
A15: Logistica (sin IGV)
A16: Empaque Lima (S/) | B16: 3.5 | C16: Fulfillment Tecretail (usuario).
A17: Empaque provincia (S/) | B17: 5 | C17: Fulfillment Tecretail (usuario).
A18: Courier Lima (S/) | B18: 12.5 | C18: Promedio de S/ 10-15 (Dinsides dia siguiente); express S/ 15. Sin IGV.
A19: Courier provincia si lo pago yo (S/) | B19: 50 | C19: Usuario: a veces cobran S/ 50, a veces 0. Ajustar.
A20: ¿El cliente paga el envio en provincia? (1 = si, 0 = no) | B20: 1 | C20: Cambiar a 0 para ver envio gratis.
A22: Comisiones de pago
A23: % pedidos en efectivo / Yape | B23: 0.5 | C23: MEZCLA ILUSTRATIVA (supuesto). Reemplazar con datos reales.
A24: % pedidos con tarjeta en 1 pago | B24: 0.2 | C24: MEZCLA ILUSTRATIVA.
A25: % pedidos en 3 cuotas | B25: 0.15 | C25: MEZCLA ILUSTRATIVA.
A26: % pedidos en 6 cuotas | B26: 0.15 | C26: MEZCLA ILUSTRATIVA.
A27: Tasa tarjeta 1 pago | B27: 0.0349 | C27: Usuario: 3.49% + S/ 1.
A28: Tasa 3 cuotas | B28: 0.0648 | C28: Usuario: 6.48% + S/ 1.
A29: Tasa 6 cuotas | B29: 0.0898 | C29: Usuario: 8.98% + S/ 1.
A30: Fijo por transaccion con tarjeta (S/) | B30: 1 | C30: Usuario.
A31: Comision % ponderada | B31: =B24*B27+B25*B28+B26*B29 -> 0.03017
A32: Comision fija ponderada (S/) | B32: =(B24+B25+B26)*B30 -> 0.5
A33: Control: la mezcla debe sumar 100% | B33: =SUM(B23:B26) -> 1
A35: Almacen (Tecretail)
A36: Almacen mensual (S/) | B36: 400 | C36: Usuario.
A37: Pedidos al mes para prorratear | B37: 100 | C37: Supuesto. Cambiar segun ventas.
A38: Almacen por pedido (S/) | B38: =B36/B37 -> 4

Sheet Desglose
A1: Desglose desde el precio de venta, por pedido colocado (S/)
A2: Azul = entradas por producto (editables). Todo lo demas son formulas conectadas a Supuestos.
A4: Producto | B4: Nativo 18 meses | C4: Nativo 3 años | D4: Nativo 6 años | E4: Vivo 18 meses | F4: Vivo 3 años | G4: Vivo 6 años | H4: Ritual 1 filtro sin kit | I4: Ritual 1 filtro con kit | J4: Ritual Dúo con kit | K4: Ritual Familia con kit | L4: Repuesto Nativo | M4: Repuesto Vivo | N4: Repuesto Ritual
A5: Precio de venta (incluye IGV) | B5: 299 | C5: 349 | D5: 399 | E5: 199 | F5: 249 | G5: 329 | H5: 99 | I5: 99 | J5: 179 | K5: 249 | L5: 199 | M5: 99 | N5: 49
A6: Purificadores por pedido | B6: 1 | C6: 1 | D6: 1 | E6: 1 | F6: 1 | G6: 1 | H6: 0 | I6: 0 | J6: 0 | K6: 0 | L6: 0 | M6: 0 | N6: 0
A7: Repuestos de caño por pedido | B7: 0 | C7: 1 | D7: 3 | E7: 0 | F7: 1 | G7: 3 | H7: 0 | I7: 0 | J7: 0 | K7: 0 | L7: 1 | M7: 1 | N7: 0
A8: Piezas Ritual por pedido (filtro o kit) | B8: 0 | C8: 0 | D8: 0 | E8: 0 | F8: 0 | G8: 0 | H8: 1 | I8: 2 | J8: 4 | K8: 6 | L8: 0 | M8: 0 | N8: 1
A9: ¿Lleva publicidad? (1 = si, 0 = no) | B9: 1 | C9: 1 | D9: 1 | E9: 1 | F9: 1 | G9: 1 | H9: 1 | I9: 1 | J9: 1 | K9: 1 | L9: 0 | M9: 0 | N9: 0
A11: LIMA (85% de entrega)
A12: Precio de venta | B12: =B5 -> 299 | C12: =C5 -> 349 | D12: =D5 -> 399 | E12: =E5 -> 199 | F12: =F5 -> 249 | G12: =G5 -> 329 | H12: =H5 -> 99 | I12: =I5 -> 99 | ... N12: =N5 -> 49
A13: IGV | B13: =-(B5-B5/(1+Supuestos!$B$4)) -> -45.610169 | C13: =-(C5-C5/(1+Supuestos!$B$4)) -> -53.237288 | D13: =-(D5-D5/(1+Supuestos!$B$4)) -> -60.864407 | E13: =-(E5-E5/(1+Supuestos!$B$4)) -> -30.355932 | F13: =-(F5-F5/(1+Supuestos!$B$4)) -> -37.983051 | G13: =-(G5-G5/(1+Supuestos!$B$4)) -> -50.186441 | H13: =-(H5-H5/(1+Supuestos!$B$4)) -> -15.101695 | I13: =-(I5-I5/(1+Supuestos!$B$4)) -> -15.101695 | ... N13: =-(N5-N5/(1+Supuestos!$B$4)) -> -7.4745763
A14: Venta neta | B14: =B5/(1+Supuestos!$B$4) -> 253.38983 | C14: =C5/(1+Supuestos!$B$4) -> 295.76271 | D14: =D5/(1+Supuestos!$B$4) -> 338.13559 | E14: =E5/(1+Supuestos!$B$4) -> 168.64407 | F14: =F5/(1+Supuestos!$B$4) -> 211.01695 | G14: =G5/(1+Supuestos!$B$4) -> 278.81356 | H14: =H5/(1+Supuestos!$B$4) -> 83.898305 | I14: =I5/(1+Supuestos!$B$4) -> 83.898305 | ... N14: =N5/(1+Supuestos!$B$4) -> 41.525424
A15: Producto | B15: =-(B6*Supuestos!$B$11+B7*Supuestos!$B$12+B8*Supuestos!$B$13) -> -22.419911 | C15: =-(C6*Supuestos!$B$11+C7*Supuestos!$B$12+C8*Supuestos!$B$13) -> -24.936432 | D15: =-(D6*Supuestos!$B$11+D7*Supuestos!$B$12+D8*Supuestos!$B$13) -> -29.969474 | E15: =-(E6*Supuestos!$B$11+E7*Supuestos!$B$12+E8*Supuestos!$B$13) -> -22.419911 | F15: =-(F6*Supuestos!$B$11+F7*Supuestos!$B$12+F8*Supuestos!$B$13) -> -24.936432 | G15: =-(G6*Supuestos!$B$11+G7*Supuestos!$B$12+G8*Supuestos!$B$13) -> -29.969474 | H15: =-(H6*Supuestos!$B$11+H7*Supuestos!$B$12+H8*Supuestos!$B$13) -> -16.242997 | I15: =-(I6*Supuestos!$B$11+I7*Supuestos!$B$12+I8*Supuestos!$B$13) -> -32.485994 | ... N15: =-(N6*Supuestos!$B$11+N7*Supuestos!$B$12+N8*Supuestos!$B$13) -> -16.242997
A16: Comision de pago | B16: =-(B5*Supuestos!$B$31+Supuestos!$B$32) -> -9.52083 | C16: =-(C5*Supuestos!$B$31+Supuestos!$B$32) -> -11.02933 | D16: =-(D5*Supuestos!$B$31+Supuestos!$B$32) -> -12.53783 | E16: =-(E5*Supuestos!$B$31+Supuestos!$B$32) -> -6.50383 | F16: =-(F5*Supuestos!$B$31+Supuestos!$B$32) -> -8.01233 | G16: =-(G5*Supuestos!$B$31+Supuestos!$B$32) -> -10.42593 | H16: =-(H5*Supuestos!$B$31+Supuestos!$B$32) -> -3.48683 | I16: =-(I5*Supuestos!$B$31+Supuestos!$B$32) -> -3.48683 | ... N16: =-(N5*Supuestos!$B$31+Supuestos!$B$32) -> -1.97833
A17: Empaque | B17: =-Supuestos!$B$16 -> -3.5 | C17: =-Supuestos!$B$16 -> -3.5 | D17: =-Supuestos!$B$16 -> -3.5 | E17: =-Supuestos!$B$16 -> -3.5 | F17: =-Supuestos!$B$16 -> -3.5 | G17: =-Supuestos!$B$16 -> -3.5 | H17: =-Supuestos!$B$16 -> -3.5 | I17: =-Supuestos!$B$16 -> -3.5 | ... N17: =-Supuestos!$B$16 -> -3.5
A18: Courier | B18: =-Supuestos!$B$18 -> -12.5 | C18: =-Supuestos!$B$18 -> -12.5 | D18: =-Supuestos!$B$18 -> -12.5 | E18: =-Supuestos!$B$18 -> -12.5 | F18: =-Supuestos!$B$18 -> -12.5 | G18: =-Supuestos!$B$18 -> -12.5 | H18: =-Supuestos!$B$18 -> -12.5 | I18: =-Supuestos!$B$18 -> -12.5 | ... N18: =-Supuestos!$B$18 -> -12.5
A19: Margen si se entrega | B19: =SUM(B14:B18) -> 205.44909 | C19: =SUM(C14:C18) -> 243.79695 | D19: =SUM(D14:D18) -> 279.62829 | E19: =SUM(E14:E18) -> 123.72033 | F19: =SUM(F14:F18) -> 162.06819 | G19: =SUM(G14:G18) -> 222.41816 | H19: =SUM(H14:H18) -> 48.168478 | I19: =SUM(I14:I18) -> 31.925481 | ... N19: =SUM(N14:N18) -> 7.3040966
A20: Entregas fallidas | B20: =-(1-Supuestos!$B$7)*(B14+B15+B16) -> -44.289818 | C20: =-(1-Supuestos!$B$7)*(C14+C15+C16) -> -51.95939 | D20: =-(1-Supuestos!$B$7)*(D14+D15+D16) -> -59.125658 | E20: =-(1-Supuestos!$B$7)*(E14+E15+E16) -> -27.944065 | F20: =-(1-Supuestos!$B$7)*(F14+F15+F16) -> -35.613637 | G20: =-(1-Supuestos!$B$7)*(G14+G15+G16) -> -47.683631 | H20: =-(1-Supuestos!$B$7)*(H14+H15+H16) -> -12.833696 | I20: =-(1-Supuestos!$B$7)*(I14+I15+I16) -> -9.5850962 | ... N20: =-(1-Supuestos!$B$7)*(N14+N15+N16) -> -4.6608193
A21: Utilidad antes de publicidad | B21: =B19+B20 -> 161.15927 | C21: =C19+C20 -> 191.83756 | D21: =D19+D20 -> 220.50263 | E21: =E19+E20 -> 95.776261 | F21: =F19+F20 -> 126.45455 | G21: =G19+G20 -> 174.73452 | H21: =H19+H20 -> 35.334782 | I21: =I19+I20 -> 22.340385 | ... N21: =N19+N20 -> 2.6432773
A22: Publicidad (CAC) | B22: =-Supuestos!$B$6*B9 -> -65 | C22: =-Supuestos!$B$6*C9 -> -65 | D22: =-Supuestos!$B$6*D9 -> -65 | E22: =-Supuestos!$B$6*E9 -> -65 | F22: =-Supuestos!$B$6*F9 -> -65 | G22: =-Supuestos!$B$6*G9 -> -65 | H22: =-Supuestos!$B$6*H9 -> -65 | I22: =-Supuestos!$B$6*I9 -> -65 | ... N22: =-Supuestos!$B$6*N9 -> 0
A23: Utilidad final | B23: =B21+B22 -> 96.159271 | C23: =C21+C22 -> 126.83756 | D23: =D21+D22 -> 155.50263 | E23: =E21+E22 -> 30.776261 | F23: =F21+F22 -> 61.45455 | G23: =G21+G22 -> 109.73452 | H23: =H21+H22 -> -29.665218 | I23: =I21+I22 -> -42.659615 | ... N23: =N21+N22 -> 2.6432773
A24: % del precio | B24: =B23/B5 -> 0.32160291 | C24: =C23/C5 -> 0.3634314 | D24: =D23/D5 -> 0.38973091 | E24: =E23/E5 -> 0.15465458 | F24: =F23/F5 -> 0.24680542 | G24: =G23/G5 -> 0.33353959 | H24: =H23/H5 -> -0.29964866 | I24: =I23/I5 -> -0.4309052 | ... N24: =N23/N5 -> 0.053944435
A25: Almacen prorrateado | B25: =-Supuestos!$B$38 -> -4 | C25: =-Supuestos!$B$38 -> -4 | D25: =-Supuestos!$B$38 -> -4 | E25: =-Supuestos!$B$38 -> -4 | F25: =-Supuestos!$B$38 -> -4 | G25: =-Supuestos!$B$38 -> -4 | H25: =-Supuestos!$B$38 -> -4 | I25: =-Supuestos!$B$38 -> -4 | ... N25: =-Supuestos!$B$38 -> -4
A26: Utilidad final tras almacen | B26: =B23+B25 -> 92.159271 | C26: =C23+C25 -> 122.83756 | D26: =D23+D25 -> 151.50263 | E26: =E23+E25 -> 26.776261 | F26: =F23+F25 -> 57.45455 | G26: =G23+G25 -> 105.73452 | H26: =H23+H25 -> -33.665218 | I26: =I23+I25 -> -46.659615 | ... N26: =N23+N25 -> -1.3567227
A28: PROVINCIA (seña de S/ 50)
A29: Venta neta | B29: =B14 -> 253.38983 | C29: =C14 -> 295.76271 | D29: =D14 -> 338.13559 | E29: =E14 -> 168.64407 | F29: =F14 -> 211.01695 | G29: =G14 -> 278.81356 | H29: =H14 -> 83.898305 | I29: =I14 -> 83.898305 | ... N29: =N14 -> 41.525424
A30: Producto | B30: =B15 -> -22.419911 | C30: =C15 -> -24.936432 | D30: =D15 -> -29.969474 | E30: =E15 -> -22.419911 | F30: =F15 -> -24.936432 | G30: =G15 -> -29.969474 | H30: =H15 -> -16.242997 | I30: =I15 -> -32.485994 | ... N30: =N15 -> -16.242997
A31: Comision de pago | B31: =B16 -> -9.52083 | C31: =C16 -> -11.02933 | D31: =D16 -> -12.53783 | E31: =E16 -> -6.50383 | F31: =F16 -> -8.01233 | G31: =G16 -> -10.42593 | H31: =H16 -> -3.48683 | I31: =I16 -> -3.48683 | ... N31: =N16 -> -1.97833
A32: Empaque provincia | B32: =-Supuestos!$B$17 -> -5 | C32: =-Supuestos!$B$17 -> -5 | D32: =-Supuestos!$B$17 -> -5 | E32: =-Supuestos!$B$17 -> -5 | F32: =-Supuestos!$B$17 -> -5 | G32: =-Supuestos!$B$17 -> -5 | H32: =-Supuestos!$B$17 -> -5 | I32: =-Supuestos!$B$17 -> -5 | ... N32: =-Supuestos!$B$17 -> -5
A33: Courier a mi cargo | B33: =-(1-Supuestos!$B$20)*Supuestos!$B$19 -> 0 | C33: =-(1-Supuestos!$B$20)*Supuestos!$B$19 -> 0 | D33: =-(1-Supuestos!$B$20)*Supuestos!$B$19 -> 0 | E33: =-(1-Supuestos!$B$20)*Supuestos!$B$19 -> 0 | F33: =-(1-Supuestos!$B$20)*Supuestos!$B$19 -> 0 | G33: =-(1-Supuestos!$B$20)*Supuestos!$B$19 -> 0 | H33: =-(1-Supuestos!$B$20)*Supuestos!$B$19 -> 0 | I33: =-(1-Supuestos!$B$20)*Supuestos!$B$19 -> 0 | ... N33: =-(1-Supuestos!$B$20)*Supuestos!$B$19 -> 0
A34: Margen si se entrega | B34: =SUM(B29:B33) -> 216.44909 | C34: =SUM(C29:C33) -> 254.79695 | D34: =SUM(D29:D33) -> 290.62829 | E34: =SUM(E29:E33) -> 134.72033 | F34: =SUM(F29:F33) -> 173.06819 | G34: =SUM(G29:G33) -> 233.41816 | H34: =SUM(H29:H33) -> 59.168478 | I34: =SUM(I29:I33) -> 42.925481 | ... N34: =SUM(N29:N33) -> 18.304097
A35: Entregas fallidas | B35: =-(1-Supuestos!$B$8)*(B29+B30+B31) -> 0 | C35: =-(1-Supuestos!$B$8)*(C29+C30+C31) -> 0 | D35: =-(1-Supuestos!$B$8)*(D29+D30+D31) -> 0 | E35: =-(1-Supuestos!$B$8)*(E29+E30+E31) -> 0 | F35: =-(1-Supuestos!$B$8)*(F29+F30+F31) -> 0 | G35: =-(1-Supuestos!$B$8)*(G29+G30+G31) -> 0 | H35: =-(1-Supuestos!$B$8)*(H29+H30+H31) -> 0 | I35: =-(1-Supuestos!$B$8)*(I29+I30+I31) -> 0 | ... N35: =-(1-Supuestos!$B$8)*(N29+N30+N31) -> 0
A36: Utilidad antes de publicidad | B36: =B34+B35 -> 216.44909 | C36: =C34+C35 -> 254.79695 | D36: =D34+D35 -> 290.62829 | E36: =E34+E35 -> 134.72033 | F36: =F34+F35 -> 173.06819 | G36: =G34+G35 -> 233.41816 | H36: =H34+H35 -> 59.168478 | I36: =I34+I35 -> 42.925481 | ... N36: =N34+N35 -> 18.304097
A37: Publicidad (CAC) | B37: =B22 -> -65 | C37: =C22 -> -65 | D37: =D22 -> -65 | E37: =E22 -> -65 | F37: =F22 -> -65 | G37: =G22 -> -65 | H37: =H22 -> -65 | I37: =I22 -> -65 | ... N37: =N22 -> 0
A38: Utilidad final | B38: =B36+B37 -> 151.44909 | C38: =C36+C37 -> 189.79695 | D38: =D36+D37 -> 225.62829 | E38: =E36+E37 -> 69.720326 | F38: =F36+F37 -> 108.06819 | G38: =G36+G37 -> 168.41816 | H38: =H36+H37 -> -5.831522 | I38: =I36+I37 -> -22.074519 | ... N38: =N36+N37 -> 18.304097
A39: % del precio | B39: =B38/B5 -> 0.50651869 | C39: =C38/C5 -> 0.5438308 | D39: =D38/D5 -> 0.56548444 | E39: =E38/E5 -> 0.3503534 | F39: =F38/F5 -> 0.43400878 | G39: =G38/G5 -> 0.51190929 | H39: =H38/H5 -> -0.058904263 | I39: =I38/I5 -> -0.22297494 | ... N39: =N38/N5 -> 0.37355299
A41: Notas: las entregas fallidas restan la utilidad que no se cobra (se paga empaque y courier igual). En repuestos no se aplica publicidad (recompra por WhatsApp). Ritual "con kit" = filtro + kit de repuesto incluido.
A42: Excluye: PureCore / nucleo de magnesio si es otra compra, tarifa de almacen de puerto pendiente, comisiones bancarias, costos fijos de equipo e impuesto a la renta.

Sheet Contenedor2
A1: Contenedor 2 - bidones 22 L / 16 L, kit 3 en 1 y elvo· Cero (R260) - B/L COSU6464399990, 40HQ, llega a Chancay el 25-oct-2026
A2: Azul = dato de los documentos o supuesto editable. Negro = formula. Verde = viene de otra hoja. Lo marcado ESTIMADO sale del embarque anterior, no de un documento de este contenedor.
A4: Producto | B4: Unidades | C4: FOB unitario (US$) | D4: FOB total (US$) | E4: Volumen (CBM) | F4: % del volumen | G4: % del valor
A5: Bidon purificador 22 L | B5: 804 | C5: 9.5 | D5: =B5*C5 -> 7638 | E5: 19.431373 | F5: =E5/$E$9 -> 0.35871097 | G5: =D5/$D$9 -> 0.24108326
A6: Bidon purificador 16 L | B6: 804 | C6: 7 | D6: =B6*C6 -> 5628 | E6: 20.848256 | F6: =E6/$E$9 -> 0.3848672 | G6: =D6/$D$9 -> 0.1776403
A7: Kit de filtros 3 en 1 | B7: 840 | C7: 2.1 | D7: =B7*C7 -> 1764 | E7: 5.05 | F7: =E7/$E$9 -> 0.093225032 | G7: =D7/$D$9 -> 0.055678303
A8: elvo· Cero R260 (100 maquinas + 20 filtros + entrega a Ningbo) | B8: 100 | C8: =D8/B8 -> 166.52 | D8: =D17 -> 16652 | E8: =B20-SUM(E5:E7) -> 8.8403705 | F8: =E8/$E$9 -> 0.1631968 | G8: =D8/$D$9 -> 0.52559813
A9: Total | D9: =SUM(D5:D8) -> 31682 | E9: =SUM(E5:E8) -> 54.17
A10: Fuentes: factura DK-GV-2026-01 (Ningbo Dukang, 1-jun-2026) y packing list; proforma 10062026356AVR260W (Suzhou Beiang, 10-jun-2026, EXW). CBM de Cero = CBM total del B/L menos los CBM del packing list (101 cartones, ~1,014 kg).
A11: Detalle elvo· Cero (Suzhou Beiang) - pago 30% anticipo / 70% antes de embarque
A12: Concepto | B12: Cantidad | C12: Precio (US$) | D12: Total (US$)
A13: Maquinas R260 (agua fria y caliente, osmosis inversa, UV) | B13: 100 | C13: 162 | D13: =B13*C13 -> 16200
A14: Filtro ROC de repuesto | B14: 10 | C14: 20 | D14: =B14*C14 -> 200
A15: Filtro PAC de repuesto | B15: 10 | C15: 10 | D15: =B15*C15 -> 100
A16: Entrega a Ningbo (monto unico) | B16: 1 | C16: 152 | D16: =B16*C16 -> 152
A17: Total Cero | D17: =SUM(D13:D16) -> 16652
A19: Volumen y flete (B/L: flete collect, se paga en destino)
A20: Volumen total del B/L (CBM) | B20: 54.17
A21: Flete maritimo (US$) | B21: 6580
A22: Fuel Adjustment Factor (US$) | B22: 720
A23: ISPS (US$) | B23: 6
A24: THC en destino (US$) | B24: 80
A25: Total flete collect (US$) | B25: =SUM(B21:B24) -> 7386
A26: Visto bueno de importacion Callao-Chancay (US$, sin IGV) | B26: 160
A27: SAC (US$, sin IGV) | B27: 40
A28: Otros gastos locales ESTIMADOS (US$, con IGV) | B28: 606.21 | C28: Suma de agenciamiento, transmision, handling, documentacion, descarga y gastos admin. de la factura Inca Lines del embarque anterior. Contenedor completo puede variar.
A29: Seguro nocional (% del FOB) | B29: 0.01 | C29: Mismo % que la proforma de aduana anterior (US$ 74.50 sobre FOB 7,450). Es base de impuestos, no un pago.
A31: Impuestos de aduana - ratios del embarque anterior (proforma 026/0000257)
A32: CIF anterior (US$) | B32: 8189.581
A33: Tipo de cambio de aduana anterior | B33: 3.444
A34: IGV anterior (S/) | B34: 4370
A35: IPM anterior (S/) | B35: 706
A36: Percepcion anterior (S/) | B36: 885
A37: IGV + IPM como % del CIF | B37: =(B34+B35)/(B32*B33) -> 0.17996862
A38: Percepcion como % del CIF | B38: =B36/(B32*B33) -> 0.031377508
A39: Arancel ad valorem (SUPUESTO) | B39: 0 | C39: El embarque anterior pago 0%. Confirmar la partida arancelaria del Cero y de los bidones con el agente antes de nacionalizar.
A41: Agente de aduana y transporte local - ESTIMADO (S/, sin IGV)
A42: Comision del agente | B42: 1500 | C42: Anterior: S/ 900 sobre CIF de US$ 8.2k; este CIF es ~5 veces mayor.
A43: Documentos de aduana | B43: 100 | C43: Igual que el embarque anterior.
A44: Regularizacion SADA | B44: 100 | C44: Igual que el embarque anterior.
A45: Camion de contenedor Chancay - San Borja | B45: 2000 | C45: Anterior: S/ 620 en carga LCL. Un 40HQ completo cuesta mas; pedir cotizacion.
A46: IGV del agente (S/) | B46: =SUM(B42:B45)*Supuestos!B4 -> 666
A48: Resultado del contenedor
A49: Tipo de cambio (S/ por US$) | B49: =Supuestos!B5 -> 3.5
A50: FOB total (US$) | B50: =D9 -> 31682
A51: Seguro nocional (US$) | B51: =D9*B29 -> 316.82
A52: CIF (US$) | B52: =B50+B25+B51 -> 39384.82
A53: CIF (S/) | B53: =B52*B49 -> 137846.87
A54: Arancel (S/) | B54: =B53*B39 -> 0
A55: IGV + IPM (S/) | B55: =(B53+B54)*B37 -> 24808.111
A56: Percepcion (S/) | B56: =B53*B38 -> 4325.2912
A57: Impuestos de aduana (S/) | B57: =SUM(B54:B56) -> 29133.402
A58: Proveedores (S/) | B58: =B50*B49 -> 110887
A59: Flete collect (S/) | B59: =B25*B49 -> 25851
A60: Visto bueno + SAC con IGV (S/) | B60: =(B26+B27)*(1+Supuestos!B4)*B49 -> 826
A61: Otros gastos locales (S/) | B61: =B28*B49 -> 2121.735
A62: Agente con IGV (S/) | B62: =SUM(B42:B45)+B46 -> 4366
A63: TOTAL DESEMBOLSADO (S/) | B63: =B58+B59+B60+B61+B57+B62 -> 173185.14
A64: IGV recuperable (S/) | B64: =Costo_Lima!B19*(B55+B56+B46+(B60-B60/(1+Supuestos!B4))+(B61-B61/(1+Supuestos!B4))) -> 30249.057
A65: COSTO REAL PUESTO EN LIMA (S/) | B65: =B63-B64 -> 142936.08
A66: Costo real (US$) | B66: =B65/B49 -> 40838.88
A67: Pendiente de pagar: todo menos proveedores (S/) | B67: =B59+B60+B61+B57+B62 -> 62298.137 | C67: Se asume que los dos proveedores ya estan pagados. Flete collect y visto bueno se pagan antes de retirar el contenedor.
A69: Costo unitario puesto en Lima
A70: Producto | B70: Unidades | C70: Costo neto asignado (S/) | D70: COSTO UNITARIO neto de IGV recuperable (S/) | E70: Costo unitario si NO recuperas IGV (S/) | F70: Costo unitario que se usa (S/)
A71: =A5 -> Bidon purificador 22 L | B71: =B5 -> 804 | C71: =D5*$B$49+($B$59+$B$60/(1+Supuestos!$B$4)+$B$61/(1+Supuestos!$B$4)+SUM($B$42:$B$45))*F5+$B$54*G5 -> 38229.357 | D71: =C71/B71 -> 47.548951 | E71: =(C71+(($B$55+$B$56)*G5)+($B$46+($B$60-$B$60/(1+Supuestos!$B$4))+($B$61-$B$61/(1+Supuestos!$B$4)))*F5)/B71 -> 56.7825 | F71: =IF(Costo_Lima!$B$19=1,D71,E71) -> 47.548951
A72: =A6 -> Bidon purificador 16 L | B72: =B6 -> 804 | C72: =D6*$B$49+($B$59+$B$60/(1+Supuestos!$B$4)+$B$61/(1+Supuestos!$B$4)+SUM($B$42:$B$45))*F6+$B$54*G6 -> 32032.64 | D72: =C72/B72 -> 39.841592 | E72: =(C72+(($B$55+$B$56)*G6)+($B$46+($B$60-$B$60/(1+Supuestos!$B$4))+($B$61-$B$61/(1+Supuestos!$B$4)))*F6)/B72 -> 46.812543 | F72: =IF(Costo_Lima!$B$19=1,D72,E72) -> 39.841592
A73: =A7 -> Kit de filtros 3 en 1 | B73: =B7 -> 840 | C73: =D7*$B$49+($B$59+$B$60/(1+Supuestos!$B$4)+$B$61/(1+Supuestos!$B$4)+SUM($B$42:$B$45))*F7+$B$54*G7 -> 9161.7766 | D73: =C73/B73 -> 10.906877 | E73: =(C73+(($B$55+$B$56)*G7)+($B$46+($B$60-$B$60/(1+Supuestos!$B$4))+($B$61-$B$61/(1+Supuestos!$B$4)))*F7)/B73 -> 12.961764 | F73: =IF(Costo_Lima!$B$19=1,D73,E73) -> 10.906877
A74: =A8 -> elvo· Cero R260 (100 maquinas + 20 filtros + entrega a Ningbo) | B74: =B8 -> 100 | C74: =D8*$B$49+($B$59+$B$60/(1+Supuestos!$B$4)+$B$61/(1+Supuestos!$B$4)+SUM($B$42:$B$45))*F8+$B$54*G8 -> 63512.307 | D74: =C74/B74 -> 635.12307 | E74: =(C74+(($B$55+$B$56)*G8)+($B$46+($B$60-$B$60/(1+Supuestos!$B$4))+($B$61-$B$61/(1+Supuestos!$B$4)))*F8)/B74 -> 790.0684 | F74: =IF(Costo_Lima!$B$19=1,D74,E74) -> 635.12307
A75: Total | C75: =SUM(C71:C74) -> 142936.08 | D75: =C75-B65 -> 0 | E75: control: debe ser 0
A76: Reparto: mercaderia directa; flete, gastos locales y agente por volumen (CBM); arancel e impuestos por valor.
A78: Margen por pedido en Lima (S/) con precios RECOMENDADOS - courier de bultos grandes probablemente mayor
A79: Concepto | B79: Bidon 22 L | C79: Bidon 16 L | D79: Kit 3 en 1 | E79: elvo· Cero
A80: Precio de venta (con IGV) - recomendado | B80: 219 | C80: 159 | D80: 85 | E80: 2299
A81: Venta neta | B81: =B80/(1+Supuestos!$B$4) -> 185.59322 | C81: =C80/(1+Supuestos!$B$4) -> 134.74576 | D81: =D80/(1+Supuestos!$B$4) -> 72.033898 | E81: =E80/(1+Supuestos!$B$4) -> 1948.3051
A82: Costo unitario puesto en Lima | B82: =-F71 -> -47.548951 | C82: =-F72 -> -39.841592 | D82: =-F73 -> -10.906877 | E82: =-F74 -> -635.12307
A83: Comision de pago | B83: =-(B80*Supuestos!$B$31+Supuestos!$B$32) -> -7.10723 | C83: =-(C80*Supuestos!$B$31+Supuestos!$B$32) -> -5.29703 | D83: =-(D80*Supuestos!$B$31+Supuestos!$B$32) -> -3.06445 | E83: =-(E80*Supuestos!$B$31+Supuestos!$B$32) -> -69.86083
A84: Empaque | B84: =-Supuestos!$B$16 -> -3.5 | C84: =-Supuestos!$B$16 -> -3.5 | D84: =-Supuestos!$B$16 -> -3.5 | E84: =-Supuestos!$B$16 -> -3.5
A85: Courier | B85: =-Supuestos!$B$18 -> -12.5 | C85: =-Supuestos!$B$18 -> -12.5 | D85: =-Supuestos!$B$18 -> -12.5 | E85: =-Supuestos!$B$18 -> -12.5
A86: Provision de garantia | B86: =-B80*B94 -> 0 | C86: =-C80*C94 -> 0 | D86: =-D80*D94 -> 0 | E86: =-E80*E94 -> -91.96
A87: Margen si se entrega | B87: =SUM(B81:B86) -> 114.93704 | C87: =SUM(C81:C86) -> 73.607141 | D87: =SUM(D81:D86) -> 42.062571 | E87: =SUM(E81:E86) -> 1135.3612
A88: Entregas fallidas | B88: =-(1-Supuestos!$B$7)*(B81+B82+B83+B86) -> -26.187408 | C88: =-(1-Supuestos!$B$7)*(C81+C82+C83+C86) -> -17.921428 | D88: =-(1-Supuestos!$B$7)*(D81+D82+D83+D86) -> -11.612514 | E88: =-(1-Supuestos!$B$7)*(E81+E82+E83+E86) -> -230.27224
A89: Utilidad antes de publicidad | B89: =B87+B88 -> 88.749631 | C89: =C87+C88 -> 55.685713 | D89: =D87+D88 -> 30.450057 | E89: =E87+E88 -> 905.08895
A90: Publicidad | B90: =-Supuestos!$B$6*B95 -> -32.5 | C90: =-Supuestos!$B$6*C95 -> -32.5 | D90: =-Supuestos!$B$6*D95 -> 0 | E90: =-Supuestos!$B$6*E95 -> -162.5
A91: Utilidad final | B91: =B89+B90 -> 56.249631 | C91: =C89+C90 -> 23.185713 | D91: =D89+D90 -> 30.450057 | E91: =E89+E90 -> 742.58895
A92: % del precio | B92: =B91/B80 -> 0.25684763 | C92: =C91/C80 -> 0.14582209 | D92: =D91/D80 -> 0.35823597 | E92: =E91/E80 -> 0.3230052
A94: Entrada: provision de garantia (% del precio) | B94: 0 | C94: 0 | D94: 0 | E94: 0.04
A95: Factor de CAC vs Nativo (0 = sin publicidad; viene de Plan_Supuestos) | B95: =Plan_Supuestos!K32 -> 0.5 | C95: =Plan_Supuestos!K33 -> 0.5 | D95: 0 | E95: =Plan_Supuestos!K34 -> 2.5
A97: Precios recomendados: bidon 22 L S/ 219, bidon 16 L S/ 159, kit S/ 85, Cero S/ 2,299. Referencias (Sodimac Peru, busqueda oct-2026): bidon mineralizador 16 L S/ 159.90 (lista S/ 249); repuestos de filtro S/ 72.90-84.90; osmosis inversa bajo mesada de 5 etapas en Falabella Peru S/ 1,090-1,499.
A98: Garantia del Cero: 12 meses; provision de 4% del precio (~S/ 92) como SUGERENCIA, sin dato historico propio. No incluye courier de bultos grandes.

Sheet Courier_Hub
A1: The Hub vs operacion actual - pedidos en Lima, todos contraentrega
A2: Azul = dato editable. Verde = viene de otra hoja. Fuentes: proforma The Hub 21-abr-2026, Anexo 3 de tarifas y respuestas de The Hub por WhatsApp (19-oct-2026). Sin IGV.
A4: Operacion actual (empaque + courier + almacen)
A5: Empaque Lima (S/) | B5: =Supuestos!B16 -> 3.5
A6: Courier Lima (S/) | B6: =Supuestos!B18 -> 12.5
A7: Almacen prorrateado por pedido (S/) | B7: =Supuestos!B38 -> 4
A8: Entrega efectiva actual en Lima | B8: =Supuestos!B7 -> 0.8
A10: The Hub (Business Standard) - condiciones confirmadas
A11: Gestion por orden (S/) | B11: 5.5 | C11: Proforma.
A12: Envio estandar Lima, tarifa ponderada hasta 3 kg (S/) | B12: 8.75 | C12: The Hub: la tarifa urbana subio a S/ 8.00; mixtos casi siempre urbano; periferico 9.50; periferico 2: 10.50. 8.75 = ponderacion ESTIMADA con una muestra de 9 pedidos.
A13: Kg adicional sobre 3 kg (S/) | B13: 1.5 | C13: Urbano 1.5, periferico 2.0. Peso facturable = largo x alto x ancho / 5000.
A14: Cobro contraentrega en efectivo o tarjeta (% del valor) | B14: 0.045 | C14: The Hub: 4.5% en efectivo o tarjeta; no lo bajan. Solo se cobra cuando cobran. El POS permite cuotas pero NO cuotas sin intereses.
A15: Cobro contraentrega en billeteras (Yape/Plin) | B15: 0.025 | C15: The Hub: pueden bajarlo a 2.5%.
A16: % de clientes que pagan con billetera al recibir | B16: 0.25 | C16: SUPUESTO ilustrativo. Reemplazar con datos reales.
A17: Retorno por pedido no entregado (S/) | B17: 1 | C17: Hay un reintento gratis; el retorno al almacen cuesta S/ 1. Reenviar vuelve a cobrar el envio.
A18: ¿El cobro de The Hub incluye la comision de tarjeta? (1 = si, 0 = no) | B18: 1 | C18: CONFIRMADO por The Hub: el 4.5% incluye la tarjeta.
A19: Almacen (US$ por m3 al mes) | B19: 20 | C19: Confirmado: es mensual.
A20: Meses que el stock permanece en The Hub | B20: 0.5 | C20: El resto queda en almacen propio y se envia por tandas.
A21: Entrega efectiva con The Hub en Lima | B21: 0.8 | C21: Igual a la actual para comparar costos. Cambiar para probar un alza (el reintento gratis podria subirla).
A22: Recepcion de mercaderia: costo por hora-hombre (S/) | B22: 114 | C22: The Hub: S/ 114 por hora-hombre.
... A25: Minimo de pedidos al mes (se paga el empaque faltante) | B25: 150 | C25: The Hub: si no se llega a 150, se paga el empaque que falta.
A26: Tipo de cambio | B26: =Supuestos!B5 -> 3.5
A27: Cobro contraentrega promedio (% del valor) | B27: =B14*(1-B16)+B15*B16 -> 0.04
A28: Gestion efectiva por pedido (S/), con el minimo | B28: =B11*MAX(B25,B24)/B24 -> 8.25
A30: Comparacion por pedido colocado en Lima (S/)
A31: Concepto | B31: Nativo 18 meses | C31: Nativo 3 años | D31: Nativo 6 años | E31: Bidon 22 L | F31: Bidon 16 L | G31: elvo· Cero
A32: Precio de venta (con IGV) | B32: =Desglose!B5 -> 299 | C32: =Desglose!C5 -> 349 | D32: =Desglose!D5 -> 399 | E32: =Contenedor2!B80 -> 219 | F32: =Contenedor2!C80 -> 159 | G32: =Contenedor2!E80 -> 2299
A33: Margen por pedido entregado, antes de logistica | B33: =Desglose!B14+Desglose!B15+Desglose!B16 -> 221.44909 | C33: =Desglose!C14+Desglose!C15+Desglose!C16 -> 259.79695 | D33: =Desglose!D14+Desglose!D15+Desglose!D16 -> 295.62829 | E33: =Contenedor2!B81+Contenedor2!B82+Contenedor2!B83+Contenedor2!B86 -> 130.93704 | F33: =Contenedor2!C81+Contenedor2!C82+Contenedor2!C83+Contenedor2!C86 -> 89.607141 | G33: =Contenedor2!E81+Contenedor2!E82+Contenedor2!E83+Contenedor2!E86 -> 1151.3612
A34: incluye comision de pago (S/, negativa) | B34: =Desglose!B16 -> -9.52083 | C34: =Desglose!C16 -> -11.02933 | D34: =Desglose!D16 -> -12.53783 | E34: =Contenedor2!B83 -> -7.10723 | F34: =Contenedor2!C83 -> -5.29703 | G34: =Contenedor2!E83 -> -69.86083
A35: Volumen por unidad (m3) | B35: 0.0077 | C35: 0.0077 | D35: 0.0077 | E35: 0.0242 | F35: 0.0259 | G35: 0.0875
A36: Peso facturable (kg) | B36: 1.5 | C36: 1.5 | D36: 2 | E36: 4.84 | F36: 5.18 | G36: 17.5
A37: Unidades por carton | B37: 12 | C37: 12 | D37: 12 | E37: 6 | F37: 6 | G37: 1
A38: ACTUAL: logistica por pedido colocado | B38: =$B$5+$B$6+$B$7 -> 20 | C38: =$B$5+$B$6+$B$7 -> 20 | D38: =$B$5+$B$6+$B$7 -> 20 | E38: =$B$5+$B$6+$B$7 -> 20 | F38: =$B$5+$B$6+$B$7 -> 20 | G38: =$B$5+$B$6+$B$7 -> 20
A39: ACTUAL: utilidad antes de publicidad | B39: =$B$8*B33-B38 -> 157.15927 | C39: =$B$8*C33-C38 -> 187.83756 | D39: =$B$8*D33-D38 -> 216.50263 | E39: =$B$8*E33-E38 -> 84.749631 | F39: =$B$8*F33-F38 -> 51.685713 | G39: =$B$8*G33-G38 -> 901.08895
A40: HUB: gestion (con minimo) + envio | B40: =$B$28+$B$12+MAX(0,B36-3)*$B$13 -> 17 | C40: =$B$28+$B$12+MAX(0,C36-3)*$B$13 -> 17 | D40: =$B$28+$B$12+MAX(0,D36-3)*$B$13 -> 17 | E40: =$B$28+$B$12+MAX(0,E36-3)*$B$13 -> 19.76 | F40: =$B$28+$B$12+MAX(0,F36-3)*$B$13 -> 20.27 | G40: =$B$28+$B$12+MAX(0,G36-3)*$B$13 -> 38.75
A41: HUB: cobro contraentrega esperado | B41: =$B$27*B32*$B$21 -> 9.568 | C41: =$B$27*C32*$B$21 -> 11.168 | D41: =$B$27*D32*$B$21 -> 12.768 | E41: =$B$27*E32*$B$21 -> 7.008 | F41: =$B$27*F32*$B$21 -> 5.088 | G41: =$B$27*G32*$B$21 -> 73.568
A42: HUB: retorno de no entregados | B42: =(1-$B$21)*$B$17 -> 0.2 | C42: =(1-$B$21)*$B$17 -> 0.2 | D42: =(1-$B$21)*$B$17 -> 0.2 | E42: =(1-$B$21)*$B$17 -> 0.2 | F42: =(1-$B$21)*$B$17 -> 0.2 | G42: =(1-$B$21)*$B$17 -> 0.2
A43: HUB: almacen | B43: =B35*$B$19*$B$26*$B$20 -> 0.2695 | C43: =C35*$B$19*$B$26*$B$20 -> 0.2695 | D43: =D35*$B$19*$B$26*$B$20 -> 0.2695 | E43: =E35*$B$19*$B$26*$B$20 -> 0.847 | F43: =F35*$B$19*$B$26*$B$20 -> 0.9065 | G43: =G35*$B$19*$B$26*$B$20 -> 3.0625
A44: HUB: recepcion de mercaderia por unidad | B44: =$B$22/($B$23*B37) -> 0.31666667 | C44: =$B$22/($B$23*C37) -> 0.31666667 | D44: =$B$22/($B$23*D37) -> 0.31666667 | E44: =$B$22/($B$23*E37) -> 0.63333333 | F44: =$B$22/($B$23*F37) -> 0.63333333 | G44: =$B$22/($B$23*G37) -> 3.8
A45: HUB: transporte de tu almacen a The Hub por pedido | B45: =Stock_Hub!$B$28/Stock_Hub!$B$31 -> 2.1428571 | C45: =Stock_Hub!$B$28/Stock_Hub!$B$31 -> 2.1428571 | D45: =Stock_Hub!$B$28/Stock_Hub!$B$31 -> 2.1428571 | E45: =Stock_Hub!$B$28/Stock_Hub!$B$31 -> 2.1428571 | F45: =Stock_Hub!$B$28/Stock_Hub!$B$31 -> 2.1428571 | G45: =Stock_Hub!$B$28/Stock_Hub!$B$31 -> 2.1428571
A46: HUB: logistica por pedido colocado | B46: =SUM(B40:B45) -> 29.497024 | C46: =SUM(C40:C45) -> 31.097024 | D46: =SUM(D40:D45) -> 32.697024 | E46: =SUM(E40:E45) -> 30.59119 | F46: =SUM(F40:F45) -> 29.24069 | G46: =SUM(G40:G45) -> 121.52336
A47: HUB: margen por pedido entregado (sin la comision de tarjeta, que incluye el cobro) | B47: =B33-$B$18*B34 -> 230.96992 | C47: =C33-$B$18*C34 -> 270.82628 | D47: =D33-$B$18*D34 -> 308.16612 | E47: =E33-$B$18*E34 -> 138.04427 | F47: =F33-$B$18*F34 -> 94.904171 | G47: =G33-$B$18*G34 -> 1221.222
A48: HUB: utilidad antes de publicidad | B48: =$B$21*B47-B46 -> 155.27891 | C48: =$B$21*C47-C46 -> 185.564 | D48: =$B$21*D47-D46 -> 213.83587 | E48: =$B$21*E47-E46 -> 79.844225 | F48: =$B$21*F47-F46 -> 46.682646 | G48: =$B$21*G47-G46 -> 855.45425
A49: Diferencia Hub - actual (utilidad por pedido) | B49: =B48-B39 -> -1.8803598 | C49: =C48-C39 -> -2.2735598 | D49: =D48-D39 -> -2.6667598 | E49: =E48-E39 -> -4.9054065 | F49: =F48-F39 -> -5.0030665 | G49: =G48-G39 -> -45.634693
A50: Alza de entrega que iguala (puntos) | B50: =IF(B49<0,-B49/B47,0) -> 0.0081411459 | C50: =IF(C49<0,-C49/C47,0) -> 0.008394901 | D50: =IF(D49<0,-D49/D47,0) -> 0.0086536437 | E50: =IF(E49<0,-E49/E47,0) -> 0.035535024 | F50: =IF(F49<0,-F49/F47,0) -> 0.052717035 | G50: =IF(G49<0,-G49/G47,0) -> 0.037368057
A51: Cobro contraentrega promedio que iguala (% del valor) | B51: =($B$21*B47-(B40+B42+B43+B44)-B39)/(B32*$B$21) -> 0.041097397 | C51: =($B$21*C47-(C40+C42+C43+C44)-C39)/(C32*$B$21) -> 0.039531867 | D51: =($B$21*D47-(D40+D42+D43+D44)-D39)/(D32*$B$21) -> 0.038358701 | E51: =($B$21*E47-(E40+E42+E43+E44)-E39)/(E32*$B$21) -> 0.024232024 | F51: =($B$21*F47-(F40+F42+F43+F44)-F39)/(F32*$B$21) -> 0.017514078 | G51: =($B$21*G47-(G40+G42+G43+G44)-G39)/(G32*$B$21) -> 0.016352851
A54: Sensibilidad: diferencia Hub - actual por pedido de Nativo 3 años segun pedidos al mes (por el minimo de 150)
A55: Pedidos al mes en The Hub | B55: 50 | C55: 75 | D55: 100 | E55: 150 | F55: 200 | G55: 300
A56: Diferencia por pedido (S/) | B56: =$C$49+($B$28-$B$11*MAX($B$25,B55)/B55) -> -10.52356 | C56: =$C$49+($B$28-$B$11*MAX($B$25,C55)/C55) -> -5.0235598 | D56: =$C$49+($B$28-$B$11*MAX($B$25,D55)/D55) -> -2.2735598 | E56: =$C$49+($B$28-$B$11*MAX($B$25,E55)/E55) -> 0.47644019 | F56: =$C$49+($B$28-$B$11*MAX($B$25,F55)/F55) -> 0.47644019 | G56: =$C$49+($B$28-$B$11*MAX($B$25,G55)/G55) -> 0.47644019
A58: Lectura: diferencia negativa = The Hub cuesta mas a igual tasa de entrega. "Alza de entrega" = puntos que debe mejorar para compensar. Ultima fila de la tabla = cobro contraentrega promedio con el que quedas igual.
A59: Condiciones de The Hub: el POS NO hace cuotas sin intereses; en provincia NO hay contraentrega (se maneja por agencias); el seguro en ruta es de S/ 300 por ruta y el del Cero depende de la agencia.
A60: No incluye: beneficio tributario de la factura de The Hub (IGV y gasto deducible) (el transporte desde tu almacen a The Hub viene de la hoja Stock_Hub). Para bidones y Cero el courier actual (S/ 12.5) es solo una referencia.

Sheet Courier_Dinsides
A1: Dinsides (almacen + despacho) vs operacion actual vs The Hub - Lima, contraentrega
A2: Fuente: brochure de fulfillment de Dinsides. El brochure NO trae tarifas de envio ni cobro por contraentrega: se usa el courier actual de S/ 10-15. Azul/amarillo = supuesto o dato pendiente.
A3: Condiciones de Dinsides
A4: Courier Lima por pedido (S/) | B4: =Supuestos!B18 -> 12.5 | C4: Dinsides al dia siguiente: S/ 10-15 (dato del usuario).
A5: Material de empaque por pedido (S/) | B5: 1.5 | C5: SUPUESTO: Dinsides exige que el cliente provea bolsas, cajas y film.
A6: Costo por pedido armado y no entregado (S/) | B6: 2 | C6: Brochure.
A7: Almacenaje y armado de pedidos (S/ por pedido) | B7: 0 | C7: Brochure: almacenaje sin costo adicional.
A8: Cobro contraentrega de Dinsides (% del valor) | B8: 0 | C8: PENDIENTE: el brochure no lo menciona. Confirmar efectivo, POS y cuotas.
A9: Entrega efectiva con Dinsides | B9: =Supuestos!B7 -> 0.8 | C9: Igual a la actual para comparar costos.
A10: Pedidos al mes en Lima | B10: =Courier_Hub!B24 -> 100 | C10: Viene de Courier_Hub.
A11: Entregas por semana | B11: =B10/4.33 -> 23.094688
A12: Minimo de entregas por semana | B12: 15 | C12: Brochure.
A13: Penalidad por no cumplir el minimo (S/ por dia) | B13: 2 | C13: Brochure. Se asume que se cobra todos los dias del mes si no se cumple.
A14: Penalidad por pedido (S/) | B14: =IF(B11<B12,B13*30,0)/B10 -> 0
A15: Kg adicional sobre 3 kg (S/) | B15: =Courier_Hub!B13 -> 1.5 | C15: SUPUESTO: igual que The Hub, por falta de tarifa de Dinsides para bultos grandes.
A17: Concepto | B17: Nativo 18 meses | C17: Nativo 3 años | D17: Nativo 6 años | E17: Bidon 22 L | F17: Bidon 16 L | G17: elvo· Cero
A18: Precio de venta (con IGV) | B18: =Courier_Hub!B32 -> 299 | C18: =Courier_Hub!C32 -> 349 | D18: =Courier_Hub!D32 -> 399 | E18: =Courier_Hub!E32 -> 219 | F18: =Courier_Hub!F32 -> 159 | G18: =Courier_Hub!G32 -> 2299
A19: Margen por pedido entregado, antes de logistica | B19: =Courier_Hub!B33 -> 221.44909 | C19: =Courier_Hub!C33 -> 259.79695 | D19: =Courier_Hub!D33 -> 295.62829 | E19: =Courier_Hub!E33 -> 130.93704 | F19: =Courier_Hub!F33 -> 89.607141 | G19: =Courier_Hub!G33 -> 1151.3612
A20: Peso facturable (kg) | B20: =Courier_Hub!B36 -> 1.5 | C20: =Courier_Hub!C36 -> 1.5 | D20: =Courier_Hub!D36 -> 2 | E20: =Courier_Hub!E36 -> 4.84 | F20: =Courier_Hub!F36 -> 5.18 | G20: =Courier_Hub!G36 -> 17.5
A21: ACTUAL (Tecretail + courier): utilidad antes de publicidad | B21: =Courier_Hub!B39 -> 157.15927 | C21: =Courier_Hub!C39 -> 187.83756 | D21: =Courier_Hub!D39 -> 216.50263 | E21: =Courier_Hub!E39 -> 84.749631 | F21: =Courier_Hub!F39 -> 51.685713 | G21: =Courier_Hub!G39 -> 901.08895
A22: DINSIDES: courier | B22: =$B$4+MAX(0,B20-3)*$B$15 -> 12.5 | C22: =$B$4+MAX(0,C20-3)*$B$15 -> 12.5 | D22: =$B$4+MAX(0,D20-3)*$B$15 -> 12.5 | E22: =$B$4+MAX(0,E20-3)*$B$15 -> 15.26 | F22: =$B$4+MAX(0,F20-3)*$B$15 -> 15.77 | G22: =$B$4+MAX(0,G20-3)*$B$15 -> 34.25
A23: DINSIDES: material de empaque | B23: =$B$5 -> 1.5 | C23: =$B$5 -> 1.5 | D23: =$B$5 -> 1.5 | E23: =$B$5 -> 1.5 | F23: =$B$5 -> 1.5 | G23: =$B$5 -> 1.5
A24: DINSIDES: pedidos armados y no entregados | B24: =(1-$B$9)*$B$6 -> 0.4 | C24: =(1-$B$9)*$B$6 -> 0.4 | D24: =(1-$B$9)*$B$6 -> 0.4 | E24: =(1-$B$9)*$B$6 -> 0.4 | F24: =(1-$B$9)*$B$6 -> 0.4 | G24: =(1-$B$9)*$B$6 -> 0.4
A25: DINSIDES: penalidad por el minimo semanal | B25: =$B$14 -> 0 | C25: =$B$14 -> 0 | D25: =$B$14 -> 0 | E25: =$B$14 -> 0 | F25: =$B$14 -> 0 | G25: =$B$14 -> 0
A26: DINSIDES: cobro contraentrega | B26: =$B$8*B18*$B$9 -> 0 | C26: =$B$8*C18*$B$9 -> 0 | D26: =$B$8*D18*$B$9 -> 0 | E26: =$B$8*E18*$B$9 -> 0 | F26: =$B$8*F18*$B$9 -> 0 | G26: =$B$8*G18*$B$9 -> 0
A27: DINSIDES: logistica por pedido colocado | B27: =SUM(B22:B26)+$B$7 -> 14.4 | C27: =SUM(C22:C26)+$B$7 -> 14.4 | D27: =SUM(D22:D26)+$B$7 -> 14.4 | E27: =SUM(E22:E26)+$B$7 -> 17.16 | F27: =SUM(F22:F26)+$B$7 -> 17.67 | G27: =SUM(G22:G26)+$B$7 -> 36.15
A28: DINSIDES: utilidad antes de publicidad | B28: =$B$9*B19-B27 -> 162.75927 | C28: =$B$9*C19-C27 -> 193.43756 | D28: =$B$9*D19-D27 -> 222.10263 | E28: =$B$9*E19-E27 -> 87.589631 | F28: =$B$9*F19-F27 -> 54.015713 | G28: =$B$9*G19-G27 -> 884.93895
A29: THE HUB: utilidad antes de publicidad | B29: =Courier_Hub!B48 -> 155.27891 | C29: =Courier_Hub!C48 -> 185.564 | D29: =Courier_Hub!D48 -> 213.83587 | E29: =Courier_Hub!E48 -> 79.844225 | F29: =Courier_Hub!F48 -> 46.682646 | G29: =Courier_Hub!G48 -> 855.45425
A30: Dinsides - actual (utilidad por pedido) | B30: =B28-B21 -> 5.6 | C30: =C28-C21 -> 5.6 | D30: =D28-D21 -> 5.6 | E30: =E28-E21 -> 2.84 | F30: =F28-F21 -> 2.33 | G30: =G28-G21 -> -16.15
A31: Dinsides - The Hub (utilidad por pedido) | B31: =B28-B29 -> 7.4803598 | C31: =C28-C29 -> 7.8735598 | D31: =D28-D29 -> 8.2667598 | E31: =E28-E29 -> 7.7454065 | F31: =F28-F29 -> 7.3330665 | G31: =G28-G29 -> 29.484693
A32: Puntos de entrega que The Hub debe ganar para igualar a Dinsides | B32: =IF(B31>0,B31/Courier_Hub!B47,0) -> 0.032386727 | C32: =IF(C31>0,C31/Courier_Hub!C47,0) -> 0.029072363 | D32: =IF(D31>0,D31/Courier_Hub!D47,0) -> 0.026825661 | E32: =IF(E31>0,E31/Courier_Hub!E47,0) -> 0.056108135 | F32: =IF(F31>0,F31/Courier_Hub!F47,0) -> 0.077268116 | G32: =IF(G31>0,G31/Courier_Hub!G47,0) -> 0.024143598
A34: Ahorro mensual de Dinsides segun volumen (Nativo 3 años, S/)
A35: Pedidos al mes en Lima | B35: 75 | C35: 100 | D35: 150 | E35: 300 | F35: 600 | G35: 1000
A36: Dinsides vs operacion actual (S/ al mes) | B36: =$C$30*B35 -> 420 | C36: =$C$30*C35 -> 560 | D36: =$C$30*D35 -> 840 | E36: =$C$30*E35 -> 1680 | F36: =$C$30*F35 -> 3360 | G36: =$C$30*G35 -> 5600
A37: Dinsides vs The Hub (S/ al mes) | B37: =$C$31*B35 -> 590.51699 | C37: =$C$31*C35 -> 787.35598 | D37: =$C$31*D35 -> 1181.034 | E37: =$C$31*E35 -> 2362.0679 | F37: =$C$31*F35 -> 4724.1359 | G37: =$C$31*G35 -> 7873.5598
A39: Lectura: el brochure incluye almacen, armado, rotulado, seguro por robo y perdida, control de inventario 3 veces por semana y punto de recojo en su almacen. No incluye materiales de empaque.
A40: El ahorro es de costo, no de entrega efectiva: si Dinsides entrega igual que hoy (80%), el ahorro es el de la fila 30. Por eso pedir su tasa de entrega por distrito antes de decidir.
A41: En el brochure los S/ 2.00 por pedido armado y no entregado reemplazan al costo de gestion; no hay cobro por almacenaje. Confirmar si ese cobro de S/ 2.00 es adicional al reintento o a la devolucion.

Sheet Stock_Hub
A1: Plan de stock en The Hub: tandas desde tu almacen propio
A2: Idea: dejar en The Hub solo lo que se vende en unas dos semanas y reponer por tandas. Azul = supuesto editable (la mezcla de pedidos es ilustrativa).
A4: Pedidos por dia en Lima que pasan por The Hub | B4: =Courier_Hub!B24/30 -> 3.3333333 | C4: Viene de Courier_Hub (pedidos al mes / 30). 150 pedidos al mes = minimo de The Hub.
A5: Dias de venta que cubre cada tanda | B5: 28 | C5: Tandas mensuales: el almacen es barato (US$ 20 por m3) y cada viaje tiene costo fijo.
A6: Dias de stock de seguridad en The Hub | B6: 3
A7: Horas minimas facturables por recepcion | B7: 1 | C7: SUPUESTO: se asume 1 hora como minimo.
A8: Transporte de tu almacen a The Hub, por tanda (S/) | B8: 200 | C8: SUPUESTO. El anexo de tarifas trae S/ 200 por pallet para envios a CD / reposicion; confirmar si es esto.
A9: Cartones descargados por hora-hombre | B9: =Courier_Hub!B23 -> 30
A10: Costo por hora-hombre (S/) | B10: =Courier_Hub!B22 -> 114
A11: Tipo de cambio | B11: =Supuestos!B5 -> 3.5
A12: Almacen (US$ por m3 al mes) | B12: =Courier_Hub!B19 -> 20
A14: Producto | B14: % de pedidos | C14: Unidades por tanda | D14: Unidades por carton | E14: Cartones por tanda | F14: m3 por unidad | G14: m3 ocupados
A15: Nativo | B15: 0.6 | C15: =$B$4*($B$5+$B$6)*B15 -> 62 | D15: 12 | E15: =C15/D15 -> 5.1666667 | F15: 0.0077 | G15: =C15*F15 -> 0.4774
A16: Vivo | B16: 0.1 | C16: =$B$4*($B$5+$B$6)*B16 -> 10.333333 | D16: 12 | E16: =C16/D16 -> 0.86111111 | F16: 0.0077 | G16: =C16*F16 -> 0.079566667
A17: Bidon 22 L | B17: 0.12 | C17: =$B$4*($B$5+$B$6)*B17 -> 12.4 | D17: 6 | E17: =C17/D17 -> 2.0666667 | F17: 0.0242 | G17: =C17*F17 -> 0.30008
A18: Bidon 16 L | B18: 0.1 | C18: =$B$4*($B$5+$B$6)*B18 -> 10.333333 | D18: 6 | E18: =C18/D18 -> 1.7222222 | F18: 0.0259 | G18: =C18*F18 -> 0.26763333
A19: elvo· Cero | B19: 0.03 | C19: =$B$4*($B$5+$B$6)*B19 -> 3.1 | D19: 1 | E19: =C19/D19 -> 3.1 | F19: 0.0875 | G19: =C19*F19 -> 0.27125
A20: Kit 3 en 1 | B20: 0.05 | C20: =$B$4*($B$5+$B$6)*B20 -> 5.1666667 | D20: 11.5 | E20: =C20/D20 -> 0.44927536 | F20: 0.006 | G20: =C20*F20 -> 0.031
A21: Total | B21: =SUM(B15:B20) -> 1 | C21: =SUM(C15:C20) -> 103.33333 | E21: =SUM(E15:E20) -> 13.365942 | G21: =SUM(G15:G20) -> 1.42693
A23: Costo mensual de tener stock en The Hub (S/)
A24: Horas de recepcion por tanda | B24: =MAX($B$7,E21/$B$9) -> 1
A25: Costo de recepcion por tanda | B25: =B24*$B$10 -> 114
A26: Tandas por mes | B26: =30/$B$5 -> 1.0714286
A27: Recepcion al mes | B27: =B25*B26 -> 122.14286
A28: Transporte al mes | B28: =$B$8*B26 -> 214.28571
A29: Almacen al mes (m3 ocupados al maximo) | B29: =G21*$B$12*$B$11 -> 99.8851
A30: Total almacen + recepcion + transporte | B30: =B27+B28+B29 -> 436.31367
A31: Pedidos al mes | B31: =B4*30 -> 100
A32: Gestion facturable al mes (con minimo) | B32: =Courier_Hub!B11*MAX(Courier_Hub!B25,B31) -> 825
A33: Costo por pedido en The Hub (sin envio ni cobro) | B33: =(B30+B32)/B31 -> 12.613137
A34: Costo por pedido actual (empaque + almacen Tecretail) | B34: =(Supuestos!B16*B31+Supuestos!B36)/B31 -> 7.5
A35: Diferencia por pedido (Hub - actual) | B35: =B33-B34 -> 5.1131367
A37: Estimacion por tanda: sirve para ver el orden de magnitud. Las horas de descarga son estimadas (30 cartones por hora-hombre); si mandas en pallets, bajan mucho. El costo por pedido actual usa el empaque y el almacen de Tecretail de la hoja Supuestos.

Sheet Costo_Lima
A1: Costo puesto en Lima - embarque Ningbo (llegada 22-abr-2026)
A2: Azul = dato de los documentos (proforma, factura Inca Lines, proforma aduana). Negro = formula. Tipo de cambio viene de la hoja Supuestos.
A4: Producto | B4: Cantidad | C4: FOB unitario (US$) | D4: FOB total (US$)
A5: Filtro de caño NW-TR201-W (carcasa + cartucho CTO-10B + grifo) | B5: 1008 | C5: 4.9 | D5: =B5*C5 -> 4939.2
A6: Repuesto de caño CTO-10B | B6: 1000 | C6: 0.55 | D6: =B6*C6 -> 550
A7: Filtro de ducha NW-BS2 | B7: 500 | C7: 3.55 | D7: =B7*C7 -> 1775
A8: Pallets | B8: 5 | C8: 15 | D8: =B8*C8 -> 75
A9: Flete maritimo Ningbo-Callao (prepaid) | B9: 1 | C9: 665 | D9: =B9*C9 -> 665
A10: Total proveedor (CFR Callao) | D10: =SUM(D5:D9) -> 8004.2
A11: Fuente: Proforma Invoice CXY251121 (Yuyao Yadong), 21-nov-2025.
A13: Otros gastos del embarque
A14: Inca Lines: total gastos de destino (US$, incl. CAF 250 + factura 885.87) | B14: 1135.87
A15: del cual IGV de la factura Inca Lines (US$) | B15: 135.13
A16: Agencia de aduana: comision + servicios, base sin IGV (S/) | B16: 1720
A17: Agencia de aduana: IGV sobre servicios (S/) | B17: 309.6
A18: Aduana: IGV + IPM + percepcion (S/); arancel 0% | B18: 5961
A19: Recuperas el IGV como credito fiscal? (1 = si, 0 = no) | B19: 1
A20: Tipo de cambio (S/ por US$) | B20: =Supuestos!B5 -> 3.5
A21: Fuentes: aviso de llegada y factura F002-55098 / recibo 001-0132613 (Inca Lines); proforma 026/0000257 (agencia de aduana). Falta: tarifa final de almacen Villas Oquendo (pendiente).
A23: Resultado
A24: Proveedor (S/) | B24: =D10*B20 -> 28014.7
A25: Inca Lines (S/) | B25: =B14*B20 -> 3975.545
A26: Agencia de aduana con IGV (S/) | B26: =B16+B17 -> 2029.6
A27: Impuestos de aduana (S/) | B27: =B18 -> 5961
A28: Total desembolsado (S/) | B28: =SUM(B24:B27) -> 39980.845
A29: Impuestos recuperables (S/) | B29: =B19*(B18+B17+B15*B20) -> 6743.555
A30: COSTO REAL PUESTO EN LIMA (S/) | B30: =B28-B29 -> 33237.29
A31: Costo real (US$) | B31: =B30/B20 -> 9496.3686
A33: Reparto de costos compartidos (flete, puerto, aduana) por valor FOB de cada producto
A34: Producto | B34: FOB (US$) | C34: % del FOB | D34: Costo asignado (S/) | E34: Unidades | F34: COSTO UNITARIO (S/)
A35: Filtro de caño | B35: =D5 -> 4939.2 | C35: =B35/SUM($B$35:$B$37) -> 0.67993723 | D35: =C35*$B$30 -> 22599.271 | E35: =B5 -> 1008 | F35: =D35/E35 -> 22.419911
A36: Repuesto de caño | B36: =D6 -> 550 | C36: =B36/SUM($B$35:$B$37) -> 0.075713774 | D36: =C36*$B$30 -> 2516.5207 | E36: =B6 -> 1000 | F36: =D36/E36 -> 2.5165207
A37: Filtro de ducha | B37: =D7 -> 1775 | C37: =B37/SUM($B$35:$B$37) -> 0.244349 | D37: =C37*$B$30 -> 8121.4985 | E37: =B7 -> 500 | F37: =D37/E37 -> 16.242997
A38: Total | B38: =SUM(B35:B37) -> 7264.2 | C38: =SUM(C35:C37) -> 1 | D38: =SUM(D35:D37) -> 33237.29
A39: Limitacion: no incluye PureCore/nucleo de magnesio (si vienen de otra compra), empaque final, comisiones bancarias ni almacen de puerto pendiente.
